Workbook
Name Slicer_Department: #N/A
Name Slicer_Gender: #N/A
Name Slicer_Location: #N/A

Sheet Cover
A1: Rewards & Benefits Analytics Dashboard
A2: McKinsey-style executive view using live formulas, pivots, and all employee records.
A4: CONTENTS | B4: DESCRIPTION
A5: Rewards Dashboard | B5: Interactive executive dashboard with filters, KPI cards, charts, benchmarking table, and narrative insights.
A6: Employee Data | B6: Source employee table used for the live dashboard calculations.
A7: Rewards & Benefits Allocation | B7: Existing pivot allocation view used as a validation source for premium and high-cost totals.
A8: Gender Pay Equity | B8: Existing gender pay pivot analysis referenced in the pay-gap visualization.
A9: Basic Analysis | B9: Existing pivot-table workbook analysis supporting the dashboard.
A10: Dashboard Data | B10: Hidden helper sheet with live formulas feeding dashboard charts.

Sheet Rewards Dashboard
A1: Rewards operations dashboard
A2: Interactive rewards, benefits, pay equity and benchmarking view — change filters to refresh KPIs, charts and table.
A3: Location | B3: All | C3: Gender | D3: All | E3: Department | F3: All | H3: Source: Demo Data created with 492 rows | J3: Source: Demo Data created with 492 rows
A5: Headcount | D5: Avg salary | G5: Total premium | J5: High-cost %
A6: =GETPIVOTDATA("[Measures].[Headcount]",'Rewards & Benefits Allocation'!$A$1) -> 492 | D6: =GETPIVOTDATA("[Measures].[Average Salary]",'Rewards & Benefits Allocation'!$A$1) -> 118675.04 | G6: =GETPIVOTDATA("[Measures].[Total Monthly Premium Cost]",'Rewards & Benefits Allocation'!$A$1) -> 2583000 | J6: =GETPIVOTDATA("[Measures].[High-Cost Employee %]",'Rewards & Benefits Allocation'!$A$1) -> 0.23373984
A10: AVG PREMIUM BY DEPARTMENT X LOCATION | H10: PLAN MIX BY TIER
A27: HEADCOUNT BY DEPARTMENT | H27: GENDER PAY GAP BY SALARY BAND
A44: BENCHMARKING SUBMISSION VIEW
A45: Department | B45: Location | C45: Avg salary | D45: Avg premium | E45: Headcount | F45: High-cost % | H45: Story in brief: High-cost employees are defined as employees with monthly premiums over ₹7,000. Under this threshold, high-premium benefit combinations are the main cost concentration. Use the filters above to isolate a city, gender, or department; every KPI, chart and benchmarking row recalculates from the employee-level source table.
A46: ='Helper Sheet'!H50 -> Finance | B46: ='Helper Sheet'!I50 -> Hyderabad | C46: ='Helper Sheet'!J50 -> 128885.24 | D46: ='Helper Sheet'!K50 -> 5944.8276 | E46: ='Helper Sheet'!L50 -> 29 | F46: ='Helper Sheet'!M50 -> 0.34482759
A47: ='Helper Sheet'!H51 -> Sales | B47: ='Helper Sheet'!I51 -> Gurugram | C47: ='Helper Sheet'!J51 -> 134835.56 | D47: ='Helper Sheet'!K51 -> 6062 | E47: ='Helper Sheet'!L51 -> 25 | F47: ='Helper Sheet'!M51 -> 0.32
A48: ='Helper Sheet'!H52 -> Operations | B48: ='Helper Sheet'!I52 -> Hyderabad | C48: ='Helper Sheet'!J52 -> 130724.81 | D48: ='Helper Sheet'!K52 -> 5475 | E48: ='Helper Sheet'!L52 -> 26 | F48: ='Helper Sheet'!M52 -> 0.30769231
A49: ='Helper Sheet'!H53 -> Sales | B49: ='Helper Sheet'!I53 -> Noida | C49: ='Helper Sheet'!J53 -> 110101.08 | D49: ='Helper Sheet'!K53 -> 5293.75 | E49: ='Helper Sheet'!L53 -> 24 | F49: ='Helper Sheet'!M53 -> 0.29166667
A50: ='Helper Sheet'!H54 -> HR | B50: ='Helper Sheet'!I54 -> Bengaluru | C50: ='Helper Sheet'!J54 -> 131595.95 | D50: ='Helper Sheet'!K54 -> 5489.4737 | E50: ='Helper Sheet'!L54 -> 19 | F50: ='Helper Sheet'!M54 -> 0.26315789
A51: ='Helper Sheet'!H55 -> Operations | B51: ='Helper Sheet'!I55 -> Gurugram | C51: ='Helper Sheet'!J55 -> 117910.11 | D51: ='Helper Sheet'!K55 -> 5490.7407 | E51: ='Helper Sheet'!L55 -> 27 | F51: ='Helper Sheet'!M55 -> 0.25925926
A56: RAW DATA TABLE
A57: Raw data table: the dashboard is powered by `Employee Data` rows with validated Location, Department, Gender, Insurance tier and Corporate Benefit Plan fields. The hidden `Dashboard Data` helper sheet holds live formulas that feed the charts; source records remain on the original data sheet.

Sheet Helper Sheet
A1: Locations | B1: Genders | C1: Departments | D1: Tiers | E1: Plans | F1: Salary Bands
A2: All | B2: All | C2: All | D2: Bronze | E2: Individual | F2: Junior
A3: Bengaluru | B3: Female | C3: Finance | D3: Silver | E3: Family Floater | F3: Mid
A4: Gurugram | B4: Male | C4: HR | D4: Gold | E4: Parents Included | F4: Senior
A5: Hyderabad | B5: Transgender | C5: Operations | F5: Lead
A6: Noida | C6: Sales
C7: Tech
A11: Department | B11: Bengaluru | C11: Gurugram | D11: Hyderabad | E11: Noida
A12: Finance | B12: =IF(OR('Rewards Dashboard'!$B$3="All",'Rewards Dashboard'!$B$3=B$11),IF(OR('Rewards Dashboard'!$F$3="All",'Rewards Dashboard'!$F$3=$A12),IFERROR(AVERAGEIFS('Employee Data'!$I$2:$I$493,'Employee Data'!$D$2:$D$493,$A12,'Employee Data'!$E$2:$E$493,B$11,'Employee Data'!$C$2:$C$493,IF('Rewards Dashboard'!$D$3="All","*",'Rewards Dashboard'!$D$3)),NA()),NA()),NA()) -> 4927.2727 | C12: =IF(OR('Rewards Dashboard'!$B$3="All",'Rewards Dashboard'!$B$3=C$11),IF(OR('Rewards Dashboard'!$F$3="All",'Rewards Dashboard'!$F$3=$A12),IFERROR(AVERAGEIFS('Employee Data'!$I$2:$I$493,'Employee Data'!$D$2:$D$493,$A12,'Employee Data'!$E$2:$E$493,C$11,'Employee Data'!$C$2:$C$493,IF('Rewards Dashboard'!$D$3="All","*",'Rewards Dashboard'!$D$3)),NA()),NA()),NA()) -> 5190.9091 | D12: =IF(OR('Rewards Dashboard'!$B$3="All",'Rewards Dashboard'!$B$3=D$11),IF(OR('Rewards Dashboard'!$F$3="All",'Rewards Dashboard'!$F$3=$A12),IFERROR(AVERAGEIFS('Employee Data'!$I$2:$I$493,'Employee Data'!$D$2:$D$493,$A12,'Employee Data'!$E$2:$E$493,D$11,'Employee Data'!$C$2:$C$493,IF('Rewards Dashboard'!$D$3="All","*",'Rewards Dashboard'!$D$3)),NA()),NA()),NA()) -> 5944.8276 | E12: =IF(OR('Rewards Dashboard'!$B$3="All",'Rewards Dashboard'!$B$3=E$11),IF(OR('Rewards Dashboard'!$F$3="All",'Rewards Dashboard'!$F$3=$A12),IFERROR(AVERAGEIFS('Employee Data'!$I$2:$I$493,'Employee Data'!$D$2:$D$493,$A12,'Employee Data'!$E$2:$E$493,E$11,'Employee Data'!$C$2:$C$493,IF('Rewards Dashboard'!$D$3="All","*",'Rewards Dashboard'!$D$3)),NA()),NA()),NA()) -> 5785.4167
A13: HR | B13: =IF(OR('Rewards Dashboard'!$B$3="All",'Rewards Dashboard'!$B$3=B$11),IF(OR('Rewards Dashboard'!$F$3="All",'Rewards Dashboard'!$F$3=$A13),IFERROR(AVERAGEIFS('Employee Data'!$I$2:$I$493,'Employee Data'!$D$2:$D$493,$A13,'Employee Data'!$E$2:$E$493,B$11,'Employee Data'!$C$2:$C$493,IF('Rewards Dashboard'!$D$3="All","*",'Rewards Dashboard'!$D$3)),NA()),NA()),NA()) -> 5489.4737 | C13: =IF(OR('Rewards Dashboard'!$B$3="All",'Rewards Dashboard'!$B$3=C$11),IF(OR('Rewards Dashboard'!$F$3="All",'Rewards Dashboard'!$F$3=$A13),IFERROR(AVERAGEIFS('Employee Data'!$I$2:$I$493,'Employee Data'!$D$2:$D$493,$A13,'Employee Data'!$E$2:$E$493,C$11,'Employee Data'!$C$2:$C$493,IF('Rewards Dashboard'!$D$3="All","*",'Rewards Dashboard'!$D$3)),NA()),NA()),NA()) -> 5064.2857 | D13: =IF(OR('Rewards Dashboard'!$B$3="All",'Rewards Dashboard'!$B$3=D$11),IF(OR('Rewards Dashboard'!$F$3="All",'Rewards Dashboard'!$F$3=$A13),IFERROR(AVERAGEIFS('Employee Data'!$I$2:$I$493,'Employee Data'!$D$2:$D$493,$A13,'Employee Data'!$E$2:$E$493,D$11,'Employee Data'!$C$2:$C$493,IF('Rewards Dashboard'!$D$3="All","*",'Rewards Dashboard'!$D$3)),NA()),NA()),NA()) -> 4819.2308 | E13: =IF(OR('Rewards Dashboard'!$B$3="All",'Rewards Dashboard'!$B$3=E$11),IF(OR('Rewards Dashboard'!$F$3="All",'Rewards Dashboard'!$F$3=$A13),IFERROR(AVERAGEIFS('Employee Data'!$I$2:$I$493,'Employee Data'!$D$2:$D$493,$A13,'Employee Data'!$E$2:$E$493,E$11,'Employee Data'!$C$2:$C$493,IF('Rewards Dashboard'!$D$3="All","*",'Rewards Dashboard'!$D$3)),NA()),NA()),NA()) -> 4577.2727
A14: Operations | B14: =IF(OR('Rewards Dashboard'!$B$3="All",'Rewards Dashboard'!$B$3=B$11),IF(OR('Rewards Dashboard'!$F$3="All",'Rewards Dashboard'!$F$3=$A14),IFERROR(AVERAGEIFS('Employee Data'!$I$2:$I$493,'Employee Data'!$D$2:$D$493,$A14,'Employee Data'!$E$2:$E$493,B$11,'Employee Data'!$C$2:$C$493,IF('Rewards Dashboard'!$D$3="All","*",'Rewards Dashboard'!$D$3)),NA()),NA()),NA()) -> 4192.1053 | C14: =IF(OR('Rewards Dashboard'!$B$3="All",'Rewards Dashboard'!$B$3=C$11),IF(OR('Rewards Dashboard'!$F$3="All",'Rewards Dashboard'!$F$3=$A14),IFERROR(AVERAGEIFS('Employee Data'!$I$2:$I$493,'Employee Data'!$D$2:$D$493,$A14,'Employee Data'!$E$2:$E$493,C$11,'Employee Data'!$C$2:$C$493,IF('Rewards Dashboard'!$D$3="All","*",'Rewards Dashboard'!$D$3)),NA()),NA()),NA()) -> 5490.7407 | D14: =IF(OR('Rewards Dashboard'!$B$3="All",'Rewards Dashboard'!$B$3=D$11),IF(OR('Rewards Dashboard'!$F$3="All",'Rewards Dashboard'!$F$3=$A14),IFERROR(AVERAGEIFS('Employee Data'!$I$2:$I$493,'Employee Data'!$D$2:$D$493,$A14,'Employee Data'!$E$2:$E$493,D$11,'Employee Data'!$C$2:$C$493,IF('Rewards Dashboard'!$D$3="All","*",'Rewards Dashboard'!$D$3)),NA()),NA()),NA()) -> 5475 | E14: =IF(OR('Rewards Dashboard'!$B$3="All",'Rewards Dashboard'!$B$3=E$11),IF(OR('Rewards Dashboard'!$F$3="All",'Rewards Dashboard'!$F$3=$A14),IFERROR(AVERAGEIFS('Employee Data'!$I$2:$I$493,'Employee Data'!$D$2:$D$493,$A14,'Employee Data'!$E$2:$E$493,E$11,'Employee Data'!$C$2:$C$493,IF('Rewards Dashboard'!$D$3="All","*",'Rewards Dashboard'!$D$3)),NA()),NA()),NA()) -> 5140
A15: Sales | B15: =IF(OR('Rewards Dashboard'!$B$3="All",'Rewards Dashboard'!$B$3=B$11),IF(OR('Rewards Dashboard'!$F$3="All",'Rewards Dashboard'!$F$3=$A15),IFERROR(AVERAGEIFS('Employee Data'!$I$2:$I$493,'Employee Data'!$D$2:$D$493,$A15,'Employee Data'!$E$2:$E$493,B$11,'Employee Data'!$C$2:$C$493,IF('Rewards Dashboard'!$D$3="All","*",'Rewards Dashboard'!$D$3)),NA()),NA()),NA()) -> 5430 | C15: =IF(OR('Rewards Dashboard'!$B$3="All",'Rewards Dashboard'!$B$3=C$11),IF(OR('Rewards Dashboard'!$F$3="All",'Rewards Dashboard'!$F$3=$A15),IFERROR(AVERAGEIFS('Employee Data'!$I$2:$I$493,'Employee Data'!$D$2:$D$493,$A15,'Employee Data'!$E$2:$E$493,C$11,'Employee Data'!$C$2:$C$493,IF('Rewards Dashboard'!$D$3="All","*",'Rewards Dashboard'!$D$3)),NA()),NA()),NA()) -> 6062 | D15: =IF(OR('Rewards Dashboard'!$B$3="All",'Rewards Dashboard'!$B$3=D$11),IF(OR('Rewards Dashboard'!$F$3="All",'Rewards Dashboard'!$F$3=$A15),IFERROR(AVERAGEIFS('Employee Data'!$I$2:$I$493,'Employee Data'!$D$2:$D$493,$A15,'Employee Data'!$E$2:$E$493,D$11,'Employee Data'!$C$2:$C$493,IF('Rewards Dashboard'!$D$3="All","*",'Rewards Dashboard'!$D$3)),NA()),NA()),NA()) -> 5268.5714 | E15: =IF(OR('Rewards Dashboard'!$B$3="All",'Rewards Dashboard'!$B$3=E$11),IF(OR('Rewards Dashboard'!$F$3="All",'Rewards Dashboard'!$F$3=$A15),IFERROR(AVERAGEIFS('Employee Data'!$I$2:$I$493,'Employee Data'!$D$2:$D$493,$A15,'Employee Data'!$E$2:$E$493,E$11,'Employee Data'!$C$2:$C$493,IF('Rewards Dashboard'!$D$3="All","*",'Rewards Dashboard'!$D$3)),NA()),NA()),NA()) -> 5293.75
A16: Tech | B16: =IF(OR('Rewards Dashboard'!$B$3="All",'Rewards Dashboard'!$B$3=B$11),IF(OR('Rewards Dashboard'!$F$3="All",'Rewards Dashboard'!$F$3=$A16),IFERROR(AVERAGEIFS('Employee Data'!$I$2:$I$493,'Employee Data'!$D$2:$D$493,$A16,'Employee Data'!$E$2:$E$493,B$11,'Employee Data'!$C$2:$C$493,IF('Rewards Dashboard'!$D$3="All","*",'Rewards Dashboard'!$D$3)),NA()),NA()),NA()) -> 5174 | C16: =IF(OR('Rewards Dashboard'!$B$3="All",'Rewards Dashboard'!$B$3=C$11),IF(OR('Rewards Dashboard'!$F$3="All",'Rewards Dashboard'!$F$3=$A16),IFERROR(AVERAGEIFS('Employee Data'!$I$2:$I$493,'Employee Data'!$D$2:$D$493,$A16,'Employee Data'!$E$2:$E$493,C$11,'Employee Data'!$C$2:$C$493,IF('Rewards Dashboard'!$D$3="All","*",'Rewards Dashboard'!$D$3)),NA()),NA()),NA()) -> 5066 | D16: =IF(OR('Rewards Dashboard'!$B$3="All",'Rewards Dashboard'!$B$3=D$11),IF(OR('Rewards Dashboard'!$F$3="All",'Rewards Dashboard'!$F$3=$A16),IFERROR(AVERAGEIFS('Employee Data'!$I$2:$I$493,'Employee Data'!$D$2:$D$493,$A16,'Employee Data'!$E$2:$E$493,D$11,'Employee Data'!$C$2:$C$493,IF('Rewards Dashboard'!$D$3="All","*",'Rewards Dashboard'!$D$3)),NA()),NA()),NA()) -> 4591.6667 | E16: =IF(OR('Rewards Dashboard'!$B$3="All",'Rewards Dashboard'!$B$3=E$11),IF(OR('Rewards Dashboard'!$F$3="All",'Rewards Dashboard'!$F$3=$A16),IFERROR(AVERAGEIFS('Employee Data'!$I$2:$I$493,'Employee Data'!$D$2:$D$493,$A16,'Employee Data'!$E$2:$E$493,E$11,'Employee Data'!$C$2:$C$493,IF('Rewards Dashboard'!$D$3="All","*",'Rewards Dashboard'!$D$3)),NA()),NA()),NA()) -> 5511.1111
A21: Insurance tier | B21: Headcount
A22: Bronze | B22: {=SUMPRODUCT(--('Employee Data'!$A$2:$A$493<>""),--(('Rewards Dashboard'!$B$3="All")+('Employee Data'!$E$2:$E$493='Rewards Dashboard'!$B$3)>0),--(('Rewards Dashboard'!$D$3="All")+('Employee Data'!$C$2:$C$493='Rewards Dashboard'!$D$3)>0),--(('Rewards Dashboard'!$F$3="All")+('Employee Data'!$D$2:$D$493='Rewards Dashboard'!$F$3)>0),--('Employee Data'!$H$2:$H$493=A22))} -> 59
A23: Silver | B23: {=SUMPRODUCT(--('Employee Data'!$A$2:$A$493<>""),--(('Rewards Dashboard'!$B$3="All")+('Employee Data'!$E$2:$E$493='Rewards Dashboard'!$B$3)>0),--(('Rewards Dashboard'!$D$3="All")+('Employee Data'!$C$2:$C$493='Rewards Dashboard'!$D$3)>0),--(('Rewards Dashboard'!$F$3="All")+('Employee Data'!$D$2:$D$493='Rewards Dashboard'!$F$3)>0),--('Employee Data'!$H$2:$H$493=A23))} -> 217
A24: Gold | B24: {=SUMPRODUCT(--('Employee Data'!$A$2:$A$493<>""),--(('Rewards Dashboard'!$B$3="All")+('Employee Data'!$E$2:$E$493='Rewards Dashboard'!$B$3)>0),--(('Rewards Dashboard'!$D$3="All")+('Employee Data'!$C$2:$C$493='Rewards Dashboard'!$D$3)>0),--(('Rewards Dashboard'!$F$3="All")+('Employee Data'!$D$2:$D$493='Rewards Dashboard'!$F$3)>0),--('Employee Data'!$H$2:$H$493=A24))} -> 216
A29: Department | B29: Headcount
A30: Finance | B30: {=IF(OR('Rewards Dashboard'!$F$3="All",'Rewards Dashboard'!$F$3=A30),SUMPRODUCT(--('Employee Data'!$A$2:$A$493<>""),--(('Rewards Dashboard'!$B$3="All")+('Employee Data'!$E$2:$E$493='Rewards Dashboard'!$B$3)>0),--(('Rewards Dashboard'!$D$3="All")+('Employee Data'!$C$2:$C$493='Rewards Dashboard'!$D$3)>0),--('Employee Data'!$D$2:$D$493=A30)),NA())} -> 97
A31: HR | B31: {=IF(OR('Rewards Dashboard'!$F$3="All",'Rewards Dashboard'!$F$3=A31),SUMPRODUCT(--('Employee Data'!$A$2:$A$493<>""),--(('Rewards Dashboard'!$B$3="All")+('Employee Data'!$E$2:$E$493='Rewards Dashboard'!$B$3)>0),--(('Rewards Dashboard'!$D$3="All")+('Employee Data'!$C$2:$C$493='Rewards Dashboard'!$D$3)>0),--('Employee Data'!$D$2:$D$493=A31)),NA())} -> 88
A32: Operations | B32: {=IF(OR('Rewards Dashboard'!$F$3="All",'Rewards Dashboard'!$F$3=A32),SUMPRODUCT(--('Employee Data'!$A$2:$A$493<>""),--(('Rewards Dashboard'!$B$3="All")+('Employee Data'!$E$2:$E$493='Rewards Dashboard'!$B$3)>0),--(('Rewards Dashboard'!$D$3="All")+('Employee Data'!$C$2:$C$493='Rewards Dashboard'!$D$3)>0),--('Employee Data'!$D$2:$D$493=A32)),NA())} -> 97
A33: Sales | B33: {=IF(OR('Rewards Dashboard'!$F$3="All",'Rewards Dashboard'!$F$3=A33),SUMPRODUCT(--('Employee Data'!$A$2:$A$493<>""),--(('Rewards Dashboard'!$B$3="All")+('Employee Data'!$E$2:$E$493='Rewards Dashboard'!$B$3)>0),--(('Rewards Dashboard'!$D$3="All")+('Employee Data'!$C$2:$C$493='Rewards Dashboard'!$D$3)>0),--('Employee Data'!$D$2:$D$493=A33)),NA())} -> 109
A34: Tech | B34: {=IF(OR('Rewards Dashboard'!$F$3="All",'Rewards Dashboard'!$F$3=A34),SUMPRODUCT(--('Employee Data'!$A$2:$A$493<>""),--(('Rewards Dashboard'!$B$3="All")+('Employee Data'!$E$2:$E$493='Rewards Dashboard'!$B$3)>0),--(('Rewards Dashboard'!$D$3="All")+('Employee Data'!$C$2:$C$493='Rewards Dashboard'!$D$3)>0),--('Employee Data'!$D$2:$D$493=A34)),NA())} -> 101
A39: Salary band | B39: Gap (M-F)
A40: ='Gender Pay Equity'!H12 -> Junior | B40: ='Gender Pay Equity'!K12 -> 2229.5479
A41: ='Gender Pay Equity'!H13 -> Lead | B41: ='Gender Pay Equity'!K13 -> -2672.5515
A42: ='Gender Pay Equity'!H14 -> Mid | B42: ='Gender Pay Equity'!K14 -> 2277.3732
A43: ='Gender Pay Equity'!H15 -> Senior | B43: ='Gender Pay Equity'!K15 -> 1553.5495
A49: Department | B49: Location | C49: Avg salary | D49: Avg premium | E49: Headcount | F49: High-cost % | H49: Department | I49: Location | J49: Avg salary | K49: Avg premium | L49: Headcount | M49: High-cost %
A50: Finance | B50: Bengaluru | C50: {=IFERROR(SUMPRODUCT('Employee Data'!$F$2:$F$493,--('Employee Data'!$A$2:$A$493<>""),--(('Rewards Dashboard'!$B$3="All")+('Employee Data'!$E$2:$E$493='Rewards Dashboard'!$B$3)>0),--(('Rewards Dashboard'!$D$3="All")+('Employee Data'!$C$2:$C$493='Rewards Dashboard'!$D$3)>0),--(('Rewards Dashboard'!$F$3="All")+('Employee Data'!$D$2:$D$493='Rewards Dashboard'!$F$3)>0),--('Employee Data'!$D$2:$D$493=A50),--('Employee Data'!$E$2:$E$493=B50))/SUMPRODUCT(--('Employee Data'!$A$2:$A$493<>""),--(('Rewards Dashboard'!$B$3="All")+('Employee Data'!$E$2:$E$493='Rewards Dashboard'!$B$3)>0),--(('Rewards Dashboard'!$D$3="All")+('Employee Data'!$C$2:$C$493='Rewards Dashboard'!$D$3)>0),--(('Rewards Dashboard'!$F$3="All")+('Employee Data'!$D$2:$D$493='Rewards Dashboard'!$F$3)>0),--('Employee Data'!$D$2:$D$493=A50),--('Employee Data'!$E$2:$E$493=B50)),0)} -> 115477.86 | D50: {=IFERROR(SUMPRODUCT('Employee Data'!$I$2:$I$493,--('Employee Data'!$A$2:$A$493<>""),--(('Rewards Dashboard'!$B$3="All")+('Employee Data'!$E$2:$E$493='Rewards Dashboard'!$B$3)>0),--(('Rewards Dashboard'!$D$3="All")+('Employee Data'!$C$2:$C$493='Rewards Dashboard'!$D$3)>0),--(('Rewards Dashboard'!$F$3="All")+('Employee Data'!$D$2:$D$493='Rewards Dashboard'!$F$3)>0),--('Employee Data'!$D$2:$D$493=A50),--('Employee Data'!$E$2:$E$493=B50))/SUMPRODUCT(--('Employee Data'!$A$2:$A$493<>""),--(('Rewards Dashboard'!$B$3="All")+('Employee Data'!$E$2:$E$493='Rewards Dashboard'!$B$3)>0),--(('Rewards Dashboard'!$D$3="All")+('Employee Data'!$C$2:$C$493='Rewards Dashboard'!$D$3)>0),--(('Rewards Dashboard'!$F$3="All")+('Employee Data'!$D$2:$D$493='Rewards Dashboard'!$F$3)>0),--('Employee Data'!$D$2:$D$493=A50),--('Employee Data'!$E$2:$E$493=B50)),0)} -> 4927.2727 | E50: {=SUMPRODUCT(--('Employee Data'!$A$2:$A$493<>""),--(('Rewards Dashboard'!$B$3="All")+('Employee Data'!$E$2:$E$493='Rewards Dashboard'!$B$3)>0),--(('Rewards Dashboard'!$D$3="All")+('Employee Data'!$C$2:$C$493='Rewards Dashboard'!$D$3)>0),--(('Rewards Dashboard'!$F$3="All")+('Employee Data'!$D$2:$D$493='Rewards Dashboard'!$F$3)>0),--('Employee Data'!$D$2:$D$493=A50),--('Employee Data'!$E$2:$E$493=B50))} -> 22 | F50: {=IFERROR(SUMPRODUCT(--('Employee Data'!$I$2:$I$493>7000),--('Employee Data'!$A$2:$A$493<>""),--(('Rewards Dashboard'!$B$3="All")+('Employee Data'!$E$2:$E$493='Rewards Dashboard'!$B$3)>0),--(('Rewards Dashboard'!$D$3="All")+('Employee Data'!$C$2:$C$493='Rewards Dashboard'!$D$3)>0),--(('Rewards Dashboard'!$F$3="All")+('Employee Data'!$D$2:$D$493='Rewards Dashboard'!$F$3)>0),--('Employee Data'!$D$2:$D$493=A50),--('Employee Data'!$E$2:$E$493=B50))/E50,0)} -> 0.18181818 | H50: {=_xlfn.TAKE(_xlfn.SORTBY(_xlfn._xlws.FILTER($A$50:$F$69,$E$50:$E$69>0),_xlfn._xlws.FILTER($F$50:$F$69,$E$50:$E$69>0),-1,_xlfn._xlws.FILTER($D$50:$D$69,$E$50:$E$69>0),-1),6)} -> Finance | I50: Hyderabad | J50: 128885.24 | K50: 5944.8276 | L50: 29 | M50: 0.34482759
A51: HR | B51: Bengaluru | C51: {=IFERROR(SUMPRODUCT('Employee Data'!$F$2:$F$493,--('Employee Data'!$A$2:$A$493<>""),--(('Rewards Dashboard'!$B$3="All")+('Employee Data'!$E$2:$E$493='Rewards Dashboard'!$B$3)>0),--(('Rewards Dashboard'!$D$3="All")+('Employee Data'!$C$2:$C$493='Rewards Dashboard'!$D$3)>0),--(('Rewards Dashboard'!$F$3="All")+('Employee Data'!$D$2:$D$493='Rewards Dashboard'!$F$3)>0),--('Employee Data'!$D$2:$D$493=A51),--('Employee Data'!$E$2:$E$493=B51))/SUMPRODUCT(--('Employee Data'!$A$2:$A$493<>""),--(('Rewards Dashboard'!$B$3="All")+('Employee Data'!$E$2:$E$493='Rewards Dashboard'!$B$3)>0),--(('Rewards Dashboard'!$D$3="All")+('Employee Data'!$C$2:$C$493='Rewards Dashboard'!$D$3)>0),--(('Rewards Dashboard'!$F$3="All")+('Employee Data'!$D$2:$D$493='Rewards Dashboard'!$F$3)>0),--('Employee Data'!$D$2:$D$493=A51),--('Employee Data'!$E$2:$E$493=B51)),0)} -> 131595.95 | D51: {=IFERROR(SUMPRODUCT('Employee Data'!$I$2:$I$493,--('Employee Data'!$A$2:$A$493<>""),--(('Rewards Dashboard'!$B$3="All")+('Employee Data'!$E$2:$E$493='Rewards Dashboard'!$B$3)>0),--(('Rewards Dashboard'!$D$3="All")+('Employee Data'!$C$2:$C$493='Rewards Dashboard'!$D$3)>0),--(('Rewards Dashboard'!$F$3="All")+('Employee Data'!$D$2:$D$493='Rewards Dashboard'!$F$3)>0),--('Employee Data'!$D$2:$D$493=A51),--('Employee Data'!$E$2:$E$493=B51))/SUMPRODUCT(--('Employee Data'!$A$2:$A$493<>""),--(('Rewards Dashboard'!$B$3="All")+('Employee Data'!$E$2:$E$493='Rewards Dashboard'!$B$3)>0),--(('Rewards Dashboard'!$D$3="All")+('Employee Data'!$C$2:$C$493='Rewards Dashboard'!$D$3)>0),--(('Rewards Dashboard'!$F$3="All")+('Employee Data'!$D$2:$D$493='Rewards Dashboard'!$F$3)>0),--('Employee Data'!$D$2:$D$493=A51),--('Employee Data'!$E$2:$E$493=B51)),0)} -> 5489.4737 | E51: {=SUMPRODUCT(--('Employee Data'!$A$2:$A$493<>""),--(('Rewards Dashboard'!$B$3="All")+('Employee Data'!$E$2:$E$493='Rewards Dashboard'!$B$3)>0),--(('Rewards Dashboard'!$D$3="All")+('Employee Data'!$C$2:$C$493='Rewards Dashboard'!$D$3)>0),--(('Rewards Dashboard'!$F$3="All")+('Employee Data'!$D$2:$D$493='Rewards Dashboard'!$F$3)>0),--('Employee Data'!$D$2:$D$493=A51),--('Employee Data'!$E$2:$E$493=B51))} -> 19 | F51: {=IFERROR(SUMPRODUCT(--('Employee Data'!$I$2:$I$493>7000),--('Employee Data'!$A$2:$A$493<>""),--(('Rewards Dashboard'!$B$3="All")+('Employee Data'!$E$2:$E$493='Rewards Dashboard'!$B$3)>0),--(('Rewards Dashboard'!$D$3="All")+('Employee Data'!$C$2:$C$493='Rewards Dashboard'!$D$3)>0),--(('Rewards Dashboard'!$F$3="All")+('Employee Data'!$D$2:$D$493='Rewards Dashboard'!$F$3)>0),--('Employee Data'!$D$2:$D$493=A51),--('Employee Data'!$E$2:$E$493=B51))/E51,0)} -> 0.26315789 | H51: Sales | I51: Gurugram | J51: 134835.56 | K51: 6062 | L51: 25 | M51: 0.32
A52: Operations | B52: Bengaluru | C52: {=IFERROR(SUMPRODUCT('Employee Data'!$F$2:$F$493,--('Employee Data'!$A$2:$A$493<>""),--(('Rewards Dashboard'!$B$3="All")+('Employee Data'!$E$2:$E$493='Rewards Dashboard'!$B$3)>0),--(('Rewards Dashboard'!$D$3="All")+('Employee Data'!$C$2:$C$493='Rewards Dashboard'!$D$3)>0),--(('Rewards Dashboard'!$F$3="All")+('Employee Data'!$D$2:$D$493='Rewards Dashboard'!$F$3)>0),--('Employee Data'!$D$2:$D$493=A52),--('Employee Data'!$E$2:$E$493=B52))/SUMPRODUCT(--('Employee Data'!$A$2:$A$493<>""),--(('Rewards Dashboard'!$B$3="All")+('Employee Data'!$E$2:$E$493='Rewards Dashboard'!$B$3)>0),--(('Rewards Dashboard'!$D$3="All")+('Employee Data'!$C$2:$C$493='Rewards Dashboard'!$D$3)>0),--(('Rewards Dashboard'!$F$3="All")+('Employee Data'!$D$2:$D$493='Rewards Dashboard'!$F$3)>0),--('Employee Data'!$D$2:$D$493=A52),--('Employee Data'!$E$2:$E$493=B52)),0)} -> 102408.47 | D52: {=IFERROR(SUMPRODUCT('Employee Data'!$I$2:$I$493,--('Employee Data'!$A$2:$A$493<>""),--(('Rewards Dashboard'!$B$3="All")+('Employee Data'!$E$2:$E$493='Rewards Dashboard'!$B$3)>0),--(('Rewards Dashboard'!$D$3="All")+('Employee Data'!$C$2:$C$493='Rewards Dashboard'!$D$3)>0),--(('Rewards Dashboard'!$F$3="All")+('Employee Data'!$D$2:$D$493='Rewards Dashboard'!$F$3)>0),--('Employee Data'!$D$2:$D$493=A52),--('Employee Data'!$E$2:$E$493=B52))/SUMPRODUCT(--('Employee Data'!$A$2:$A$493<>""),--(('Rewards Dashboard'!$B$3="All")+('Employee Data'!$E$2:$E$493='Rewards Dashboard'!$B$3)>0),--(('Rewards Dashboard'!$D$3="All")+('Employee Data'!$C$2:$C$493='Rewards Dashboard'!$D$3)>0),--(('Rewards Dashboard'!$F$3="All")+('Employee Data'!$D$2:$D$493='Rewards Dashboard'!$F$3)>0),--('Employee Data'!$D$2:$D$493=A52),--('Employee Data'!$E$2:$E$493=B52)),0)} -> 4192.1053 | E52: {=SUMPRODUCT(--('Employee Data'!$A$2:$A$493<>""),--(('Rewards Dashboard'!$B$3="All")+('Employee Data'!$E$2:$E$493='Rewards Dashboard'!$B$3)>0),--(('Rewards Dashboard'!$D$3="All")+('Employee Data'!$C$2:$C$493='Rewards Dashboard'!$D$3)>0),--(('Rewards Dashboard'!$F$3="All")+('Employee Data'!$D$2:$D$493='Rewards Dashboard'!$F$3)>0),--('Employee Data'!$D$2:$D$493=A52),--('Employee Data'!$E$2:$E$493=B52))} -> 19 | F52: {=IFERROR(SUMPRODUCT(--('Employee Data'!$I$2:$I$493>7000),--('Employee Data'!$A$2:$A$493<>""),--(('Rewards Dashboard'!$B$3="All")+('Employee Data'!$E$2:$E$493='Rewards Dashboard'!$B$3)>0),--(('Rewards Dashboard'!$D$3="All")+('Employee Data'!$C$2:$C$493='Rewards Dashboard'!$D$3)>0),--(('Rewards Dashboard'!$F$3="All")+('Employee Data'!$D$2:$D$493='Rewards Dashboard'!$F$3)>0),--('Employee Data'!$D$2:$D$493=A52),--('Employee Data'!$E$2:$E$493=B52))/E52,0)} -> 0.21052632 | H52: Operations | I52: Hyderabad | J52: 130724.81 | K52: 5475 | L52: 26 | M52: 0.30769231
A53: Sales | B53: Bengaluru | C53: {=IFERROR(SUMPRODUCT('Employee Data'!$F$2:$F$493,--('Employee Data'!$A$2:$A$493<>""),--(('Rewards Dashboard'!$B$3="All")+('Employee Data'!$E$2:$E$493='Rewards Dashboard'!$B$3)>0),--(('Rewards Dashboard'!$D$3="All")+('Employee Data'!$C$2:$C$493='Rewards Dashboard'!$D$3)>0),--(('Rewards Dashboard'!$F$3="All")+('Employee Data'!$D$2:$D$493='Rewards Dashboard'!$F$3)>0),--('Employee Data'!$D$2:$D$493=A53),--('Employee Data'!$E$2:$E$493=B53))/SUMPRODUCT(--('Employee Data'!$A$2:$A$493<>""),--(('Rewards Dashboard'!$B$3="All")+('Employee Data'!$E$2:$E$493='Rewards Dashboard'!$B$3)>0),--(('Rewards Dashboard'!$D$3="All")+('Employee Data'!$C$2:$C$493='Rewards Dashboard'!$D$3)>0),--(('Rewards Dashboard'!$F$3="All")+('Employee Data'!$D$2:$D$493='Rewards Dashboard'!$F$3)>0),--('Employee Data'!$D$2:$D$493=A53),--('Employee Data'!$E$2:$E$493=B53)),0)} -> 125256.52 | D53: {=IFERROR(SUMPRODUCT('Employee Data'!$I$2:$I$493,--('Employee Data'!$A$2:$A$493<>""),--(('Rewards Dashboard'!$B$3="All")+('Employee Data'!$E$2:$E$493='Rewards Dashboard'!$B$3)>0),--(('Rewards Dashboard'!$D$3="All")+('Employee Data'!$C$2:$C$493='Rewards Dashboard'!$D$3)>0),--(('Rewards Dashboard'!$F$3="All")+('Employee Data'!$D$2:$D$493='Rewards Dashboard'!$F$3)>0),--('Employee Data'!$D$2:$D$493=A53),--('Employee Data'!$E$2:$E$493=B53))/SUMPRODUCT(--('Employee Data'!$A$2:$A$493<>""),--(('Rewards Dashboard'!$B$3="All")+('Employee Data'!$E$2:$E$493='Rewards Dashboard'!$B$3)>0),--(('Rewards Dashboard'!$D$3="All")+('Employee Data'!$C$2:$C$493='Rewards Dashboard'!$D$3)>0),--(('Rewards Dashboard'!$F$3="All")+('Employee Data'!$D$2:$D$493='Rewards Dashboard'!$F$3)>0),--('Employee Data'!$D$2:$D$493=A53),--('Employee Data'!$E$2:$E$493=B53)),0)} -> 5430 | E53: {=SUMPRODUCT(--('Employee Data'!$A$2:$A$493<>""),--(('Rewards Dashboard'!$B$3="All")+('Employee Data'!$E$2:$E$493='Rewards Dashboard'!$B$3)>0),--(('Rewards Dashboard'!$D$3="All")+('Employee Data'!$C$2:$C$493='Rewards Dashboard'!$D$3)>0),--(('Rewards Dashboard'!$F$3="All")+('Employee Data'!$D$2:$D$493='Rewards Dashboard'!$F$3)>0),--('Employee Data'!$D$2:$D$493=A53),--('Employee Data'!$E$2:$E$493=B53))} -> 25 | F53: {=IFERROR(SUMPRODUCT(--('Employee Data'!$I$2:$I$493>7000),--('Employee Data'!$A$2:$A$493<>""),--(('Rewards Dashboard'!$B$3="All")+('Employee Data'!$E$2:$E$493='Rewards Dashboard'!$B$3)>0),--(('Rewards Dashboard'!$D$3="All")+('Employee Data'!$C$2:$C$493='Rewards Dashboard'!$D$3)>0),--(('Rewards Dashboard'!$F$3="All")+('Employee Data'!$D$2:$D$493='Rewards Dashboard'!$F$3)>0),--('Employee Data'!$D$2:$D$493=A53),--('Employee Data'!$E$2:$E$493=B53))/E53,0)} -> 0.2 | H53: Sales | I53: Noida | J53: 110101.08 | K53: 5293.75 | L53: 24 | M53: 0.29166667
A54: Tech | B54: Bengaluru | C54: {=IFERROR(SUMPRODUCT('Employee Data'!$F$2:$F$493,--('Employee Data'!$A$2:$A$493<>""),--(('Rewards Dashboard'!$B$3="All")+('Employee Data'!$E$2:$E$493='Rewards Dashboard'!$B$3)>0),--(('Rewards Dashboard'!$D$3="All")+('Employee Data'!$C$2:$C$493='Rewards Dashboard'!$D$3)>0),--(('Rewards Dashboard'!$F$3="All")+('Employee Data'!$D$2:$D$493='Rewards Dashboard'!$F$3)>0),--('Employee Data'!$D$2:$D$493=A54),--('Employee Data'!$E$2:$E$493=B54))/SUMPRODUCT(--('Employee Data'!$A$2:$A$493<>""),--(('Rewards Dashboard'!$B$3="All")+('Employee Data'!$E$2:$E$493='Rewards Dashboard'!$B$3)>0),--(('Rewards Dashboard'!$D$3="All")+('Employee Data'!$C$2:$C$493='Rewards Dashboard'!$D$3)>0),--(('Rewards Dashboard'!$F$3="All")+('Employee Data'!$D$2:$D$493='Rewards Dashboard'!$F$3)>0),--('Employee Data'!$D$2:$D$493=A54),--('Employee Data'!$E$2:$E$493=B54)),0)} -> 122661.32 | D54: {=IFERROR(SUMPRODUCT('Employee Data'!$I$2:$I$493,--('Employee Data'!$A$2:$A$493<>""),--(('Rewards Dashboard'!$B$3="All")+('Employee Data'!$E$2:$E$493='Rewards Dashboard'!$B$3)>0),--(('Rewards Dashboard'!$D$3="All")+('Employee Data'!$C$2:$C$493='Rewards Dashboard'!$D$3)>0),--(('Rewards Dashboard'!$F$3="All")+('Employee Data'!$D$2:$D$493='Rewards Dashboard'!$F$3)>0),--('Employee Data'!$D$2:$D$493=A54),--('Employee Data'!$E$2:$E$493=B54))/SUMPRODUCT(--('Employee Data'!$A$2:$A$493<>""),--(('Rewards Dashboard'!$B$3="All")+('Employee Data'!$E$2:$E$493='Rewards Dashboard'!$B$3)>0),--(('Rewards Dashboard'!$D$3="All")+('Employee Data'!$C$2:$C$493='Rewards Dashboard'!$D$3)>0),--(('Rewards Dashboard'!$F$3="All")+('Employee Data'!$D$2:$D$493='Rewards Dashboard'!$F$3)>0),--('Employee Data'!$D$2:$D$493=A54),--('Employee Data'!$E$2:$E$493=B54)),0)} -> 5174 | E54: {=SUMPRODUCT(--('Employee Data'!$A$2:$A$493<>""),--(('Rewards Dashboard'!$B$3="All")+('Employee Data'!$E$2:$E$493='Rewards Dashboard'!$B$3)>0),--(('Rewards Dashboard'!$D$3="All")+('Employee Data'!$C$2:$C$493='Rewards Dashboard'!$D$3)>0),--(('Rewards Dashboard'!$F$3="All")+('Employee Data'!$D$2:$D$493='Rewards Dashboard'!$F$3)>0),--('Employee Data'!$D$2:$D$493=A54),--('Employee Data'!$E$2:$E$493=B54))} -> 25 | F54: {=IFERROR(SUMPRODUCT(--('Employee Data'!$I$2:$I$493>7000),--('Employee Data'!$A$2:$A$493<>""),--(('Rewards Dashboard'!$B$3="All")+('Employee Data'!$E$2:$E$493='Rewards Dashboard'!$B$3)>0),--(('Rewards Dashboard'!$D$3="All")+('Employee Data'!$C$2:$C$493='Rewards Dashboard'!$D$3)>0),--(('Rewards Dashboard'!$F$3="All")+('Employee Data'!$D$2:$D$493='Rewards Dashboard'!$F$3)>0),--('Employee Data'!$D$2:$D$493=A54),--('Employee Data'!$E$2:$E$493=B54))/E54,0)} -> 0.16 | H54: HR | I54: Bengaluru | J54: 131595.95 | K54: 5489.4737 | L54: 19 | M54: 0.26315789
A55: Finance | B55: Gurugram | C55: {=IFERROR(SUMPRODUCT('Employee Data'!$F$2:$F$493,--('Employee Data'!$A$2:$A$493<>""),--(('Rewards Dashboard'!$B$3="All")+('Employee Data'!$E$2:$E$493='Rewards Dashboard'!$B$3)>0),--(('Rewards Dashboard'!$D$3="All")+('Employee Data'!$C$2:$C$493='Rewards Dashboard'!$D$3)>0),--(('Rewards Dashboard'!$F$3="All")+('Employee Data'!$D$2:$D$493='Rewards Dashboard'!$F$3)>0),--('Employee Data'!$D$2:$D$493=A55),--('Employee Data'!$E$2:$E$493=B55))/SUMPRODUCT(--('Employee Data'!$A$2:$A$493<>""),--(('Rewards Dashboard'!$B$3="All")+('Employee Data'!$E$2:$E$493='Rewards Dashboard'!$B$3)>0),--(('Rewards Dashboard'!$D$3="All")+('Employee Data'!$C$2:$C$493='Rewards Dashboard'!$D$3)>0),--(('Rewards Dashboard'!$F$3="All")+('Employee Data'!$D$2:$D$493='Rewards Dashboard'!$F$3)>0),--('Employee Data'!$D$2:$D$493=A55),--('Employee Data'!$E$2:$E$493=B55)),0)} -> 113401.59 | D55: {=IFERROR(SUMPRODUCT('Employee Data'!$I$2:$I$493,--('Employee Data'!$A$2:$A$493<>""),--(('Rewards Dashboard'!$B$3="All")+('Employee Data'!$E$2:$E$493='Rewards Dashboard'!$B$3)>0),--(('Rewards Dashboard'!$D$3="All")+('Employee Data'!$C$2:$C$493='Rewards Dashboard'!$D$3)>0),--(('Rewards Dashboard'!$F$3="All")+('Employee Data'!$D$2:$D$493='Rewards Dashboard'!$F$3)>0),--('Employee Data'!$D$2:$D$493=A55),--('Employee Data'!$E$2:$E$493=B55))/SUMPRODUCT(--('Employee Data'!$A$2:$A$493<>""),--(('Rewards Dashboard'!$B$3="All")+('Employee Data'!$E$2:$E$493='Rewards Dashboard'!$B$3)>0),--(('Rewards Dashboard'!$D$3="All")+('Employee Data'!$C$2:$C$493='Rewards Dashboard'!$D$3)>0),--(('Rewards Dashboard'!$F$3="All")+('Employee Data'!$D$2:$D$493='Rewards Dashboard'!$F$3)>0),--('Employee Data'!$D$2:$D$493=A55),--('Employee Data'!$E$2:$E$493=B55)),0)} -> 5190.9091 | E55: {=SUMPRODUCT(--('Employee Data'!$A$2:$A$493<>""),--(('Rewards Dashboard'!$B$3="All")+('Employee Data'!$E$2:$E$493='Rewards Dashboard'!$B$3)>0),--(('Rewards Dashboard'!$D$3="All")+('Employee Data'!$C$2:$C$493='Rewards Dashboard'!$D$3)>0),--(('Rewards Dashboard'!$F$3="All")+('Employee Data'!$D$2:$D$493='Rewards Dashboard'!$F$3)>0),--('Employee Data'!$D$2:$D$493=A55),--('Employee Data'!$E$2:$E$493=B55))} -> 22 | F55: {=IFERROR(SUMPRODUCT(--('Employee Data'!$I$2:$I$493>7000),--('Employee Data'!$A$2:$A$493<>""),--(('Rewards Dashboard'!$B$3="All")+('Employee Data'!$E$2:$E$493='Rewards Dashboard'!$B$3)>0),--(('Rewards Dashboard'!$D$3="All")+('Employee Data'!$C$2:$C$493='Rewards Dashboard'!$D$3)>0),--(('Rewards Dashboard'!$F$3="All")+('Employee Data'!$D$2:$D$493='Rewards Dashboard'!$F$3)>0),--('Employee Data'!$D$2:$D$493=A55),--('Employee Data'!$E$2:$E$493=B55))/E55,0)} -> 0.22727273 | H55: Operations | I55: Gurugram | J55: 117910.11 | K55: 5490.7407 | L55: 27 | M55: 0.25925926
A56: HR | B56: Gurugram | C56: {=IFERROR(SUMPRODUCT('Employee Data'!$F$2:$F$493,--('Employee Data'!$A$2:$A$493<>""),--(('Rewards Dashboard'!$B$3="All")+('Employee Data'!$E$2:$E$493='Rewards Dashboard'!$B$3)>0),--(('Rewards Dashboard'!$D$3="All")+('Employee Data'!$C$2:$C$493='Rewards Dashboard'!$D$3)>0),--(('Rewards Dashboard'!$F$3="All")+('Employee Data'!$D$2:$D$493='Rewards Dashboard'!$F$3)>0),--('Employee Data'!$D$2:$D$493=A56),--('Employee Data'!$E$2:$E$493=B56))/SUMPRODUCT(--('Employee Data'!$A$2:$A$493<>""),--(('Rewards Dashboard'!$B$3="All")+('Employee Data'!$E$2:$E$493='Rewards Dashboard'!$B$3)>0),--(('Rewards Dashboard'!$D$3="All")+('Employee Data'!$C$2:$C$493='Rewards Dashboard'!$D$3)>0),--(('Rewards Dashboard'!$F$3="All")+('Employee Data'!$D$2:$D$493='Rewards Dashboard'!$F$3)>0),--('Employee Data'!$D$2:$D$493=A56),--('Employee Data'!$E$2:$E$493=B56)),0)} -> 117717.62 | D56: {=IFERROR(SUMPRODUCT('Employee Data'!$I$2:$I$493,--('Employee Data'!$A$2:$A$493<>""),--(('Rewards Dashboard'!$B$3="All")+('Employee Data'!$E$2:$E$493='Rewards Dashboard'!$B$3)>0),--(('Rewards Dashboard'!$D$3="All")+('Employee Data'!$C$2:$C$493='Rewards Dashboard'!$D$3)>0),--(('Rewards Dashboard'!$F$3="All")+('Employee Data'!$D$2:$D$493='Rewards Dashboard'!$F$3)>0),--('Employee Data'!$D$2:$D$493=A56),--('Employee Data'!$E$2:$E$493=B56))/SUMPRODUCT(--('Employee Data'!$A$2:$A$493<>""),--(('Rewards Dashboard'!$B$3="All")+('Employee Data'!$E$2:$E$493='Rewards Dashboard'!$B$3)>0),--(('Rewards Dashboard'!$D$3="All")+('Employee Data'!$C$2:$C$493='Rewards Dashboard'!$D$3)>0),--(('Rewards Dashboard'!$F$3="All")+('Employee Data'!$D$2:$D$493='Rewards Dashboard'!$F$3)>0),--('Employee Data'!$D$2:$D$493=A56),--('Employee Data'!$E$2:$E$493=B56)),0)} -> 5064.2857 | E56: {=SUMPRODUCT(--('Employee Data'!$A$2:$A$493<>""),--(('Rewards Dashboard'!$B$3="All")+('Employee Data'!$E$2:$E$493='Rewards Dashboard'!$B$3)>0),--(('Rewards Dashboard'!$D$3="All")+('Employee Data'!$C$2:$C$493='Rewards Dashboard'!$D$3)>0),--(('Rewards Dashboard'!$F$3="All")+('Employee Data'!$D$2:$D$493='Rewards Dashboard'!$F$3)>0),--('Employee Data'!$D$2:$D$493=A56),--('Employee Data'!$E$2:$E$493=B56))} -> 21 | F56: {=IFERROR(SUMPRODUCT(--('Employee Data'!$I$2:$I$493>7000),--('Employee Data'!$A$2:$A$493<>""),--(('Rewards Dashboard'!$B$3="All")+('Employee Data'!$E$2:$E$493='Rewards Dashboard'!$B$3)>0),--(('Rewards Dashboard'!$D$3="All")+('Employee Data'!$C$2:$C$493='Rewards Dashboard'!$D$3)>0),--(('Rewards Dashboard'!$F$3="All")+('Employee Data'!$D$2:$D$493='Rewards Dashboard'!$F$3)>0),--('Employee Data'!$D$2:$D$493=A56),--('Employee Data'!$E$2:$E$493=B56))/E56,0)} -> 0.19047619
A57: Operations | B57: Gurugram | C57: {=IFERROR(SUMPRODUCT('Employee Data'!$F$2:$F$493,--('Employee Data'!$A$2:$A$493<>""),--(('Rewards Dashboard'!$B$3="All")+('Employee Data'!$E$2:$E$493='Rewards Dashboard'!$B$3)>0),--(('Rewards Dashboard'!$D$3="All")+('Employee Data'!$C$2:$C$493='Rewards Dashboard'!$D$3)>0),--(('Rewards Dashboard'!$F$3="All")+('Employee Data'!$D$2:$D$493='Rewards Dashboard'!$F$3)>0),--('Employee Data'!$D$2:$D$493=A57),--('Employee Data'!$E$2:$E$493=B57))/SUMPRODUCT(--('Employee Data'!$A$2:$A$493<>""),--(('Rewards Dashboard'!$B$3="All")+('Employee Data'!$E$2:$E$493='Rewards Dashboard'!$B$3)>0),--(('Rewards Dashboard'!$D$3="All")+('Employee Data'!$C$2:$C$493='Rewards Dashboard'!$D$3)>0),--(('Rewards Dashboard'!$F$3="All")+('Employee Data'!$D$2:$D$493='Rewards Dashboard'!$F$3)>0),--('Employee Data'!$D$2:$D$493=A57),--('Employee Data'!$E$2:$E$493=B57)),0)} -> 117910.11 | D57: {=IFERROR(SUMPRODUCT('Employee Data'!$I$2:$I$493,--('Employee Data'!$A$2:$A$493<>""),--(('Rewards Dashboard'!$B$3="All")+('Employee Data'!$E$2:$E$493='Rewards Dashboard'!$B$3)>0),--(('Rewards Dashboard'!$D$3="All")+('Employee Data'!$C$2:$C$493='Rewards Dashboard'!$D$3)>0),--(('Rewards Dashboard'!$F$3="All")+('Employee Data'!$D$2:$D$493='Rewards Dashboard'!$F$3)>0),--('Employee Data'!$D$2:$D$493=A57),--('Employee Data'!$E$2:$E$493=B57))/SUMPRODUCT(--('Employee Data'!$A$2:$A$493<>""),--(('Rewards Dashboard'!$B$3="All")+('Employee Data'!$E$2:$E$493='Rewards Dashboard'!$B$3)>0),--(('Rewards Dashboard'!$D$3="All")+('Employee Data'!$C$2:$C$493='Rewards Dashboard'!$D$3)>0),--(('Rewards Dashboard'!$F$3="All")+('Employee Data'!$D$2:$D$493='Rewards Dashboard'!$F$3)>0),--('Employee Data'!$D$2:$D$493=A57),--('Employee Data'!$E$2:$E$493=B57)),0)} -> 5490.7407 | E57: {=SUMPRODUCT(--('Employee Data'!$A$2:$A$493<>""),--(('Rewards Dashboard'!$B$3="All")+('Employee Data'!$E$2:$E$493='Rewards Dashboard'!$B$3)>0),--(('Rewards Dashboard'!$D$3="All")+('Employee Data'!$C$2:$C$493='Rewards Dashboard'!$D$3)>0),--(('Rewards Dashboard'!$F$3="All")+('Employee Data'!$D$2:$D$493='Rewards Dashboard'!$F$3)>0),--('Employee Data'!$D$2:$D$493=A57),--('Employee Data'!$E$2:$E$493=B57))} -> 27 | F57: {=IFERROR(SUMPRODUCT(--('Employee Data'!$I$2:$I$493>7000),--('Employee Data'!$A$2:$A$493<>""),--(('Rewards Dashboard'!$B$3="All")+('Employee Data'!$E$2:$E$493='Rewards Dashboard'!$B$3)>0),--(('Rewards Dashboard'!$D$3="All")+('Employee Data'!$C$2:$C$493='Rewards Dashboard'!$D$3)>0),--(('Rewards Dashboard'!$F$3="All")+('Employee Data'!$D$2:$D$493='Rewards Dashboard'!$F$3)>0),--('Employee Data'!$D$2:$D$493=A57),--('Employee Data'!$E$2:$E$493=B57))/E57,0)} -> 0.25925926
A58: Sales | B58: Gurugram | C58: {=IFERROR(SUMPRODUCT('Employee Data'!$F$2:$F$493,--('Employee Data'!$A$2:$A$493<>""),--(('Rewards Dashboard'!$B$3="All")+('Employee Data'!$E$2:$E$493='Rewards Dashboard'!$B$3)>0),--(('Rewards Dashboard'!$D$3="All")+('Employee Data'!$C$2:$C$493='Rewards Dashboard'!$D$3)>0),--(('Rewards Dashboard'!$F$3="All")+('Employee Data'!$D$2:$D$493='Rewards Dashboard'!$F$3)>0),--('Employee Data'!$D$2:$D$493=A58),--('Employee Data'!$E$2:$E$493=B58))/SUMPRODUCT(--('Employee Data'!$A$2:$A$493<>""),--(('Rewards Dashboard'!$B$3="All")+('Employee Data'!$E$2:$E$493='Rewards Dashboard'!$B$3)>0),--(('Rewards Dashboard'!$D$3="All")+('Employee Data'!$C$2:$C$493='Rewards Dashboard'!$D$3)>0),--(('Rewards Dashboard'!$F$3="All")+('Employee Data'!$D$2:$D$493='Rewards Dashboard'!$F$3)>0),--('Employee Data'!$D$2:$D$493=A58),--('Employee Data'!$E$2:$E$493=B58)),0)} -> 134835.56 | D58: {=IFERROR(SUMPRODUCT('Employee Data'!$I$2:$I$493,--('Employee Data'!$A$2:$A$493<>""),--(('Rewards Dashboard'!$B$3="All")+('Employee Data'!$E$2:$E$493='Rewards Dashboard'!$B$3)>0),--(('Rewards Dashboard'!$D$3="All")+('Employee Data'!$C$2:$C$493='Rewards Dashboard'!$D$3)>0),--(('Rewards Dashboard'!$F$3="All")+('Employee Data'!$D$2:$D$493='Rewards Dashboard'!$F$3)>0),--('Employee Data'!$D$2:$D$493=A58),--('Employee Data'!$E$2:$E$493=B58))/SUMPRODUCT(--('Employee Data'!$A$2:$A$493<>""),--(('Rewards Dashboard'!$B$3="All")+('Employee Data'!$E$2:$E$493='Rewards Dashboard'!$B$3)>0),--(('Rewards Dashboard'!$D$3="All")+('Employee Data'!$C$2:$C$493='Rewards Dashboard'!$D$3)>0),--(('Rewards Dashboard'!$F$3="All")+('Employee Data'!$D$2:$D$493='Rewards Dashboard'!$F$3)>0),--('Employee Data'!$D$2:$D$493=A58),--('Employee Data'!$E$2:$E$493=B58)),0)} -> 6062 | E58: {=SUMPRODUCT(--('Employee Data'!$A$2:$A$493<>""),--(('Rewards Dashboard'!$B$3="All")+('Employee Data'!$E$2:$E$493='Rewards Dashboard'!$B$3)>0),--(('Rewards Dashboard'!$D$3="All")+('Employee Data'!$C$2:$C$493='Rewards Dashboard'!$D$3)>0),--(('Rewards Dashboard'!$F$3="All")+('Employee Data'!$D$2:$D$493='Rewards Dashboard'!$F$3)>0),--('Employee Data'!$D$2:$D$493=A58),--('Employee Data'!$E$2:$E$493=B58))} -> 25 | F58: {=IFERROR(SUMPRODUCT(--('Employee Data'!$I$2:$I$493>7000),--('Employee Data'!$A$2:$A$493<>""),--(('Rewards Dashboard'!$B$3="All")+('Employee Data'!$E$2:$E$493='Rewards Dashboard'!$B$3)>0),--(('Rewards Dashboard'!$D$3="All")+('Employee Data'!$C$2:$C$493='Rewards Dashboard'!$D$3)>0),--(('Rewards Dashboard'!$F$3="All")+('Employee Data'!$D$2:$D$493='Rewards Dashboard'!$F$3)>0),--('Employee Data'!$D$2:$D$493=A58),--('Employee Data'!$E$2:$E$493=B58))/E58,0)} -> 0.32
A59: Tech | B59: Gurugram | C59: {=IFERROR(SUMPRODUCT('Employee Data'!$F$2:$F$493,--('Employee Data'!$A$2:$A$493<>""),--(('Rewards Dashboard'!$B$3="All")+('Employee Data'!$E$2:$E$493='Rewards Dashboard'!$B$3)>0),--(('Rewards Dashboard'!$D$3="All")+('Employee Data'!$C$2:$C$493='Rewards Dashboard'!$D$3)>0),--(('Rewards Dashboard'!$F$3="All")+('Employee Data'!$D$2:$D$493='Rewards Dashboard'!$F$3)>0),--('Employee Data'!$D$2:$D$493=A59),--('Employee Data'!$E$2:$E$493=B59))/SUMPRODUCT(--('Employee Data'!$A$2:$A$493<>""),--(('Rewards Dashboard'!$B$3="All")+('Employee Data'!$E$2:$E$493='Rewards Dashboard'!$B$3)>0),--(('Rewards Dashboard'!$D$3="All")+('Employee Data'!$C$2:$C$493='Rewards Dashboard'!$D$3)>0),--(('Rewards Dashboard'!$F$3="All")+('Employee Data'!$D$2:$D$493='Rewards Dashboard'!$F$3)>0),--('Employee Data'!$D$2:$D$493=A59),--('Employee Data'!$E$2:$E$493=B59)),0)} -> 113808.76 | D59: {=IFERROR(SUMPRODUCT('Employee Data'!$I$2:$I$493,--('Employee Data'!$A$2:$A$493<>""),--(('Rewards Dashboard'!$B$3="All")+('Employee Data'!$E$2:$E$493='Rewards Dashboard'!$B$3)>0),--(('Rewards Dashboard'!$D$3="All")+('Employee Data'!$C$2:$C$493='Rewards Dashboard'!$D$3)>0),--(('Rewards Dashboard'!$F$3="All")+('Employee Data'!$D$2:$D$493='Rewards Dashboard'!$F$3)>0),--('Employee Data'!$D$2:$D$493=A59),--('Employee Data'!$E$2:$E$493=B59))/SUMPRODUCT(--('Employee Data'!$A$2:$A$493<>""),--(('Rewards Dashboard'!$B$3="All")+('Employee Data'!$E$2:$E$493='Rewards Dashboard'!$B$3)>0),--(('Rewards Dashboard'!$D$3="All")+('Employee Data'!$C$2:$C$493='Rewards Dashboard'!$D$3)>0),--(('Rewards Dashboard'!$F$3="All")+('Employee Data'!$D$2:$D$493='Rewards Dashboard'!$F$3)>0),--('Employee Data'!$D$2:$D$493=A59),--('Employee Data'!$E$2:$E$493=B59)),0)} -> 5066 | E59: {=SUMPRODUCT(--('Employee Data'!$A$2:$A$493<>""),--(('Rewards Dashboard'!$B$3="All")+('Employee Data'!$E$2:$E$493='Rewards Dashboard'!$B$3)>0),--(('Rewards Dashboard'!$D$3="All")+('Employee Data'!$C$2:$C$493='Rewards Dashboard'!$D$3)>0),--(('Rewards Dashboard'!$F$3="All")+('Employee Data'!$D$2:$D$493='Rewards Dashboard'!$F$3)>0),--('Employee Data'!$D$2:$D$493=A59),--('Employee Data'!$E$2:$E$493=B59))} -> 25 | F59: {=IFERROR(SUMPRODUCT(--('Employee Data'!$I$2:$I$493>7000),--('Employee Data'!$A$2:$A$493<>""),--(('Rewards Dashboard'!$B$3="All")+('Employee Data'!$E$2:$E$493='Rewards Dashboard'!$B$3)>0),--(('Rewards Dashboard'!$D$3="All")+('Employee Data'!$C$2:$C$493='Rewards Dashboard'!$D$3)>0),--(('Rewards Dashboard'!$F$3="All")+('Employee Data'!$D$2:$D$493='Rewards Dashboard'!$F$3)>0),--('Employee Data'!$D$2:$D$493=A59),--('Employee Data'!$E$2:$E$493=B59))/E59,0)} -> 0.2
A60: Finance | B60: Hyderabad | C60: {=IFERROR(SUMPRODUCT('Employee Data'!$F$2:$F$493,--('Employee Data'!$A$2:$A$493<>""),--(('Rewards Dashboard'!$B$3="All")+('Employee Data'!$E$2:$E$493='Rewards Dashboard'!$B$3)>0),--(('Rewards Dashboard'!$D$3="All")+('Employee Data'!$C$2:$C$493='Rewards Dashboard'!$D$3)>0),--(('Rewards Dashboard'!$F$3="All")+('Employee Data'!$D$2:$D$493='Rewards Dashboard'!$F$3)>0),--('Employee Data'!$D$2:$D$493=A60),--('Employee Data'!$E$2:$E$493=B60))/SUMPRODUCT(--('Employee Data'!$A$2:$A$493<>""),--(('Rewards Dashboard'!$B$3="All")+('Employee Data'!$E$2:$E$493='Rewards Dashboard'!$B$3)>0),--(('Rewards Dashboard'!$D$3="All")+('Employee Data'!$C$2:$C$493='Rewards Dashboard'!$D$3)>0),--(('Rewards Dashboard'!$F$3="All")+('Employee Data'!$D$2:$D$493='Rewards Dashboard'!$F$3)>0),--('Employee Data'!$D$2:$D$493=A60),--('Employee Data'!$E$2:$E$493=B60)),0)} -> 128885.24 | D60: {=IFERROR(SUMPRODUCT('Employee Data'!$I$2:$I$493,--('Employee Data'!$A$2:$A$493<>""),--(('Rewards Dashboard'!$B$3="All")+('Employee Data'!$E$2:$E$493='Rewards Dashboard'!$B$3)>0),--(('Rewards Dashboard'!$D$3="All")+('Employee Data'!$C$2:$C$493='Rewards Dashboard'!$D$3)>0),--(('Rewards Dashboard'!$F$3="All")+('Employee Data'!$D$2:$D$493='Rewards Dashboard'!$F$3)>0),--('Employee Data'!$D$2:$D$493=A60),--('Employee Data'!$E$2:$E$493=B60))/SUMPRODUCT(--('Employee Data'!$A$2:$A$493<>""),--(('Rewards Dashboard'!$B$3="All")+('Employee Data'!$E$2:$E$493='Rewards Dashboard'!$B$3)>0),--(('Rewards Dashboard'!$D$3="All")+('Employee Data'!$C$2:$C$493='Rewards Dashboard'!$D$3)>0),--(('Rewards Dashboard'!$F$3="All")+('Employee Data'!$D$2:$D$493='Rewards Dashboard'!$F$3)>0),--('Employee Data'!$D$2:$D$493=A60),--('Employee Data'!$E$2:$E$493=B60)),0)} -> 5944.8276 | E60: {=SUMPRODUCT(--('Employee Data'!$A$2:$A$493<>""),--(('Rewards Dashboard'!$B$3="All")+('Employee Data'!$E$2:$E$493='Rewards Dashboard'!$B$3)>0),--(('Rewards Dashboard'!$D$3="All")+('Employee Data'!$C$2:$C$493='Rewards Dashboard'!$D$3)>0),--(('Rewards Dashboard'!$F$3="All")+('Employee Data'!$D$2:$D$493='Rewards Dashboard'!$F$3)>0),--('Employee Data'!$D$2:$D$493=A60),--('Employee Data'!$E$2:$E$493=B60))} -> 29 | F60: {=IFERROR(SUMPRODUCT(--('Employee Data'!$I$2:$I$493>7000),--('Employee Data'!$A$2:$A$493<>""),--(('Rewards Dashboard'!$B$3="All")+('Employee Data'!$E$2:$E$493='Rewards Dashboard'!$B$3)>0),--(('Rewards Dashboard'!$D$3="All")+('Employee Data'!$C$2:$C$493='Rewards Dashboard'!$D$3)>0),--(('Rewards Dashboard'!$F$3="All")+('Employee Data'!$D$2:$D$493='Rewards Dashboard'!$F$3)>0),--('Employee Data'!$D$2:$D$493=A60),--('Employee Data'!$E$2:$E$493=B60))/E60,0)} -> 0.34482759
A61: HR | B61: Hyderabad | C61: {=IFERROR(SUMPRODUCT('Employee Data'!$F$2:$F$493,--('Employee Data'!$A$2:$A$493<>""),--(('Rewards Dashboard'!$B$3="All")+('Employee Data'!$E$2:$E$493='Rewards Dashboard'!$B$3)>0),--(('Rewards Dashboard'!$D$3="All")+('Employee Data'!$C$2:$C$493='Rewards Dashboard'!$D$3)>0),--(('Rewards Dashboard'!$F$3="All")+('Employee Data'!$D$2:$D$493='Rewards Dashboard'!$F$3)>0),--('Employee Data'!$D$2:$D$493=A61),--('Employee Data'!$E$2:$E$493=B61))/SUMPRODUCT(--('Employee Data'!$A$2:$A$493<>""),--(('Rewards Dashboard'!$B$3="All")+('Employee Data'!$E$2:$E$493='Rewards Dashboard'!$B$3)>0),--(('Rewards Dashboard'!$D$3="All")+('Employee Data'!$C$2:$C$493='Rewards Dashboard'!$D$3)>0),--(('Rewards Dashboard'!$F$3="All")+('Employee Data'!$D$2:$D$493='Rewards Dashboard'!$F$3)>0),--('Employee Data'!$D$2:$D$493=A61),--('Employee Data'!$E$2:$E$493=B61)),0)} -> 116479.5 | D61: {=IFERROR(SUMPRODUCT('Employee Data'!$I$2:$I$493,--('Employee Data'!$A$2:$A$493<>""),--(('Rewards Dashboard'!$B$3="All")+('Employee Data'!$E$2:$E$493='Rewards Dashboard'!$B$3)>0),--(('Rewards Dashboard'!$D$3="All")+('Employee Data'!$C$2:$C$493='Rewards Dashboard'!$D$3)>0),--(('Rewards Dashboard'!$F$3="All")+('Employee Data'!$D$2:$D$493='Rewards Dashboard'!$F$3)>0),--('Employee Data'!$D$2:$D$493=A61),--('Employee Data'!$E$2:$E$493=B61))/SUMPRODUCT(--('Employee Data'!$A$2:$A$493<>""),--(('Rewards Dashboard'!$B$3="All")+('Employee Data'!$E$2:$E$493='Rewards Dashboard'!$B$3)>0),--(('Rewards Dashboard'!$D$3="All")+('Employee Data'!$C$2:$C$493='Rewards Dashboard'!$D$3)>0),--(('Rewards Dashboard'!$F$3="All")+('Employee Data'!$D$2:$D$493='Rewards Dashboard'!$F$3)>0),--('Employee Data'!$D$2:$D$493=A61),--('Employee Data'!$E$2:$E$493=B61)),0)} -> 4819.2308 | E61: {=SUMPRODUCT(--('Employee Data'!$A$2:$A$493<>""),--(('Rewards Dashboard'!$B$3="All")+('Employee Data'!$E$2:$E$493='Rewards Dashboard'!$B$3)>0),--(('Rewards Dashboard'!$D$3="All")+('Employee Data'!$C$2:$C$493='Rewards Dashboard'!$D$3)>0),--(('Rewards Dashboard'!$F$3="All")+('Employee Data'!$D$2:$D$493='Rewards Dashboard'!$F$3)>0),--('Employee Data'!$D$2:$D$493=A61),--('Employee Data'!$E$2:$E$493=B61))} -> 26 | F61: {=IFERROR(SUMPRODUCT(--('Employee Data'!$I$2:$I$493>7000),--('Employee Data'!$A$2:$A$493<>""),--(('Rewards Dashboard'!$B$3="All")+('Employee Data'!$E$2:$E$493='Rewards Dashboard'!$B$3)>0),--(('Rewards Dashboard'!$D$3="All")+('Employee Data'!$C$2:$C$493='Rewards Dashboard'!$D$3)>0),--(('Rewards Dashboard'!$F$3="All")+('Employee Data'!$D$2:$D$493='Rewards Dashboard'!$F$3)>0),--('Employee Data'!$D$2:$D$493=A61),--('Employee Data'!$E$2:$E$493=B61))/E61,0)} -> 0.19230769
A62: Operations | B62: Hyderabad | C62: {=IFERROR(SUMPRODUCT('Employee Data'!$F$2:$F$493,--('Employee Data'!$A$2:$A$493<>""),--(('Rewards Dashboard'!$B$3="All")+('Employee Data'!$E$2:$E$493='Rewards Dashboard'!$B$3)>0),--(('Rewards Dashboard'!$D$3="All")+('Employee Data'!$C$2:$C$493='Rewards Dashboard'!$D$3)>0),--(('Rewards Dashboard'!$F$3="All")+('Employee Data'!$D$2:$D$493='Rewards Dashboard'!$F$3)>0),--('Employee Data'!$D$2:$D$493=A62),--('Employee Data'!$E$2:$E$493=B62))/SUMPRODUCT(--('Employee Data'!$A$2:$A$493<>""),--(('Rewards Dashboard'!$B$3="All")+('Employee Data'!$E$2:$E$493='Rewards Dashboard'!$B$3)>0),--(('Rewards Dashboard'!$D$3="All")+('Employee Data'!$C$2:$C$493='Rewards Dashboard'!$D$3)>0),--(('Rewards Dashboard'!$F$3="All")+('Employee Data'!$D$2:$D$493='Rewards Dashboard'!$F$3)>0),--('Employee Data'!$D$2:$D$493=A62),--('Employee Data'!$E$2:$E$493=B62)),0)} -> 130724.81 | D62: {=IFERROR(SUMPRODUCT('Employee Data'!$I$2:$I$493,--('Employee Data'!$A$2:$A$493<>""),--(('Rewards Dashboard'!$B$3="All")+('Employee Data'!$E$2:$E$493='Rewards Dashboard'!$B$3)>0),--(('Rewards Dashboard'!$D$3="All")+('Employee Data'!$C$2:$C$493='Rewards Dashboard'!$D$3)>0),--(('Rewards Dashboard'!$F$3="All")+('Employee Data'!$D$2:$D$493='Rewards Dashboard'!$F$3)>0),--('Employee Data'!$D$2:$D$493=A62),--('Employee Data'!$E$2:$E$493=B62))/SUMPRODUCT(--('Employee Data'!$A$2:$A$493<>""),--(('Rewards Dashboard'!$B$3="All")+('Employee Data'!$E$2:$E$493='Rewards Dashboard'!$B$3)>0),--(('Rewards Dashboard'!$D$3="All")+('Employee Data'!$C$2:$C$493='Rewards Dashboard'!$D$3)>0),--(('Rewards Dashboard'!$F$3="All")+('Employee Data'!$D$2:$D$493='Rewards Dashboard'!$F$3)>0),--('Employee Data'!$D$2:$D$493=A62),--('Employee Data'!$E$2:$E$493=B62)),0)} -> 5475 | E62: {=SUMPRODUCT(--('Employee Data'!$A$2:$A$493<>""),--(('Rewards Dashboard'!$B$3="All")+('Employee Data'!$E$2:$E$493='Rewards Dashboard'!$B$3)>0),--(('Rewards Dashboard'!$D$3="All")+('Employee Data'!$C$2:$C$493='Rewards Dashboard'!$D$3)>0),--(('Rewards Dashboard'!$F$3="All")+('Employee Data'!$D$2:$D$493='Rewards Dashboard'!$F$3)>0),--('Employee Data'!$D$2:$D$493=A62),--('Employee Data'!$E$2:$E$493=B62))} -> 26 | F62: {=IFERROR(SUMPRODUCT(--('Employee Data'!$I$2:$I$493>7000),--('Employee Data'!$A$2:$A$493<>""),--(('Rewards Dashboard'!$B$3="All")+('Employee Data'!$E$2:$E$493='Rewards Dashboard'!$B$3)>0),--(('Rewards Dashboard'!$D$3="All")+('Employee Data'!$C$2:$C$493='Rewards Dashboard'!$D$3)>0),--(('Rewards Dashboard'!$F$3="All")+('Employee Data'!$D$2:$D$493='Rewards Dashboard'!$F$3)>0),--('Employee Data'!$D$2:$D$493=A62),--('Employee Data'!$E$2:$E$493=B62))/E62,0)} -> 0.30769231
A63: Sales | B63: Hyderabad | C63: {=IFERROR(SUMPRODUCT('Employee Data'!$F$2:$F$493,--('Employee Data'!$A$2:$A$493<>""),--(('Rewards Dashboard'!$B$3="All")+('Employee Data'!$E$2:$E$493='Rewards Dashboard'!$B$3)>0),--(('Rewards Dashboard'!$D$3="All")+('Employee Data'!$C$2:$C$493='Rewards Dashboard'!$D$3)>0),--(('Rewards Dashboard'!$F$3="All")+('Employee Data'!$D$2:$D$493='Rewards Dashboard'!$F$3)>0),--('Employee Data'!$D$2:$D$493=A63),--('Employee Data'!$E$2:$E$493=B63))/SUMPRODUCT(--('Employee Data'!$A$2:$A$493<>""),--(('Rewards Dashboard'!$B$3="All")+('Employee Data'!$E$2:$E$493='Rewards Dashboard'!$B$3)>0),--(('Rewards Dashboard'!$D$3="All")+('Employee Data'!$C$2:$C$493='Rewards Dashboard'!$D$3)>0),--(('Rewards Dashboard'!$F$3="All")+('Employee Data'!$D$2:$D$493='Rewards Dashboard'!$F$3)>0),--('Employee Data'!$D$2:$D$493=A63),--('Employee Data'!$E$2:$E$493=B63)),0)} -> 117752.26 | D63: {=IFERROR(SUMPRODUCT('Employee Data'!$I$2:$I$493,--('Employee Data'!$A$2:$A$493<>""),--(('Rewards Dashboard'!$B$3="All")+('Employee Data'!$E$2:$E$493='Rewards Dashboard'!$B$3)>0),--(('Rewards Dashboard'!$D$3="All")+('Employee Data'!$C$2:$C$493='Rewards Dashboard'!$D$3)>0),--(('Rewards Dashboard'!$F$3="All")+('Employee Data'!$D$2:$D$493='Rewards Dashboard'!$F$3)>0),--('Employee Data'!$D$2:$D$493=A63),--('Employee Data'!$E$2:$E$493=B63))/SUMPRODUCT(--('Employee Data'!$A$2:$A$493<>""),--(('Rewards Dashboard'!$B$3="All")+('Employee Data'!$E$2:$E$493='Rewards Dashboard'!$B$3)>0),--(('Rewards Dashboard'!$D$3="All")+('Employee Data'!$C$2:$C$493='Rewards Dashboard'!$D$3)>0),--(('Rewards Dashboard'!$F$3="All")+('Employee Data'!$D$2:$D$493='Rewards Dashboard'!$F$3)>0),--('Employee Data'!$D$2:$D$493=A63),--('Employee Data'!$E$2:$E$493=B63)),0)} -> 5268.5714 | E63: {=SUMPRODUCT(--('Employee Data'!$A$2:$A$493<>""),--(('Rewards Dashboard'!$B$3="All")+('Employee Data'!$E$2:$E$493='Rewards Dashboard'!$B$3)>0),--(('Rewards Dashboard'!$D$3="All")+('Employee Data'!$C$2:$C$493='Rewards Dashboard'!$D$3)>0),--(('Rewards Dashboard'!$F$3="All")+('Employee Data'!$D$2:$D$493='Rewards Dashboard'!$F$3)>0),--('Employee Data'!$D$2:$D$493=A63),--('Employee Data'!$E$2:$E$493=B63))} -> 35 | F63: {=IFERROR(SUMPRODUCT(--('Employee Data'!$I$2:$I$493>7000),--('Employee Data'!$A$2:$A$493<>""),--(('Rewards Dashboard'!$B$3="All")+('Employee Data'!$E$2:$E$493='Rewards Dashboard'!$B$3)>0),--(('Rewards Dashboard'!$D$3="All")+('Employee Data'!$C$2:$C$493='Rewards Dashboard'!$D$3)>0),--(('Rewards Dashboard'!$F$3="All")+('Employee Data'!$D$2:$D$493='Rewards Dashboard'!$F$3)>0),--('Employee Data'!$D$2:$D$493=A63),--('Employee Data'!$E$2:$E$493=B63))/E63,0)} -> 0.22857143
A64: Tech | B64: Hyderabad | C64: {=IFERROR(SUMPRODUCT('Employee Data'!$F$2:$F$493,--('Employee Data'!$A$2:$A$493<>""),--(('Rewards Dashboard'!$B$3="All")+('Employee Data'!$E$2:$E$493='Rewards Dashboard'!$B$3)>0),--(('Rewards Dashboard'!$D$3="All")+('Employee Data'!$C$2:$C$493='Rewards Dashboard'!$D$3)>0),--(('Rewards Dashboard'!$F$3="All")+('Employee Data'!$D$2:$D$493='Rewards Dashboard'!$F$3)>0),--('Employee Data'!$D$2:$D$493=A64),--('Employee Data'!$E$2:$E$493=B64))/SUMPRODUCT(--('Employee Data'!$A$2:$A$493<>""),--(('Rewards Dashboard'!$B$3="All")+('Employee Data'!$E$2:$E$493='Rewards Dashboard'!$B$3)>0),--(('Rewards Dashboard'!$D$3="All")+('Employee Data'!$C$2:$C$493='Rewards Dashboard'!$D$3)>0),--(('Rewards Dashboard'!$F$3="All")+('Employee Data'!$D$2:$D$493='Rewards Dashboard'!$F$3)>0),--('Employee Data'!$D$2:$D$493=A64),--('Employee Data'!$E$2:$E$493=B64)),0)} -> 99810.75 | D64: {=IFERROR(SUMPRODUCT('Employee Data'!$I$2:$I$493,--('Employee Data'!$A$2:$A$493<>""),--(('Rewards Dashboard'!$B$3="All")+('Employee Data'!$E$2:$E$493='Rewards Dashboard'!$B$3)>0),--(('Rewards Dashboard'!$D$3="All")+('Employee Data'!$C$2:$C$493='Rewards Dashboard'!$D$3)>0),--(('Rewards Dashboard'!$F$3="All")+('Employee Data'!$D$2:$D$493='Rewards Dashboard'!$F$3)>0),--('Employee Data'!$D$2:$D$493=A64),--('Employee Data'!$E$2:$E$493=B64))/SUMPRODUCT(--('Employee Data'!$A$2:$A$493<>""),--(('Rewards Dashboard'!$B$3="All")+('Employee Data'!$E$2:$E$493='Rewards Dashboard'!$B$3)>0),--(('Rewards Dashboard'!$D$3="All")+('Employee Data'!$C$2:$C$493='Rewards Dashboard'!$D$3)>0),--(('Rewards Dashboard'!$F$3="All")+('Employee Data'!$D$2:$D$493='Rewards Dashboard'!$F$3)>0),--('Employee Data'!$D$2:$D$493=A64),--('Employee Data'!$E$2:$E$493=B64)),0)} -> 4591.6667 | E64: {=SUMPRODUCT(--('Employee Data'!$A$2:$A$493<>""),--(('Rewards Dashboard'!$B$3="All")+('Employee Data'!$E$2:$E$493='Rewards Dashboard'!$B$3)>0),--(('Rewards Dashboard'!$D$3="All")+('Employee Data'!$C$2:$C$493='Rewards Dashboard'!$D$3)>0),--(('Rewards Dashboard'!$F$3="All")+('Employee Data'!$D$2:$D$493='Rewards Dashboard'!$F$3)>0),--('Employee Data'!$D$2:$D$493=A64),--('Employee Data'!$E$2:$E$493=B64))} -> 24 | F64: {=IFERROR(SUMPRODUCT(--('Employee Data'!$I$2:$I$493>7000),--('Employee Data'!$A$2:$A$493<>""),--(('Rewards Dashboard'!$B$3="All")+('Employee Data'!$E$2:$E$493='Rewards Dashboard'!$B$3)>0),--(('Rewards Dashboard'!$D$3="All")+('Employee Data'!$C$2:$C$493='Rewards Dashboard'!$D$3)>0),--(('Rewards Dashboard'!$F$3="All")+('Employee Data'!$D$2:$D$493='Rewards Dashboard'!$F$3)>0),--('Employee Data'!$D$2:$D$493=A64),--('Employee Data'!$E$2:$E$493=B64))/E64,0)} -> 0.25
A65: Finance | B65: Noida | C65: {=IFERROR(SUMPRODUCT('Employee Data'!$F$2:$F$493,--('Employee Data'!$A$2:$A$493<>""),--(('Rewards Dashboard'!$B$3="All")+('Employee Data'!$E$2:$E$493='Rewards Dashboard'!$B$3)>0),--(('Rewards Dashboard'!$D$3="All")+('Employee Data'!$C$2:$C$493='Rewards Dashboard'!$D$3)>0),--(('Rewards Dashboard'!$F$3="All")+('Employee Data'!$D$2:$D$493='Rewards Dashboard'!$F$3)>0),--('Employee Data'!$D$2:$D$493=A65),--('Employee Data'!$E$2:$E$493=B65))/SUMPRODUCT(--('Employee Data'!$A$2:$A$493<>""),--(('Rewards Dashboard'!$B$3="All")+('Employee Data'!$E$2:$E$493='Rewards Dashboard'!$B$3)>0),--(('Rewards Dashboard'!$D$3="All")+('Employee Data'!$C$2:$C$493='Rewards Dashboard'!$D$3)>0),--(('Rewards Dashboard'!$F$3="All")+('Employee Data'!$D$2:$D$493='Rewards Dashboard'!$F$3)>0),--('Employee Data'!$D$2:$D$493=A65),--('Employee Data'!$E$2:$E$493=B65)),0)} -> 126815 | D65: {=IFERROR(SUMPRODUCT('Employee Data'!$I$2:$I$493,--('Employee Data'!$A$2:$A$493<>""),--(('Rewards Dashboard'!$B$3="All")+('Employee Data'!$E$2:$E$493='Rewards Dashboard'!$B$3)>0),--(('Rewards Dashboard'!$D$3="All")+('Employee Data'!$C$2:$C$493='Rewards Dashboard'!$D$3)>0),--(('Rewards Dashboard'!$F$3="All")+('Employee Data'!$D$2:$D$493='Rewards Dashboard'!$F$3)>0),--('Employee Data'!$D$2:$D$493=A65),--('Employee Data'!$E$2:$E$493=B65))/SUMPRODUCT(--('Employee Data'!$A$2:$A$493<>""),--(('Rewards Dashboard'!$B$3="All")+('Employee Data'!$E$2:$E$493='Rewards Dashboard'!$B$3)>0),--(('Rewards Dashboard'!$D$3="All")+('Employee Data'!$C$2:$C$493='Rewards Dashboard'!$D$3)>0),--(('Rewards Dashboard'!$F$3="All")+('Employee Data'!$D$2:$D$493='Rewards Dashboard'!$F$3)>0),--('Employee Data'!$D$2:$D$493=A65),--('Employee Data'!$E$2:$E$493=B65)),0)} -> 5785.4167 | E65: {=SUMPRODUCT(--('Employee Data'!$A$2:$A$493<>""),--(('Rewards Dashboard'!$B$3="All")+('Employee Data'!$E$2:$E$493='Rewards Dashboard'!$B$3)>0),--(('Rewards Dashboard'!$D$3="All")+('Employee Data'!$C$2:$C$493='Rewards Dashboard'!$D$3)>0),--(('Rewards Dashboard'!$F$3="All")+('Employee Data'!$D$2:$D$493='Rewards Dashboard'!$F$3)>0),--('Employee Data'!$D$2:$D$493=A65),--('Employee Data'!$E$2:$E$493=B65))} -> 24 | F65: {=IFERROR(SUMPRODUCT(--('Employee Data'!$I$2:$I$493>7000),--('Employee Data'!$A$2:$A$493<>""),--(('Rewards Dashboard'!$B$3="All")+('Employee Data'!$E$2:$E$493='Rewards Dashboard'!$B$3)>0),--(('Rewards Dashboard'!$D$3="All")+('Employee Data'!$C$2:$C$493='Rewards Dashboard'!$D$3)>0),--(('Rewards Dashboard'!$F$3="All")+('Employee Data'!$D$2:$D$493='Rewards Dashboard'!$F$3)>0),--('Employee Data'!$D$2:$D$493=A65),--('Employee Data'!$E$2:$E$493=B65))/E65,0)} -> 0.25
A66: HR | B66: Noida | C66: {=IFERROR(SUMPRODUCT('Employee Data'!$F$2:$F$493,--('Employee Data'!$A$2:$A$493<>""),--(('Rewards Dashboard'!$B$3="All")+('Employee Data'!$E$2:$E$493='Rewards Dashboard'!$B$3)>0),--(('Rewards Dashboard'!$D$3="All")+('Employee Data'!$C$2:$C$493='Rewards Dashboard'!$D$3)>0),--(('Rewards Dashboard'!$F$3="All")+('Employee Data'!$D$2:$D$493='Rewards Dashboard'!$F$3)>0),--('Employee Data'!$D$2:$D$493=A66),--('Employee Data'!$E$2:$E$493=B66))/SUMPRODUCT(--('Employee Data'!$A$2:$A$493<>""),--(('Rewards Dashboard'!$B$3="All")+('Employee Data'!$E$2:$E$493='Rewards Dashboard'!$B$3)>0),--(('Rewards Dashboard'!$D$3="All")+('Employee Data'!$C$2:$C$493='Rewards Dashboard'!$D$3)>0),--(('Rewards Dashboard'!$F$3="All")+('Employee Data'!$D$2:$D$493='Rewards Dashboard'!$F$3)>0),--('Employee Data'!$D$2:$D$493=A66),--('Employee Data'!$E$2:$E$493=B66)),0)} -> 99674 | D66: {=IFERROR(SUMPRODUCT('Employee Data'!$I$2:$I$493,--('Employee Data'!$A$2:$A$493<>""),--(('Rewards Dashboard'!$B$3="All")+('Employee Data'!$E$2:$E$493='Rewards Dashboard'!$B$3)>0),--(('Rewards Dashboard'!$D$3="All")+('Employee Data'!$C$2:$C$493='Rewards Dashboard'!$D$3)>0),--(('Rewards Dashboard'!$F$3="All")+('Employee Data'!$D$2:$D$493='Rewards Dashboard'!$F$3)>0),--('Employee Data'!$D$2:$D$493=A66),--('Employee Data'!$E$2:$E$493=B66))/SUMPRODUCT(--('Employee Data'!$A$2:$A$493<>""),--(('Rewards Dashboard'!$B$3="All")+('Employee Data'!$E$2:$E$493='Rewards Dashboard'!$B$3)>0),--(('Rewards Dashboard'!$D$3="All")+('Employee Data'!$C$2:$C$493='Rewards Dashboard'!$D$3)>0),--(('Rewards Dashboard'!$F$3="All")+('Employee Data'!$D$2:$D$493='Rewards Dashboard'!$F$3)>0),--('Employee Data'!$D$2:$D$493=A66),--('Employee Data'!$E$2:$E$493=B66)),0)} -> 4577.2727 | E66: {=SUMPRODUCT(--('Employee Data'!$A$2:$A$493<>""),--(('Rewards Dashboard'!$B$3="All")+('Employee Data'!$E$2:$E$493='Rewards Dashboard'!$B$3)>0),--(('Rewards Dashboard'!$D$3="All")+('Employee Data'!$C$2:$C$493='Rewards Dashboard'!$D$3)>0),--(('Rewards Dashboard'!$F$3="All")+('Employee Data'!$D$2:$D$493='Rewards Dashboard'!$F$3)>0),--('Employee Data'!$D$2:$D$493=A66),--('Employee Data'!$E$2:$E$493=B66))} -> 22 | F66: {=IFERROR(SUMPRODUCT(--('Employee Data'!$I$2:$I$493>7000),--('Employee Data'!$A$2:$A$493<>""),--(('Rewards Dashboard'!$B$3="All")+('Employee Data'!$E$2:$E$493='Rewards Dashboard'!$B$3)>0),--(('Rewards Dashboard'!$D$3="All")+('Employee Data'!$C$2:$C$493='Rewards Dashboard'!$D$3)>0),--(('Rewards Dashboard'!$F$3="All")+('Employee Data'!$D$2:$D$493='Rewards Dashboard'!$F$3)>0),--('Employee Data'!$D$2:$D$493=A66),--('Employee Data'!$E$2:$E$493=B66))/E66,0)} -> 0.18181818
A67: Operations | B67: Noida | C67: {=IFERROR(SUMPRODUCT('Employee Data'!$F$2:$F$493,--('Employee Data'!$A$2:$A$493<>""),--(('Rewards Dashboard'!$B$3="All")+('Employee Data'!$E$2:$E$493='Rewards Dashboard'!$B$3)>0),--(('Rewards Dashboard'!$D$3="All")+('Employee Data'!$C$2:$C$493='Rewards Dashboard'!$D$3)>0),--(('Rewards Dashboard'!$F$3="All")+('Employee Data'!$D$2:$D$493='Rewards Dashboard'!$F$3)>0),--('Employee Data'!$D$2:$D$493=A67),--('Employee Data'!$E$2:$E$493=B67))/SUMPRODUCT(--('Employee Data'!$A$2:$A$493<>""),--(('Rewards Dashboard'!$B$3="All")+('Employee Data'!$E$2:$E$493='Rewards Dashboard'!$B$3)>0),--(('Rewards Dashboard'!$D$3="All")+('Employee Data'!$C$2:$C$493='Rewards Dashboard'!$D$3)>0),--(('Rewards Dashboard'!$F$3="All")+('Employee Data'!$D$2:$D$493='Rewards Dashboard'!$F$3)>0),--('Employee Data'!$D$2:$D$493=A67),--('Employee Data'!$E$2:$E$493=B67)),0)} -> 116921 | D67: {=IFERROR(SUMPRODUCT('Employee Data'!$I$2:$I$493,--('Employee Data'!$A$2:$A$493<>""),--(('Rewards Dashboard'!$B$3="All")+('Employee Data'!$E$2:$E$493='Rewards Dashboard'!$B$3)>0),--(('Rewards Dashboard'!$D$3="All")+('Employee Data'!$C$2:$C$493='Rewards Dashboard'!$D$3)>0),--(('Rewards Dashboard'!$F$3="All")+('Employee Data'!$D$2:$D$493='Rewards Dashboard'!$F$3)>0),--('Employee Data'!$D$2:$D$493=A67),--('Employee Data'!$E$2:$E$493=B67))/SUMPRODUCT(--('Employee Data'!$A$2:$A$493<>""),--(('Rewards Dashboard'!$B$3="All")+('Employee Data'!$E$2:$E$493='Rewards Dashboard'!$B$3)>0),--(('Rewards Dashboard'!$D$3="All")+('Employee Data'!$C$2:$C$493='Rewards Dashboard'!$D$3)>0),--(('Rewards Dashboard'!$F$3="All")+('Employee Data'!$D$2:$D$493='Rewards Dashboard'!$F$3)>0),--('Employee Data'!$D$2:$D$493=A67),--('Employee Data'!$E$2:$E$493=B67)),0)} -> 5140 | E67: {=SUMPRODUCT(--('Employee Data'!$A$2:$A$493<>""),--(('Rewards Dashboard'!$B$3="All")+('Employee Data'!$E$2:$E$493='Rewards Dashboard'!$B$3)>0),--(('Rewards Dashboard'!$D$3="All")+('Employee Data'!$C$2:$C$493='Rewards Dashboard'!$D$3)>0),--(('Rewards Dashboard'!$F$3="All")+('Employee Data'!$D$2:$D$493='Rewards Dashboard'!$F$3)>0),--('Employee Data'!$D$2:$D$493=A67),--('Employee Data'!$E$2:$E$493=B67))} -> 25 | F67: {=IFERROR(SUMPRODUCT(--('Employee Data'!$I$2:$I$493>7000),--('Employee Data'!$A$2:$A$493<>""),--(('Rewards Dashboard'!$B$3="All")+('Employee Data'!$E$2:$E$493='Rewards Dashboard'!$B$3)>0),--(('Rewards Dashboard'!$D$3="All")+('Employee Data'!$C$2:$C$493='Rewards Dashboard'!$D$3)>0),--(('Rewards Dashboard'!$F$3="All")+('Employee Data'!$D$2:$D$493='Rewards Dashboard'!$F$3)>0),--('Employee Data'!$D$2:$D$493=A67),--('Employee Data'!$E$2:$E$493=B67))/E67,0)} -> 0.16
... A69: Tech | B69: Noida | C69: {=IFERROR(SUMPRODUCT('Employee Data'!$F$2:$F$493,--('Employee Data'!$A$2:$A$493<>""),--(('Rewards Dashboard'!$B$3="All")+('Employee Data'!$E$2:$E$493='Rewards Dashboard'!$B$3)>0),--(('Rewards Dashboard'!$D$3="All")+('Employee Data'!$C$2:$C$493='Rewards Dashboard'!$D$3)>0),--(('Rewards Dashboard'!$F$3="All")+('Employee Data'!$D$2:$D$493='Rewards Dashboard'!$F$3)>0),--('Employee Data'!$D$2:$D$493=A69),--('Employee Data'!$E$2:$E$493=B69))/SUMPRODUCT(--('Employee Data'!$A$2:$A$493<>""),--(('Rewards Dashboard'!$B$3="All")+('Employee Data'!$E$2:$E$493='Rewards Dashboard'!$B$3)>0),--(('Rewards Dashboard'!$D$3="All")+('Employee Data'!$C$2:$C$493='Rewards Dashboard'!$D$3)>0),--(('Rewards Dashboard'!$F$3="All")+('Employee Data'!$D$2:$D$493='Rewards Dashboard'!$F$3)>0),--('Employee Data'!$D$2:$D$493=A69),--('Employee Data'!$E$2:$E$493=B69)),0)} -> 124199.26 | D69: {=IFERROR(SUMPRODUCT('Employee Data'!$I$2:$I$493,--('Employee Data'!$A$2:$A$493<>""),--(('Rewards Dashboard'!$B$3="All")+('Employee Data'!$E$2:$E$493='Rewards Dashboard'!$B$3)>0),--(('Rewards Dashboard'!$D$3="All")+('Employee Data'!$C$2:$C$493='Rewards Dashboard'!$D$3)>0),--(('Rewards Dashboard'!$F$3="All")+('Employee Data'!$D$2:$D$493='Rewards Dashboard'!$F$3)>0),--('Employee Data'!$D$2:$D$493=A69),--('Employee Data'!$E$2:$E$493=B69))/SUMPRODUCT(--('Employee Data'!$A$2:$A$493<>""),--(('Rewards Dashboard'!$B$3="All")+('Employee Data'!$E$2:$E$493='Rewards Dashboard'!$B$3)>0),--(('Rewards Dashboard'!$D$3="All")+('Employee Data'!$C$2:$C$493='Rewards Dashboard'!$D$3)>0),--(('Rewards Dashboard'!$F$3="All")+('Employee Data'!$D$2:$D$493='Rewards Dashboard'!$F$3)>0),--('Employee Data'!$D$2:$D$493=A69),--('Employee Data'!$E$2:$E$493=B69)),0)} -> 5511.1111 | E69: {=SUMPRODUCT(--('Employee Data'!$A$2:$A$493<>""),--(('Rewards Dashboard'!$B$3="All")+('Employee Data'!$E$2:$E$493='Rewards Dashboard'!$B$3)>0),--(('Rewards Dashboard'!$D$3="All")+('Employee Data'!$C$2:$C$493='Rewards Dashboard'!$D$3)>0),--(('Rewards Dashboard'!$F$3="All")+('Employee Data'!$D$2:$D$493='Rewards Dashboard'!$F$3)>0),--('Employee Data'!$D$2:$D$493=A69),--('Employee Data'!$E$2:$E$493=B69))} -> 27 | F69: {=IFERROR(SUMPRODUCT(--('Employee Data'!$I$2:$I$493>7000),--('Employee Data'!$A$2:$A$493<>""),--(('Rewards Dashboard'!$B$3="All")+('Employee Data'!$E$2:$E$493='Rewards Dashboard'!$B$3)>0),--(('Rewards Dashboard'!$D$3="All")+('Employee Data'!$C$2:$C$493='Rewards Dashboard'!$D$3)>0),--(('Rewards Dashboard'!$F$3="All")+('Employee Data'!$D$2:$D$493='Rewards Dashboard'!$F$3)>0),--('Employee Data'!$D$2:$D$493=A69),--('Employee Data'!$E$2:$E$493=B69))/E69,0)} -> 0.22222222

Sheet Basic Analysis
A1: Count of Department | B1: Column Labels | I1: Count of Department | J1: Column Labels | P1: Count of Insurance tier | Q1: Salary Band | W1: Max of Monthly Base Salary (INR) | X1: Column Labels
A2: Row Labels | B2: Finance | C2: HR | D2: Operations | E2: Sales | F2: Tech | G2: Grand Total | I2: Row Labels | J2: Bengaluru | K2: Gurugram | L2: Hyderabad | M2: Noida | N2: Grand Total | P2: Insurance Tier | Q2: Junior | R2: Lead | S2: Mid | T2: Senior | U2: Grand Total | W2: Row Labels | X2: Junior | Y2: Lead | Z2: Mid | AA2: Senior | AB2: Grand Total
A3: Junior | I3: Junior | P3: Bronze | Q3: 54 | R3: 2 | S3: 1 | T3: 2 | U3: 59 | W3: Finance | X3: 77431 | Y3: 230431 | Z3: 112943 | AA3: 151206 | AB3: 230431
A4: Female | B4: 7 | C4: 11 | D4: 14 | E4: 12 | F4: 11 | G4: 55 | I4: Female | J4: 13 | K4: 11 | L4: 21 | M4: 10 | N4: 55 | P4: Gold | R4: 122 | T4: 94 | U4: 216 | W4: HR | X4: 77592 | Y4: 226495 | Z4: 111621 | AA4: 152558 | AB4: 226495
A5: Male | B5: 12 | C5: 11 | D5: 13 | E5: 14 | F5: 18 | G5: 68 | I5: Male | J5: 16 | K5: 14 | L5: 16 | M5: 22 | N5: 68 | P5: Silver | Q5: 69 | S5: 122 | T5: 26 | U5: 217 | W5: Operations | X5: 77183 | Y5: 233542 | Z5: 112449 | AA5: 152788 | AB5: 233542
A6: Lead | I6: Lead | P6: Grand Total | Q6: 123 | R6: 124 | S6: 123 | T6: 122 | U6: 492 | W6: Sales | X6: 78895 | Y6: 230880 | Z6: 112838 | AA6: 152013 | AB6: 230880
A7: Female | B7: 8 | C7: 13 | D7: 12 | E7: 12 | F7: 6 | G7: 51 | I7: Female | J7: 17 | K7: 13 | L7: 12 | M7: 9 | N7: 51 | W7: Tech | X7: 78635 | Y7: 215780 | Z7: 111986 | AA7: 152988 | AB7: 215780
A8: Male | B8: 13 | C8: 9 | D8: 13 | E8: 18 | F8: 18 | G8: 71 | I8: Male | J8: 12 | K8: 18 | L8: 20 | M8: 21 | N8: 71 | P8: Max of Monthly Premiums | Q8: Column Labels | W8: Grand Total | X8: 78895 | Y8: 233542 | Z8: 112943 | AA8: 152988 | AB8: 233542
A9: Transgender | B9: 2 | G9: 2 | I9: Transgender | L9: 1 | M9: 1 | N9: 2 | P9: Row Labels | Q9: Junior | R9: Lead | S9: Mid | T9: Senior | U9: Grand Total
A10: Mid | I10: Mid | P10: Bronze | Q10: 1500 | R10: 9500 | S10: 9500 | T10: 9500 | U10: 9500 | W10: Min of Monthly Base Salary (INR) | X10: Column Labels
A11: Female | B11: 11 | C11: 11 | D11: 12 | E11: 16 | F11: 8 | G11: 58 | I11: Female | J11: 12 | K11: 11 | L11: 16 | M11: 19 | N11: 58 | P11: Gold | R11: 9000 | T11: 9000 | U11: 9000 | W11: Row Labels | X11: Junior | Y11: Lead | Z11: Mid | AA11: Senior | AB11: Grand Total
A12: Male | B12: 13 | C12: 16 | D12: 11 | E12: 13 | F12: 12 | G12: 65 | I12: Male | J12: 16 | K12: 21 | L12: 16 | M12: 12 | N12: 65 | P12: Silver | Q12: 4200 | S12: 4200 | T12: 4200 | U12: 4200 | W12: Finance | X12: 40601 | Y12: 156954 | Z12: 79394 | AA12: 113244 | AB12: 40601
A13: Senior | I13: Senior | P13: Grand Total | Q13: 4200 | R13: 9500 | S13: 9500 | T13: 9500 | U13: 9500 | W13: HR | X13: 45515 | Y13: 154178 | Z13: 81071 | AA13: 113535 | AB13: 45515
A14: Female | B14: 18 | C14: 8 | D14: 9 | E14: 15 | F14: 10 | G14: 60 | I14: Female | J14: 9 | K14: 21 | L14: 19 | M14: 11 | N14: 60 | W14: Operations | X14: 37393 | Y14: 155897 | Z14: 79993 | AA14: 114498 | AB14: 37393
A15: Male | B15: 13 | C15: 9 | D15: 13 | E15: 9 | F15: 17 | G15: 61 | I15: Male | J15: 14 | K15: 11 | L15: 19 | M15: 17 | N15: 61 | P15: Min of Monthly Premiums | Q15: Column Labels | W15: Sales | X15: 37078 | Y15: 159056 | Z15: 79153 | AA15: 117304 | AB15: 37078
A16: Transgender | F16: 1 | G16: 1 | I16: Transgender | J16: 1 | N16: 1 | P16: Row Labels | Q16: Junior | R16: Lead | S16: Mid | T16: Senior | U16: Grand Total | W16: Tech | X16: 38296 | Y16: 153444 | Z16: 79816 | AA16: 113887 | AB16: 38296
A17: Grand Total | B17: 97 | C17: 88 | D17: 97 | E17: 109 | F17: 101 | G17: 492 | I17: Grand Total | J17: 110 | K17: 120 | L17: 140 | M17: 122 | N17: 492 | P17: Bronze | Q17: 1500 | R17: 9500 | S17: 9500 | T17: 9500 | U17: 1500 | W17: Grand Total | X17: 37078 | Y17: 153444 | Z17: 79153 | AA17: 113244 | AB17: 37078
P18: Gold | R18: 6750 | T18: 6750 | U18: 6750
P19: Silver | Q19: 2800 | S19: 2800 | T19: 2800 | U19: 2800
A20: Insurance Tier | B20: Count of Insurance tier | P20: Grand Total | Q20: 1500 | R20: 6750 | S20: 2800 | T20: 2800 | U20: 1500
A21: Bronze | B21: 59
A22: Gold | B22: 216 | P22: Count of Monthly Premiums | Q22: Column Labels
A23: Silver | B23: 217 | P23: Row Labels | Q23: Junior | R23: Lead | S23: Mid | T23: Senior | U23: Grand Total
A24: Grand Total | B24: 492 | P24: Bronze
P25: Individual | Q25: 54 | U25: 54
P26: Parents Included | R26: 2 | S26: 1 | T26: 2 | U26: 5
P27: Gold
P28: Family Floater | R28: 59 | T28: 48 | U28: 107
P29: Parents Included | R29: 63 | T29: 46 | U29: 109
P30: Silver
P31: Family Floater | Q31: 35 | S31: 58 | T31: 8 | U31: 101
P32: Individual | Q32: 34 | S32: 64 | T32: 18 | U32: 116
P33: Grand Total | Q33: 123 | R33: 124 | S33: 123 | T33: 122 | U33: 492

Sheet Rewards & Benefits Allocation
A1: Row Labels | B1: Headcount | C1: Total Monthly Premium Cost | D1: Average Salary | E1: High-Cost Employee % | H1: Average of Monthly Premiums | I1: Locations
A2: Bengaluru | H2: Department | I2: Bengaluru | J2: Gurugram | K2: Hyderabad | L2: Noida | M2: Grand Total
A3: Finance | B3: 22 | C3: 108400 | D3: 115477.86 | E3: 0.18181818 | H3: Finance | I3: 4927.2727 | J3: 5190.9091 | K3: 5944.8276 | L3: 5785.4167 | M3: 5503.6082
A4: HR | B4: 19 | C4: 104300 | D4: 131595.95 | E4: 0.26315789 | H4: HR | I4: 5489.4737 | J4: 5064.2857 | K4: 4819.2308 | L4: 4577.2727 | M4: 4961.9318
A5: Operations | B5: 19 | C5: 79650 | D5: 102408.47 | E5: 0.21052632 | H5: Operations | I5: 4192.1053 | J5: 5490.7407 | K5: 5475 | L5: 5140 | M5: 5141.7526
A6: Sales | B6: 25 | C6: 135750 | D6: 125256.52 | E6: 0.2 | H6: Sales | I6: 5430 | J6: 6062 | K6: 5268.5714 | L6: 5293.75 | M6: 5493.1193
A7: Tech | B7: 25 | C7: 129350 | D7: 122661.32 | E7: 0.16 | H7: Tech | I7: 5174 | J7: 5066 | K7: 4591.6667 | L7: 5511.1111 | M7: 5099.0099
A8: Gurugram | H8: Grand Total | I8: 5067.7273 | J8: 5391.6667 | K8: 5247.5 | L8: 5277.8689 | M8: 5250
A9: Finance | B9: 22 | C9: 114200 | D9: 113401.59 | E9: 0.22727273
A10: HR | B10: 21 | C10: 106350 | D10: 117717.62 | E10: 0.19047619
A11: Operations | B11: 27 | C11: 148250 | D11: 117910.11 | E11: 0.25925926
A12: Sales | B12: 25 | C12: 151550 | D12: 134835.56 | E12: 0.32
A13: Tech | B13: 25 | C13: 126650 | D13: 113808.76 | E13: 0.2
A14: Hyderabad
A15: Finance | B15: 29 | C15: 172400 | D15: 128885.24 | E15: 0.34482759
A16: HR | B16: 26 | C16: 125300 | D16: 116479.5 | E16: 0.19230769
A17: Operations | B17: 26 | C17: 142350 | D17: 130724.81 | E17: 0.30769231
A18: Sales | B18: 35 | C18: 184400 | D18: 117752.26 | E18: 0.22857143
A19: Tech | B19: 24 | C19: 110200 | D19: 99810.75 | E19: 0.25
A20: Noida
A21: Finance | B21: 24 | C21: 138850 | D21: 126815 | E21: 0.25
A22: HR | B22: 22 | C22: 100700 | D22: 99674 | E22: 0.18181818
A23: Operations | B23: 25 | C23: 128500 | D23: 116921 | E23: 0.16
A24: Sales | B24: 24 | C24: 127050 | D24: 110101.08 | E24: 0.29166667
A25: Tech | B25: 27 | C25: 148800 | D25: 124199.26 | E25: 0.22222222
A26: Grand Total | B26: 492 | C26: 2583000 | D26: 118675.04 | E26: 0.23373984

Sheet Gender Pay Equity
A1: Gender Pay Gap | B1: Column Labels
A2: Row Labels | B2: Junior | C2: Lead | D2: Mid | E2: Senior | F2: Grand Total
A3: Finance | B3: 4285.9762 | C3: -6018.2308 | D3: 2288.6573 | E3: -2005.8419 | F3: -2435.8913
A4: HR | B4: -1292 | C4: 7213.8803 | D4: -5557.2955 | E4: -6347.6389 | F4: -9700.6636
A5: Operations | B5: 2094.3297 | C5: 13906.872 | D5: 1276.8788 | E5: 989.68376 | F5: 8769.1106
A6: Sales | B6: -5698.7619 | C6: -2950.1389 | D6: -4477.6538 | E6: -4772.1111 | F6: 1035.6825
A7: Tech | B7: -6402.2929 | C7: 3260.1667 | D7: -4871.0417 | E7: 5366.3 | F7: 8851.244
A8: Grand Total | B8: -2229.5479 | C8: 2672.5515 | D8: -2277.3732 | E8: -1553.5495 | F8: 1047.4824
A10: Average of Monthly Base Salary (INR) | B10: Column Labels | E10: Each band's gap is under 3% of that band's average, and the direction flips (women ahead in three bands, men ahead in one). This pattern is consistent with normal variation rather than a systematic gap — no band shows a one-sided, consistent disadvantage for either gender. | H10: Average of Monthly Base Salary (INR)
A11: Row Labels | B11: Female | C11: Male | D11: Gap (M-F) | H11: Salary Band | I11: Female | J11: Male | K11: Gap (M-F)
A12: Junior | B12: 62039.327 | C12: 59809.779 | D12: =B12-C12 -> 2229.5479 | H12: Junior | I12: 62039.327 | J12: 59809.779 | K12: 2229.5479
A13: Lead | B13: 184793.39 | C13: 187465.94 | D13: =B13-C13 -> -2672.5515 | H13: Lead | I13: 184793.39 | J13: 187465.94 | K13: -2672.5515
A14: Mid | B14: 95928.466 | C14: 93651.092 | D14: =B14-C14 -> 2277.3732 | H14: Mid | I14: 95928.466 | J14: 93651.092 | K14: 2277.3732
A15: Senior | B15: 132606.52 | C15: 131052.97 | D15: =B15-C15 -> 1553.5495 | H15: Senior | I15: 132606.52 | J15: 131052.97 | K15: 1553.5495
A16: Grand Total | B16: 117664.59 | C16: 118712.07 | D16: =B16-C16 -> -1047.4824 | H16: Grand Total | I16: 117664.59 | J16: 118712.07 | K16: -1047.4824
A18: Note: The Transgender group is too small for standalone statistical comparison and is excluded from the gender pay analysis below — noted here as a scope limitation, not an omission.

Sheet Vendor Map Data
A1: Internal Department | B1: Vendor Survey Job Code | C1: Vendor Global Group Name | D1: Industry Peer Segment
A2: Tech | B2: IN-TECH-04 | C2: High-Value Technical Core | D2: Technology / Energy
A3: Operations | B3: IN-OPS-02 | C3: Core Operations Specialist | D3: Industrial Operations
A4: Sales | B4: IN-SLS-01 | C4: Field Sales Execution | D4: Commercial & Retail
A5: Finance | B5: IN-FIN-03 | C5: Corporate Finance Core | D5: Shared Services
A6: HR | B6: IN-HR-02 | C6: Corporate Talent Admin | D6: Shared Services

Sheet Query_Audit_Exceptions
A1: Employee ID | B1: Full Name | C1: Gender | D1: Department | E1: Location | F1: Monthly Base Salary (INR) | G1: Corporate Benefit Plan | H1: Insurance tier | I1: Monthly Premiums | J1: Salary Bracket | K1: Salary Tier | L1: Vendor Survey Job Code | M1: Vendor Global Group Name

Sheet Employee Data
A1: Employee ID | B1: Full Name | C1: Gender | D1: Department | E1: Location | F1: Monthly Base Salary (INR) | G1: Corporate Benefit Plan | H1: Insurance tier | I1: Monthly Premiums | J1: Salary Bracket | K1: Salary Tier | L1: Vendor Survey Job Code | M1: Vendor Global Group Name | O1: Min | P1: =MIN(F:F) -> 37078 | Q1: Max | R1: =MAX(F:F) -> 233542
A2: Emp1085 | B2: Indira Joshi | C2: Male | D2: HR | E2: Gurugram | F2: 88815 | G2: Individual | H2: Silver | I2: 2800 | J2: Between 50k and 200k | K2: Mid | L2: IN-HR-02 | M2: Corporate Talent Admin | O2: Range of Salary | P2: =R1-P1 -> 196464
A3: Emp1307 | B3: Rajkumar Devi | C3: Male | D3: Finance | E3: Bengaluru | F3: 88549 | G3: Individual | H3: Silver | I3: 2800 | J3: Between 50k and 200k | K3: Mid | L3: IN-FIN-03 | M3: Corporate Finance Core | O3: IQR | P3: =_xlfn.QUARTILE.INC(Indian_Employee_Data[Monthly Base Salary (INR)],1) - _xlfn.QUARTILE.INC(Indian_Employee_Data[Monthly Base Salary (INR)],) -> 42010.5
A4: Emp1122 | B4: Renchamo Kikon | C4: Male | D4: Sales | E4: Hyderabad | F4: 87960 | G4: Individual | H4: Silver | I4: 2800 | J4: Between 50k and 200k | K4: Mid | L4: IN-SLS-01 | M4: Field Sales Execution | O4: Outlier check | P4: Lower bound | Q4: Upper Bound
A5: Emp1166 | B5: Sachin Verma | C5: Male | D5: Tech | E5: Gurugram | F5: 88290 | G5: Family Floater | H5: Silver | I5: 4200 | J5: Between 50k and 200k | K5: Mid | L5: IN-TECH-04 | M5: High-Value Technical Core | P5: =_xlfn.QUARTILE.INC(Indian_Employee_Data[Monthly Base Salary (INR)],1) - (1.5*$P$3) -> 16072.75 | Q5: =_xlfn.QUARTILE.INC(Indian_Employee_Data[Monthly Base Salary (INR)],3) - (1.5*$P$3) -> 90611.75
A6: Emp1330 | B6: Sngi Kharkongor | C6: Male | D6: HR | E6: Noida | F6: 92535 | G6: Family Floater | H6: Silver | I6: 4200 | J6: Between 50k and 200k | K6: Mid | L6: IN-HR-02 | M6: Corporate Talent Admin | P6: No Low Outliers | Q6: High Outliers Exist
A7: Emp1133 | B7: Subhalata Koloi | C7: Male | D7: Finance | E7: Bengaluru | F7: 90307 | G7: Family Floater | H7: Silver | I7: 4200 | J7: Between 50k and 200k | K7: Mid | L7: IN-FIN-03 | M7: Corporate Finance Core
A8: Emp1281 | B8: Chidambaram Reddy | C8: Male | D8: Tech | E8: Hyderabad | F8: 90352 | G8: Individual | H8: Silver | I8: 2800 | J8: Between 50k and 200k | K8: Mid | L8: IN-TECH-04 | M8: High-Value Technical Core
A9: Emp1194 | B9: Kersi Vakil | C9: Male | D9: Sales | E9: Noida | F9: 90477 | G9: Family Floater | H9: Silver | I9: 4200 | J9: Between 50k and 200k | K9: Mid | L9: IN-SLS-01 | M9: Field Sales Execution
A10: Emp1394 | B10: Aspi Contractor | C10: Male | D10: HR | E10: Gurugram | F10: 90691 | G10: Family Floater | H10: Silver | I10: 4200 | J10: Between 50k and 200k | K10: Mid | L10: IN-HR-02 | M10: Corporate Talent Admin
A11: Emp1180 | B11: Vanlalhruaii Khiangte | C11: Male | D11: Tech | E11: Noida | F11: 90723 | G11: Family Floater | H11: Silver | I11: 4200 | J11: Between 50k and 200k | K11: Mid | L11: IN-TECH-04 | M11: High-Value Technical Core
A12: Emp1063 | B12: Mark D'Souza | C12: Male | D12: Sales | E12: Gurugram | F12: 92631 | G12: Individual | H12: Silver | I12: 2800 | J12: Between 50k and 200k | K12: Mid | L12: IN-SLS-01 | M12: Field Sales Execution
A13: Emp1253 | B13: Kalpana Raman | C13: Male | D13: HR | E13: Gurugram | F13: 87831 | G13: Individual | H13: Silver | I13: 2800 | J13: Between 50k and 200k | K13: Mid | L13: IN-HR-02 | M13: Corporate Talent Admin
A14: Emp1323 | B14: Zubin Irani | C14: Male | D14: HR | E14: Bengaluru | F14: 83499 | G14: Individual | H14: Silver | I14: 2800 | J14: Between 50k and 200k | K14: Mid | L14: IN-HR-02 | M14: Corporate Talent Admin
A15: Emp1224 | B15: Gyati Yein | C15: Male | D15: Sales | E15: Hyderabad | F15: 81804 | G15: Individual | H15: Silver | I15: 2800 | J15: Between 50k and 200k | K15: Mid | L15: IN-SLS-01 | M15: Field Sales Execution
A16: Emp1492 | B16: Xavier Mondal | C16: Male | D16: Finance | E16: Hyderabad | F16: 83204 | G16: Individual | H16: Silver | I16: 2800 | J16: Between 50k and 200k | K16: Mid | L16: IN-FIN-03 | M16: Corporate Finance Core
A17: Emp1268 | B17: Hemant Joshi | C17: Male | D17: Operations | E17: Gurugram | F17: 92966 | G17: Family Floater | H17: Silver | I17: 4200 | J17: Between 50k and 200k | K17: Mid | L17: IN-OPS-02 | M17: Core Operations Specialist
A18: Emp1236 | B18: Rajkumari Laishram | C18: Male | D18: Sales | E18: Hyderabad | F18: 83596 | G18: Family Floater | H18: Silver | I18: 4200 | J18: Between 50k and 200k | K18: Mid | L18: IN-SLS-01 | M18: Field Sales Execution
... A493: Emp1208 | B493: Varun Rathore | C493: Male | D493: Sales | E493: Hyderabad | F493: 37078 | G493: Individual | H493: Bronze | I493: 1500 | J493: Under 50k | K493: Junior | L493: IN-SLS-01 | M493: Field Sales Execution

Sheet Main Pivot Table Sheet
A1: High-Cost Employee % | B1: Location | J1: Vendor Global Group Name | K1: Vendor Survey Job Code | L1: Total Monthly Premium Cost | M1: High-Cost Employee % | N1: Headcount | O1: Average Salary
A2: Department | B2: Bengaluru | C2: Gurugram | D2: Hyderabad | E2: Noida | F2: Grand Total | J2: Core Operations Specialist | K2: IN-OPS-02 | L2: 498750 | M2: 0.2371134 | N2: 97 | O2: 118053.65
A3: Finance | B3: 0.18181818 | C3: 0.22727273 | D3: 0.34482759 | E3: 0.25 | F3: 0.25773196 | J3: Corporate Finance Core | K3: IN-FIN-03 | L3: 533850 | M3: 0.25773196 | N3: 97 | O3: 121820.41
A4: HR | B4: 0.26315789 | C4: 0.19047619 | D4: 0.19230769 | E4: 0.18181818 | F4: 0.20454545 | J4: Corporate Talent Admin | K4: IN-HR-02 | L4: 436650 | M4: 0.20454545 | N4: 88 | O4: 115837.36
A5: Operations | B5: 0.21052632 | C5: 0.25925926 | D5: 0.30769231 | E5: 0.16 | F5: 0.2371134 | J5: Field Sales Execution | K5: IN-SLS-01 | L5: 598750 | M5: 0.25688073 | N5: 109 | O5: 121706.94
A6: Sales | B6: 0.2 | C6: 0.32 | D6: 0.22857143 | E6: 0.29166667 | F6: 0.25688073 | J6: High-Value Technical Core | K6: IN-TECH-04 | L6: 515000 | M6: 0.20792079 | N6: 101 | O6: 115451.39
A7: Tech | B7: 0.16 | C7: 0.2 | D7: 0.25 | E7: 0.22222222 | F7: 0.20792079 | J7: Grand Total | L7: 2583000 | M7: 0.23373984 | N7: 492 | O7: 118675.04
A8: Grand Total | B8: 0.2 | C8: 0.24166667 | D8: 0.26428571 | E8: 0.22131148 | F8: 0.23373984
A11: Average of Monthly Base Salary (INR) | B11: Gender | E11: Each band's gap is under 3% of that band's average, and the direction flips (women ahead in three bands, men ahead in one). This pattern is consistent with normal variation rather than a systematic gap — no band shows a one-sided, consistent disadvantage for either gender.
A12: Salary Band | B12: Female | C12: Male | D12: Gap (M-F)
A13: Junior | B13: 62039.327 | C13: 59809.779 | D13: =C13-B13 -> -2229.5479
A14: Mid | B14: 95928.466 | C14: 93651.092 | D14: =C14-B14 -> -2277.3732
A15: Senior | B15: 132606.52 | C15: 131052.97 | D15: =C15-B15 -> -1553.5495
A16: Lead | B16: 184793.39 | C16: 187465.94 | D16: =C16-B16 -> 2672.5515
A17: Grand Total | B17: 117664.59 | C17: 118712.07 | D17: =C17-B17 -> 1047.4824
A19: Note: The Transgender group is too small for standalone statistical comparison and is excluded from the gender pay analysis below — noted here as a scope limitation, not an omission.
A21: Insurance Tier | B21: Count of Insurance tier
A22: Bronze | B22: 59
A23: Gold | B23: 216
A24: Silver | B24: 217
A25: Grand Total | B25: 492
A28: Benefit Plan | B28: Count
A29: Family Floater | B29: 208 | J29: Employee ID | K29: Insurance tier | L29: =CUBEMEMBER("ThisWorkbookDataModel","[Measures].[Sum of Monthly Base Salary (INR)]") -> Sum of Monthly Base Salary (INR) | M29: =CUBEMEMBER("ThisWorkbookDataModel","[Measures].[Sum of Monthly Premiums]") -> Sum of Monthly Premiums | N29: Bronze Premium Y | O29: Silver Premium Y | P29: Gold Premium Y | Q29: Bronze Salary X | R29: Silver Salary X | S29: Gold Salary X
A30: Individual | B30: 170 | J30: =CUBEMEMBER("ThisWorkbookDataModel","[Indian_Employee_Data].[Employee ID].&[Emp1000]") -> Emp1000 | K30: =CUBEMEMBER("ThisWorkbookDataModel",{"[Indian_Employee_Data].[Employee ID].&[Emp1000]","[Indian_Employee_Data].[Insurance tier].&[Silver]"}) -> Silver | L30: =CUBEVALUE("ThisWorkbookDataModel",$K30,L$29,Slicer_Department) -> 94822 | M30: =CUBEVALUE("ThisWorkbookDataModel",$K30,M$29,Slicer_Department) -> 4200 | N30: =IF(AND($K30="Bronze",ISNUMBER($L30),ISNUMBER($M30)),$M30,NA()) -> #N/A | O30: =IF(AND($K30="Silver",ISNUMBER($L30),ISNUMBER($M30)),$M30,NA()) -> 4200 | P30: =IF(AND($K30="Gold",ISNUMBER($L30),ISNUMBER($M30)),$M30,NA()) -> #N/A | Q30: =IF(AND($K30="Bronze",ISNUMBER($L30),ISNUMBER($N30)),$L30,NA()) -> #N/A | R30: =IF(AND($K30="Silver",ISNUMBER($L30),ISNUMBER($O30)),$L30,NA()) -> 94822 | S30: =IF(AND($K30="Gold",ISNUMBER($L30),ISNUMBER($P30)),$L30,NA()) -> #N/A
A31: Parents Included | B31: 114 | J31: =CUBEMEMBER("ThisWorkbookDataModel","[Indian_Employee_Data].[Employee ID].&[Emp1001]") -> Emp1001 | K31: =CUBEMEMBER("ThisWorkbookDataModel",{"[Indian_Employee_Data].[Employee ID].&[Emp1001]","[Indian_Employee_Data].[Insurance tier].&[Gold]"}) -> Gold | L31: =CUBEVALUE("ThisWorkbookDataModel",$K31,L$29,Slicer_Department) -> 206439 | M31: =CUBEVALUE("ThisWorkbookDataModel",$K31,M$29,Slicer_Department) -> 9000 | N31: =IF(AND($K31="Bronze",ISNUMBER($L31),ISNUMBER($M31)),$M31,NA()) -> #N/A | O31: =IF(AND($K31="Silver",ISNUMBER($L31),ISNUMBER($M31)),$M31,NA()) -> #N/A | P31: =IF(AND($K31="Gold",ISNUMBER($L31),ISNUMBER($M31)),$M31,NA()) -> 9000 | Q31: =IF(AND($K31="Bronze",ISNUMBER($L31),ISNUMBER($N31)),$L31,NA()) -> #N/A | R31: =IF(AND($K31="Silver",ISNUMBER($L31),ISNUMBER($O31)),$L31,NA()) -> #N/A | S31: =IF(AND($K31="Gold",ISNUMBER($L31),ISNUMBER($P31)),$L31,NA()) -> 206439
A32: Grand Total | B32: 492 | J32: =CUBEMEMBER("ThisWorkbookDataModel","[Indian_Employee_Data].[Employee ID].&[Emp1002]") -> Emp1002 | K32: =CUBEMEMBER("ThisWorkbookDataModel",{"[Indian_Employee_Data].[Employee ID].&[Emp1002]","[Indian_Employee_Data].[Insurance tier].&[Gold]"}) -> Gold | L32: =CUBEVALUE("ThisWorkbookDataModel",$K32,L$29,Slicer_Department) -> 148421 | M32: =CUBEVALUE("ThisWorkbookDataModel",$K32,M$29,Slicer_Department) -> 9000 | N32: =IF(AND($K32="Bronze",ISNUMBER($L32),ISNUMBER($M32)),$M32,NA()) -> #N/A | O32: =IF(AND($K32="Silver",ISNUMBER($L32),ISNUMBER($M32)),$M32,NA()) -> #N/A | P32: =IF(AND($K32="Gold",ISNUMBER($L32),ISNUMBER($M32)),$M32,NA()) -> 9000 | Q32: =IF(AND($K32="Bronze",ISNUMBER($L32),ISNUMBER($N32)),$L32,NA()) -> #N/A | R32: =IF(AND($K32="Silver",ISNUMBER($L32),ISNUMBER($O32)),$L32,NA()) -> #N/A | S32: =IF(AND($K32="Gold",ISNUMBER($L32),ISNUMBER($P32)),$L32,NA()) -> 148421
J33: =CUBEMEMBER("ThisWorkbookDataModel","[Indian_Employee_Data].[Employee ID].&[Emp1003]") -> Emp1003 | K33: =CUBEMEMBER("ThisWorkbookDataModel",{"[Indian_Employee_Data].[Employee ID].&[Emp1003]","[Indian_Employee_Data].[Insurance tier].&[Gold]"}) -> Gold | L33: =CUBEVALUE("ThisWorkbookDataModel",$K33,L$29,Slicer_Department) -> 125695 | M33: =CUBEVALUE("ThisWorkbookDataModel",$K33,M$29,Slicer_Department) -> 9000 | N33: =IF(AND($K33="Bronze",ISNUMBER($L33),ISNUMBER($M33)),$M33,NA()) -> #N/A | O33: =IF(AND($K33="Silver",ISNUMBER($L33),ISNUMBER($M33)),$M33,NA()) -> #N/A | P33: =IF(AND($K33="Gold",ISNUMBER($L33),ISNUMBER($M33)),$M33,NA()) -> 9000 | Q33: =IF(AND($K33="Bronze",ISNUMBER($L33),ISNUMBER($N33)),$L33,NA()) -> #N/A | R33: =IF(AND($K33="Silver",ISNUMBER($L33),ISNUMBER($O33)),$L33,NA()) -> #N/A | S33: =IF(AND($K33="Gold",ISNUMBER($L33),ISNUMBER($P33)),$L33,NA()) -> 125695
J34: =CUBEMEMBER("ThisWorkbookDataModel","[Indian_Employee_Data].[Employee ID].&[Emp1004]") -> Emp1004 | K34: =CUBEMEMBER("ThisWorkbookDataModel",{"[Indian_Employee_Data].[Employee ID].&[Emp1004]","[Indian_Employee_Data].[Insurance tier].&[Silver]"}) -> Silver | L34: =CUBEVALUE("ThisWorkbookDataModel",$K34,L$29,Slicer_Department) -> 69301 | M34: =CUBEVALUE("ThisWorkbookDataModel",$K34,M$29,Slicer_Department) -> 4200 | N34: =IF(AND($K34="Bronze",ISNUMBER($L34),ISNUMBER($M34)),$M34,NA()) -> #N/A | O34: =IF(AND($K34="Silver",ISNUMBER($L34),ISNUMBER($M34)),$M34,NA()) -> 4200 | P34: =IF(AND($K34="Gold",ISNUMBER($L34),ISNUMBER($M34)),$M34,NA()) -> #N/A | Q34: =IF(AND($K34="Bronze",ISNUMBER($L34),ISNUMBER($N34)),$L34,NA()) -> #N/A | R34: =IF(AND($K34="Silver",ISNUMBER($L34),ISNUMBER($O34)),$L34,NA()) -> 69301 | S34: =IF(AND($K34="Gold",ISNUMBER($L34),ISNUMBER($P34)),$L34,NA()) -> #N/A
J35: =CUBEMEMBER("ThisWorkbookDataModel","[Indian_Employee_Data].[Employee ID].&[Emp1005]") -> Emp1005 | K35: =CUBEMEMBER("ThisWorkbookDataModel",{"[Indian_Employee_Data].[Employee ID].&[Emp1005]","[Indian_Employee_Data].[Insurance tier].&[Silver]"}) -> Silver | L35: =CUBEVALUE("ThisWorkbookDataModel",$K35,L$29,Slicer_Department) -> 69298 | M35: =CUBEVALUE("ThisWorkbookDataModel",$K35,M$29,Slicer_Department) -> 4200 | N35: =IF(AND($K35="Bronze",ISNUMBER($L35),ISNUMBER($M35)),$M35,NA()) -> #N/A | O35: =IF(AND($K35="Silver",ISNUMBER($L35),ISNUMBER($M35)),$M35,NA()) -> 4200 | P35: =IF(AND($K35="Gold",ISNUMBER($L35),ISNUMBER($M35)),$M35,NA()) -> #N/A | Q35: =IF(AND($K35="Bronze",ISNUMBER($L35),ISNUMBER($N35)),$L35,NA()) -> #N/A | R35: =IF(AND($K35="Silver",ISNUMBER($L35),ISNUMBER($O35)),$L35,NA()) -> 69298 | S35: =IF(AND($K35="Gold",ISNUMBER($L35),ISNUMBER($P35)),$L35,NA()) -> #N/A
J36: =CUBEMEMBER("ThisWorkbookDataModel","[Indian_Employee_Data].[Employee ID].&[Emp1006]") -> Emp1006 | K36: =CUBEMEMBER("ThisWorkbookDataModel",{"[Indian_Employee_Data].[Employee ID].&[Emp1006]","[Indian_Employee_Data].[Insurance tier].&[Bronze]"}) -> Bronze | L36: =CUBEVALUE("ThisWorkbookDataModel",$K36,L$29,Slicer_Department) -> 53979 | M36: =CUBEVALUE("ThisWorkbookDataModel",$K36,M$29,Slicer_Department) -> 1500 | N36: =IF(AND($K36="Bronze",ISNUMBER($L36),ISNUMBER($M36)),$M36,NA()) -> 1500 | O36: =IF(AND($K36="Silver",ISNUMBER($L36),ISNUMBER($M36)),$M36,NA()) -> #N/A | P36: =IF(AND($K36="Gold",ISNUMBER($L36),ISNUMBER($M36)),$M36,NA()) -> #N/A | Q36: =IF(AND($K36="Bronze",ISNUMBER($L36),ISNUMBER($N36)),$L36,NA()) -> 53979 | R36: =IF(AND($K36="Silver",ISNUMBER($L36),ISNUMBER($O36)),$L36,NA()) -> #N/A | S36: =IF(AND($K36="Gold",ISNUMBER($L36),ISNUMBER($P36)),$L36,NA()) -> #N/A
J37: =CUBEMEMBER("ThisWorkbookDataModel","[Indian_Employee_Data].[Employee ID].&[Emp1007]") -> Emp1007 | K37: =CUBEMEMBER("ThisWorkbookDataModel",{"[Indian_Employee_Data].[Employee ID].&[Emp1007]","[Indian_Employee_Data].[Insurance tier].&[Bronze]"}) -> Bronze | L37: =CUBEVALUE("ThisWorkbookDataModel",$K37,L$29,Slicer_Department) -> 178221 | M37: =CUBEVALUE("ThisWorkbookDataModel",$K37,M$29,Slicer_Department) -> 9500 | N37: =IF(AND($K37="Bronze",ISNUMBER($L37),ISNUMBER($M37)),$M37,NA()) -> 9500 | O37: =IF(AND($K37="Silver",ISNUMBER($L37),ISNUMBER($M37)),$M37,NA()) -> #N/A | P37: =IF(AND($K37="Gold",ISNUMBER($L37),ISNUMBER($M37)),$M37,NA()) -> #N/A | Q37: =IF(AND($K37="Bronze",ISNUMBER($L37),ISNUMBER($N37)),$L37,NA()) -> 178221 | R37: =IF(AND($K37="Silver",ISNUMBER($L37),ISNUMBER($O37)),$L37,NA()) -> #N/A | S37: =IF(AND($K37="Gold",ISNUMBER($L37),ISNUMBER($P37)),$L37,NA()) -> #N/A
J38: =CUBEMEMBER("ThisWorkbookDataModel","[Indian_Employee_Data].[Employee ID].&[Emp1008]") -> Emp1008 | K38: =CUBEMEMBER("ThisWorkbookDataModel",{"[Indian_Employee_Data].[Employee ID].&[Emp1008]","[Indian_Employee_Data].[Insurance tier].&[Gold]"}) -> Gold | L38: =CUBEVALUE("ThisWorkbookDataModel",$K38,L$29,Slicer_Department) -> 126076 | M38: =CUBEVALUE("ThisWorkbookDataModel",$K38,M$29,Slicer_Department) -> 9000 | N38: =IF(AND($K38="Bronze",ISNUMBER($L38),ISNUMBER($M38)),$M38,NA()) -> #N/A | O38: =IF(AND($K38="Silver",ISNUMBER($L38),ISNUMBER($M38)),$M38,NA()) -> #N/A | P38: =IF(AND($K38="Gold",ISNUMBER($L38),ISNUMBER($M38)),$M38,NA()) -> 9000 | Q38: =IF(AND($K38="Bronze",ISNUMBER($L38),ISNUMBER($N38)),$L38,NA()) -> #N/A | R38: =IF(AND($K38="Silver",ISNUMBER($L38),ISNUMBER($O38)),$L38,NA()) -> #N/A | S38: =IF(AND($K38="Gold",ISNUMBER($L38),ISNUMBER($P38)),$L38,NA()) -> 126076
J39: =CUBEMEMBER("ThisWorkbookDataModel","[Indian_Employee_Data].[Employee ID].&[Emp1009]") -> Emp1009 | K39: =CUBEMEMBER("ThisWorkbookDataModel",{"[Indian_Employee_Data].[Employee ID].&[Emp1009]","[Indian_Employee_Data].[Insurance tier].&[Gold]"}) -> Gold | L39: =CUBEVALUE("ThisWorkbookDataModel",$K39,L$29,Slicer_Department) -> 143984 | M39: =CUBEVALUE("ThisWorkbookDataModel",$K39,M$29,Slicer_Department) -> 6750 | N39: =IF(AND($K39="Bronze",ISNUMBER($L39),ISNUMBER($M39)),$M39,NA()) -> #N/A | O39: =IF(AND($K39="Silver",ISNUMBER($L39),ISNUMBER($M39)),$M39,NA()) -> #N/A | P39: =IF(AND($K39="Gold",ISNUMBER($L39),ISNUMBER($M39)),$M39,NA()) -> 6750 | Q39: =IF(AND($K39="Bronze",ISNUMBER($L39),ISNUMBER($N39)),$L39,NA()) -> #N/A | R39: =IF(AND($K39="Silver",ISNUMBER($L39),ISNUMBER($O39)),$L39,NA()) -> #N/A | S39: =IF(AND($K39="Gold",ISNUMBER($L39),ISNUMBER($P39)),$L39,NA()) -> 143984
J40: =CUBEMEMBER("ThisWorkbookDataModel","[Indian_Employee_Data].[Employee ID].&[Emp1010]") -> Emp1010 | K40: =CUBEMEMBER("ThisWorkbookDataModel",{"[Indian_Employee_Data].[Employee ID].&[Emp1010]","[Indian_Employee_Data].[Insurance tier].&[Bronze]"}) -> Bronze | L40: =CUBEVALUE("ThisWorkbookDataModel",$K40,L$29,Slicer_Department) -> 44275 | M40: =CUBEVALUE("ThisWorkbookDataModel",$K40,M$29,Slicer_Department) -> 1500 | N40: =IF(AND($K40="Bronze",ISNUMBER($L40),ISNUMBER($M40)),$M40,NA()) -> 1500 | O40: =IF(AND($K40="Silver",ISNUMBER($L40),ISNUMBER($M40)),$M40,NA()) -> #N/A | P40: =IF(AND($K40="Gold",ISNUMBER($L40),ISNUMBER($M40)),$M40,NA()) -> #N/A | Q40: =IF(AND($K40="Bronze",ISNUMBER($L40),ISNUMBER($N40)),$L40,NA()) -> 44275 | R40: =IF(AND($K40="Silver",ISNUMBER($L40),ISNUMBER($O40)),$L40,NA()) -> #N/A | S40: =IF(AND($K40="Gold",ISNUMBER($L40),ISNUMBER($P40)),$L40,NA()) -> #N/A
J41: =CUBEMEMBER("ThisWorkbookDataModel","[Indian_Employee_Data].[Employee ID].&[Emp1011]") -> Emp1011 | K41: =CUBEMEMBER("ThisWorkbookDataModel",{"[Indian_Employee_Data].[Employee ID].&[Emp1011]","[Indian_Employee_Data].[Insurance tier].&[Gold]"}) -> Gold | L41: =CUBEVALUE("ThisWorkbookDataModel",$K41,L$29,Slicer_Department) -> 215963 | M41: =CUBEVALUE("ThisWorkbookDataModel",$K41,M$29,Slicer_Department) -> 6750 | N41: =IF(AND($K41="Bronze",ISNUMBER($L41),ISNUMBER($M41)),$M41,NA()) -> #N/A | O41: =IF(AND($K41="Silver",ISNUMBER($L41),ISNUMBER($M41)),$M41,NA()) -> #N/A | P41: =IF(AND($K41="Gold",ISNUMBER($L41),ISNUMBER($M41)),$M41,NA()) -> 6750 | Q41: =IF(AND($K41="Bronze",ISNUMBER($L41),ISNUMBER($N41)),$L41,NA()) -> #N/A | R41: =IF(AND($K41="Silver",ISNUMBER($L41),ISNUMBER($O41)),$L41,NA()) -> #N/A | S41: =IF(AND($K41="Gold",ISNUMBER($L41),ISNUMBER($P41)),$L41,NA()) -> 215963
J42: =CUBEMEMBER("ThisWorkbookDataModel","[Indian_Employee_Data].[Employee ID].&[Emp1012]") -> Emp1012 | K42: =CUBEMEMBER("ThisWorkbookDataModel",{"[Indian_Employee_Data].[Employee ID].&[Emp1012]","[Indian_Employee_Data].[Insurance tier].&[Gold]"}) -> Gold | L42: =CUBEVALUE("ThisWorkbookDataModel",$K42,L$29,Slicer_Department) -> 169682 | M42: =CUBEVALUE("ThisWorkbookDataModel",$K42,M$29,Slicer_Department) -> 6750 | N42: =IF(AND($K42="Bronze",ISNUMBER($L42),ISNUMBER($M42)),$M42,NA()) -> #N/A | O42: =IF(AND($K42="Silver",ISNUMBER($L42),ISNUMBER($M42)),$M42,NA()) -> #N/A | P42: =IF(AND($K42="Gold",ISNUMBER($L42),ISNUMBER($M42)),$M42,NA()) -> 6750 | Q42: =IF(AND($K42="Bronze",ISNUMBER($L42),ISNUMBER($N42)),$L42,NA()) -> #N/A | R42: =IF(AND($K42="Silver",ISNUMBER($L42),ISNUMBER($O42)),$L42,NA()) -> #N/A | S42: =IF(AND($K42="Gold",ISNUMBER($L42),ISNUMBER($P42)),$L42,NA()) -> 169682
J43: =CUBEMEMBER("ThisWorkbookDataModel","[Indian_Employee_Data].[Employee ID].&[Emp1013]") -> Emp1013 | K43: =CUBEMEMBER("ThisWorkbookDataModel",{"[Indian_Employee_Data].[Employee ID].&[Emp1013]","[Indian_Employee_Data].[Insurance tier].&[Silver]"}) -> Silver | L43: =CUBEVALUE("ThisWorkbookDataModel",$K43,L$29,Slicer_Department) -> 75859 | M43: =CUBEVALUE("ThisWorkbookDataModel",$K43,M$29,Slicer_Department) -> 2800 | N43: =IF(AND($K43="Bronze",ISNUMBER($L43),ISNUMBER($M43)),$M43,NA()) -> #N/A | O43: =IF(AND($K43="Silver",ISNUMBER($L43),ISNUMBER($M43)),$M43,NA()) -> 2800 | P43: =IF(AND($K43="Gold",ISNUMBER($L43),ISNUMBER($M43)),$M43,NA()) -> #N/A | Q43: =IF(AND($K43="Bronze",ISNUMBER($L43),ISNUMBER($N43)),$L43,NA()) -> #N/A | R43: =IF(AND($K43="Silver",ISNUMBER($L43),ISNUMBER($O43)),$L43,NA()) -> 75859 | S43: =IF(AND($K43="Gold",ISNUMBER($L43),ISNUMBER($P43)),$L43,NA()) -> #N/A
J44: =CUBEMEMBER("ThisWorkbookDataModel","[Indian_Employee_Data].[Employee ID].&[Emp1014]") -> Emp1014 | K44: =CUBEMEMBER("ThisWorkbookDataModel",{"[Indian_Employee_Data].[Employee ID].&[Emp1014]","[Indian_Employee_Data].[Insurance tier].&[Silver]"}) -> Silver | L44: =CUBEVALUE("ThisWorkbookDataModel",$K44,L$29,Slicer_Department) -> 72427 | M44: =CUBEVALUE("ThisWorkbookDataModel",$K44,M$29,Slicer_Department) -> 4200 | N44: =IF(AND($K44="Bronze",ISNUMBER($L44),ISNUMBER($M44)),$M44,NA()) -> #N/A | O44: =IF(AND($K44="Silver",ISNUMBER($L44),ISNUMBER($M44)),$M44,NA()) -> 4200 | P44: =IF(AND($K44="Gold",ISNUMBER($L44),ISNUMBER($M44)),$M44,NA()) -> #N/A | Q44: =IF(AND($K44="Bronze",ISNUMBER($L44),ISNUMBER($N44)),$L44,NA()) -> #N/A | R44: =IF(AND($K44="Silver",ISNUMBER($L44),ISNUMBER($O44)),$L44,NA()) -> 72427 | S44: =IF(AND($K44="Gold",ISNUMBER($L44),ISNUMBER($P44)),$L44,NA()) -> #N/A
A45: Insurance Tier | B45: Total Monthly Premium Cost | J45: =CUBEMEMBER("ThisWorkbookDataModel","[Indian_Employee_Data].[Employee ID].&[Emp1015]") -> Emp1015 | K45: =CUBEMEMBER("ThisWorkbookDataModel",{"[Indian_Employee_Data].[Employee ID].&[Emp1015]","[Indian_Employee_Data].[Insurance tier].&[Silver]"}) -> Silver | L45: =CUBEVALUE("ThisWorkbookDataModel",$K45,L$29,Slicer_Department) -> 72611 | M45: =CUBEVALUE("ThisWorkbookDataModel",$K45,M$29,Slicer_Department) -> 4200 | N45: =IF(AND($K45="Bronze",ISNUMBER($L45),ISNUMBER($M45)),$M45,NA()) -> #N/A | O45: =IF(AND($K45="Silver",ISNUMBER($L45),ISNUMBER($M45)),$M45,NA()) -> 4200 | P45: =IF(AND($K45="Gold",ISNUMBER($L45),ISNUMBER($M45)),$M45,NA()) -> #N/A | Q45: =IF(AND($K45="Bronze",ISNUMBER($L45),ISNUMBER($N45)),$L45,NA()) -> #N/A | R45: =IF(AND($K45="Silver",ISNUMBER($L45),ISNUMBER($O45)),$L45,NA()) -> 72611 | S45: =IF(AND($K45="Gold",ISNUMBER($L45),ISNUMBER($P45)),$L45,NA()) -> #N/A
A46: Family Floater | B46: 1148700 | J46: =CUBEMEMBER("ThisWorkbookDataModel","[Indian_Employee_Data].[Employee ID].&[Emp1016]") -> Emp1016 | K46: =CUBEMEMBER("ThisWorkbookDataModel",{"[Indian_Employee_Data].[Employee ID].&[Emp1016]","[Indian_Employee_Data].[Insurance tier].&[Silver]"}) -> Silver | L46: =CUBEVALUE("ThisWorkbookDataModel",$K46,L$29,Slicer_Department) -> 86333 | M46: =CUBEVALUE("ThisWorkbookDataModel",$K46,M$29,Slicer_Department) -> 2800 | N46: =IF(AND($K46="Bronze",ISNUMBER($L46),ISNUMBER($M46)),$M46,NA()) -> #N/A | O46: =IF(AND($K46="Silver",ISNUMBER($L46),ISNUMBER($M46)),$M46,NA()) -> 2800 | P46: =IF(AND($K46="Gold",ISNUMBER($L46),ISNUMBER($M46)),$M46,NA()) -> #N/A | Q46: =IF(AND($K46="Bronze",ISNUMBER($L46),ISNUMBER($N46)),$L46,NA()) -> #N/A | R46: =IF(AND($K46="Silver",ISNUMBER($L46),ISNUMBER($O46)),$L46,NA()) -> 86333 | S46: =IF(AND($K46="Gold",ISNUMBER($L46),ISNUMBER($P46)),$L46,NA()) -> #N/A
A47: Individual | B47: 405800 | J47: =CUBEMEMBER("ThisWorkbookDataModel","[Indian_Employee_Data].[Employee ID].&[Emp1017]") -> Emp1017 | K47: =CUBEMEMBER("ThisWorkbookDataModel",{"[Indian_Employee_Data].[Employee ID].&[Emp1017]","[Indian_Employee_Data].[Insurance tier].&[Silver]"}) -> Silver | L47: =CUBEVALUE("ThisWorkbookDataModel",$K47,L$29,Slicer_Department) -> 114734 | M47: =CUBEVALUE("ThisWorkbookDataModel",$K47,M$29,Slicer_Department) -> 4200 | N47: =IF(AND($K47="Bronze",ISNUMBER($L47),ISNUMBER($M47)),$M47,NA()) -> #N/A | O47: =IF(AND($K47="Silver",ISNUMBER($L47),ISNUMBER($M47)),$M47,NA()) -> 4200 | P47: =IF(AND($K47="Gold",ISNUMBER($L47),ISNUMBER($M47)),$M47,NA()) -> #N/A | Q47: =IF(AND($K47="Bronze",ISNUMBER($L47),ISNUMBER($N47)),$L47,NA()) -> #N/A | R47: =IF(AND($K47="Silver",ISNUMBER($L47),ISNUMBER($O47)),$L47,NA()) -> 114734 | S47: =IF(AND($K47="Gold",ISNUMBER($L47),ISNUMBER($P47)),$L47,NA()) -> #N/A
A48: Parents Included | B48: 1028500 | J48: =CUBEMEMBER("ThisWorkbookDataModel","[Indian_Employee_Data].[Employee ID].&[Emp1018]") -> Emp1018 | K48: =CUBEMEMBER("ThisWorkbookDataModel",{"[Indian_Employee_Data].[Employee ID].&[Emp1018]","[Indian_Employee_Data].[Insurance tier].&[Silver]"}) -> Silver | L48: =CUBEVALUE("ThisWorkbookDataModel",$K48,L$29,Slicer_Department) -> 102114 | M48: =CUBEVALUE("ThisWorkbookDataModel",$K48,M$29,Slicer_Department) -> 2800 | N48: =IF(AND($K48="Bronze",ISNUMBER($L48),ISNUMBER($M48)),$M48,NA()) -> #N/A | O48: =IF(AND($K48="Silver",ISNUMBER($L48),ISNUMBER($M48)),$M48,NA()) -> 2800 | P48: =IF(AND($K48="Gold",ISNUMBER($L48),ISNUMBER($M48)),$M48,NA()) -> #N/A | Q48: =IF(AND($K48="Bronze",ISNUMBER($L48),ISNUMBER($N48)),$L48,NA()) -> #N/A | R48: =IF(AND($K48="Silver",ISNUMBER($L48),ISNUMBER($O48)),$L48,NA()) -> 102114 | S48: =IF(AND($K48="Gold",ISNUMBER($L48),ISNUMBER($P48)),$L48,NA()) -> #N/A
A49: Grand Total | B49: 2583000 | J49: =CUBEMEMBER("ThisWorkbookDataModel","[Indian_Employee_Data].[Employee ID].&[Emp1019]") -> Emp1019 | K49: =CUBEMEMBER("ThisWorkbookDataModel",{"[Indian_Employee_Data].[Employee ID].&[Emp1019]","[Indian_Employee_Data].[Insurance tier].&[Silver]"}) -> Silver | L49: =CUBEVALUE("ThisWorkbookDataModel",$K49,L$29,Slicer_Department) -> 84810 | M49: =CUBEVALUE("ThisWorkbookDataModel",$K49,M$29,Slicer_Department) -> 2800 | N49: =IF(AND($K49="Bronze",ISNUMBER($L49),ISNUMBER($M49)),$M49,NA()) -> #N/A | O49: =IF(AND($K49="Silver",ISNUMBER($L49),ISNUMBER($M49)),$M49,NA()) -> 2800 | P49: =IF(AND($K49="Gold",ISNUMBER($L49),ISNUMBER($M49)),$M49,NA()) -> #N/A | Q49: =IF(AND($K49="Bronze",ISNUMBER($L49),ISNUMBER($N49)),$L49,NA()) -> #N/A | R49: =IF(AND($K49="Silver",ISNUMBER($L49),ISNUMBER($O49)),$L49,NA()) -> 84810 | S49: =IF(AND($K49="Gold",ISNUMBER($L49),ISNUMBER($P49)),$L49,NA()) -> #N/A
J50: =CUBEMEMBER("ThisWorkbookDataModel","[Indian_Employee_Data].[Employee ID].&[Emp1020]") -> Emp1020 | K50: =CUBEMEMBER("ThisWorkbookDataModel",{"[Indian_Employee_Data].[Employee ID].&[Emp1020]","[Indian_Employee_Data].[Insurance tier].&[Gold]"}) -> Gold | L50: =CUBEVALUE("ThisWorkbookDataModel",$K50,L$29,Slicer_Department) -> 127755 | M50: =CUBEVALUE("ThisWorkbookDataModel",$K50,M$29,Slicer_Department) -> 6750 | N50: =IF(AND($K50="Bronze",ISNUMBER($L50),ISNUMBER($M50)),$M50,NA()) -> #N/A | O50: =IF(AND($K50="Silver",ISNUMBER($L50),ISNUMBER($M50)),$M50,NA()) -> #N/A | P50: =IF(AND($K50="Gold",ISNUMBER($L50),ISNUMBER($M50)),$M50,NA()) -> 6750 | Q50: =IF(AND($K50="Bronze",ISNUMBER($L50),ISNUMBER($N50)),$L50,NA()) -> #N/A | R50: =IF(AND($K50="Silver",ISNUMBER($L50),ISNUMBER($O50)),$L50,NA()) -> #N/A | S50: =IF(AND($K50="Gold",ISNUMBER($L50),ISNUMBER($P50)),$L50,NA()) -> 127755
J51: =CUBEMEMBER("ThisWorkbookDataModel","[Indian_Employee_Data].[Employee ID].&[Emp1021]") -> Emp1021 | K51: =CUBEMEMBER("ThisWorkbookDataModel",{"[Indian_Employee_Data].[Employee ID].&[Emp1021]","[Indian_Employee_Data].[Insurance tier].&[Silver]"}) -> Silver | L51: =CUBEVALUE("ThisWorkbookDataModel",$K51,L$29,Slicer_Department) -> 67161 | M51: =CUBEVALUE("ThisWorkbookDataModel",$K51,M$29,Slicer_Department) -> 2800 | N51: =IF(AND($K51="Bronze",ISNUMBER($L51),ISNUMBER($M51)),$M51,NA()) -> #N/A | O51: =IF(AND($K51="Silver",ISNUMBER($L51),ISNUMBER($M51)),$M51,NA()) -> 2800 | P51: =IF(AND($K51="Gold",ISNUMBER($L51),ISNUMBER($M51)),$M51,NA()) -> #N/A | Q51: =IF(AND($K51="Bronze",ISNUMBER($L51),ISNUMBER($N51)),$L51,NA()) -> #N/A | R51: =IF(AND($K51="Silver",ISNUMBER($L51),ISNUMBER($O51)),$L51,NA()) -> 67161 | S51: =IF(AND($K51="Gold",ISNUMBER($L51),ISNUMBER($P51)),$L51,NA()) -> #N/A
J52: =CUBEMEMBER("ThisWorkbookDataModel","[Indian_Employee_Data].[Employee ID].&[Emp1022]") -> Emp1022 | K52: =CUBEMEMBER("ThisWorkbookDataModel",{"[Indian_Employee_Data].[Employee ID].&[Emp1022]","[Indian_Employee_Data].[Insurance tier].&[Silver]"}) -> Silver | L52: =CUBEVALUE("ThisWorkbookDataModel",$K52,L$29,Slicer_Department) -> 84916 | M52: =CUBEVALUE("ThisWorkbookDataModel",$K52,M$29,Slicer_Department) -> 4200 | N52: =IF(AND($K52="Bronze",ISNUMBER($L52),ISNUMBER($M52)),$M52,NA()) -> #N/A | O52: =IF(AND($K52="Silver",ISNUMBER($L52),ISNUMBER($M52)),$M52,NA()) -> 4200 | P52: =IF(AND($K52="Gold",ISNUMBER($L52),ISNUMBER($M52)),$M52,NA()) -> #N/A | Q52: =IF(AND($K52="Bronze",ISNUMBER($L52),ISNUMBER($N52)),$L52,NA()) -> #N/A | R52: =IF(AND($K52="Silver",ISNUMBER($L52),ISNUMBER($O52)),$L52,NA()) -> 84916 | S52: =IF(AND($K52="Gold",ISNUMBER($L52),ISNUMBER($P52)),$L52,NA()) -> #N/A
J53: =CUBEMEMBER("ThisWorkbookDataModel","[Indian_Employee_Data].[Employee ID].&[Emp1023]") -> Emp1023 | K53: =CUBEMEMBER("ThisWorkbookDataModel",{"[Indian_Employee_Data].[Employee ID].&[Emp1023]","[Indian_Employee_Data].[Insurance tier].&[Silver]"}) -> Silver | L53: =CUBEVALUE("ThisWorkbookDataModel",$K53,L$29,Slicer_Department) -> 93810 | M53: =CUBEVALUE("ThisWorkbookDataModel",$K53,M$29,Slicer_Department) -> 2800 | N53: =IF(AND($K53="Bronze",ISNUMBER($L53),ISNUMBER($M53)),$M53,NA()) -> #N/A | O53: =IF(AND($K53="Silver",ISNUMBER($L53),ISNUMBER($M53)),$M53,NA()) -> 2800 | P53: =IF(AND($K53="Gold",ISNUMBER($L53),ISNUMBER($M53)),$M53,NA()) -> #N/A | Q53: =IF(AND($K53="Bronze",ISNUMBER($L53),ISNUMBER($N53)),$L53,NA()) -> #N/A | R53: =IF(AND($K53="Silver",ISNUMBER($L53),ISNUMBER($O53)),$L53,NA()) -> 93810 | S53: =IF(AND($K53="Gold",ISNUMBER($L53),ISNUMBER($P53)),$L53,NA()) -> #N/A
J54: =CUBEMEMBER("ThisWorkbookDataModel","[Indian_Employee_Data].[Employee ID].&[Emp1024]") -> Emp1024 | K54: =CUBEMEMBER("ThisWorkbookDataModel",{"[Indian_Employee_Data].[Employee ID].&[Emp1024]","[Indian_Employee_Data].[Insurance tier].&[Silver]"}) -> Silver | L54: =CUBEVALUE("ThisWorkbookDataModel",$K54,L$29,Slicer_Department) -> 105288 | M54: =CUBEVALUE("ThisWorkbookDataModel",$K54,M$29,Slicer_Department) -> 4200 | N54: =IF(AND($K54="Bronze",ISNUMBER($L54),ISNUMBER($M54)),$M54,NA()) -> #N/A | O54: =IF(AND($K54="Silver",ISNUMBER($L54),ISNUMBER($M54)),$M54,NA()) -> 4200 | P54: =IF(AND($K54="Gold",ISNUMBER($L54),ISNUMBER($M54)),$M54,NA()) -> #N/A | Q54: =IF(AND($K54="Bronze",ISNUMBER($L54),ISNUMBER($N54)),$L54,NA()) -> #N/A | R54: =IF(AND($K54="Silver",ISNUMBER($L54),ISNUMBER($O54)),$L54,NA()) -> 105288 | S54: =IF(AND($K54="Gold",ISNUMBER($L54),ISNUMBER($P54)),$L54,NA()) -> #N/A
J55: =CUBEMEMBER("ThisWorkbookDataModel","[Indian_Employee_Data].[Employee ID].&[Emp1025]") -> Emp1025 | K55: =CUBEMEMBER("ThisWorkbookDataModel",{"[Indian_Employee_Data].[Employee ID].&[Emp1025]","[Indian_Employee_Data].[Insurance tier].&[Gold]"}) -> Gold | L55: =CUBEVALUE("ThisWorkbookDataModel",$K55,L$29,Slicer_Department) -> 159056 | M55: =CUBEVALUE("ThisWorkbookDataModel",$K55,M$29,Slicer_Department) -> 9000 | N55: =IF(AND($K55="Bronze",ISNUMBER($L55),ISNUMBER($M55)),$M55,NA()) -> #N/A | O55: =IF(AND($K55="Silver",ISNUMBER($L55),ISNUMBER($M55)),$M55,NA()) -> #N/A | P55: =IF(AND($K55="Gold",ISNUMBER($L55),ISNUMBER($M55)),$M55,NA()) -> 9000 | Q55: =IF(AND($K55="Bronze",ISNUMBER($L55),ISNUMBER($N55)),$L55,NA()) -> #N/A | R55: =IF(AND($K55="Silver",ISNUMBER($L55),ISNUMBER($O55)),$L55,NA()) -> #N/A | S55: =IF(AND($K55="Gold",ISNUMBER($L55),ISNUMBER($P55)),$L55,NA()) -> 159056
J56: =CUBEMEMBER("ThisWorkbookDataModel","[Indian_Employee_Data].[Employee ID].&[Emp1026]") -> Emp1026 | K56: =CUBEMEMBER("ThisWorkbookDataModel",{"[Indian_Employee_Data].[Employee ID].&[Emp1026]","[Indian_Employee_Data].[Insurance tier].&[Silver]"}) -> Silver | L56: =CUBEVALUE("ThisWorkbookDataModel",$K56,L$29,Slicer_Department) -> 74460 | M56: =CUBEVALUE("ThisWorkbookDataModel",$K56,M$29,Slicer_Department) -> 4200 | N56: =IF(AND($K56="Bronze",ISNUMBER($L56),ISNUMBER($M56)),$M56,NA()) -> #N/A | O56: =IF(AND($K56="Silver",ISNUMBER($L56),ISNUMBER($M56)),$M56,NA()) -> 4200 | P56: =IF(AND($K56="Gold",ISNUMBER($L56),ISNUMBER($M56)),$M56,NA()) -> #N/A | Q56: =IF(AND($K56="Bronze",ISNUMBER($L56),ISNUMBER($N56)),$L56,NA()) -> #N/A | R56: =IF(AND($K56="Silver",ISNUMBER($L56),ISNUMBER($O56)),$L56,NA()) -> 74460 | S56: =IF(AND($K56="Gold",ISNUMBER($L56),ISNUMBER($P56)),$L56,NA()) -> #N/A
J57: =CUBEMEMBER("ThisWorkbookDataModel","[Indian_Employee_Data].[Employee ID].&[Emp1027]") -> Emp1027 | K57: =CUBEMEMBER("ThisWorkbookDataModel",{"[Indian_Employee_Data].[Employee ID].&[Emp1027]","[Indian_Employee_Data].[Insurance tier].&[Silver]"}) -> Silver | L57: =CUBEVALUE("ThisWorkbookDataModel",$K57,L$29,Slicer_Department) -> 113244 | M57: =CUBEVALUE("ThisWorkbookDataModel",$K57,M$29,Slicer_Department) -> 4200 | N57: =IF(AND($K57="Bronze",ISNUMBER($L57),ISNUMBER($M57)),$M57,NA()) -> #N/A | O57: =IF(AND($K57="Silver",ISNUMBER($L57),ISNUMBER($M57)),$M57,NA()) -> 4200 | P57: =IF(AND($K57="Gold",ISNUMBER($L57),ISNUMBER($M57)),$M57,NA()) -> #N/A | Q57: =IF(AND($K57="Bronze",ISNUMBER($L57),ISNUMBER($N57)),$L57,NA()) -> #N/A | R57: =IF(AND($K57="Silver",ISNUMBER($L57),ISNUMBER($O57)),$L57,NA()) -> 113244 | S57: =IF(AND($K57="Gold",ISNUMBER($L57),ISNUMBER($P57)),$L57,NA()) -> #N/A
J58: =CUBEMEMBER("ThisWorkbookDataModel","[Indian_Employee_Data].[Employee ID].&[Emp1028]") -> Emp1028 | K58: =CUBEMEMBER("ThisWorkbookDataModel",{"[Indian_Employee_Data].[Employee ID].&[Emp1028]","[Indian_Employee_Data].[Insurance tier].&[Gold]"}) -> Gold | L58: =CUBEVALUE("ThisWorkbookDataModel",$K58,L$29,Slicer_Department) -> 124732 | M58: =CUBEVALUE("ThisWorkbookDataModel",$K58,M$29,Slicer_Department) -> 6750 | N58: =IF(AND($K58="Bronze",ISNUMBER($L58),ISNUMBER($M58)),$M58,NA()) -> #N/A | O58: =IF(AND($K58="Silver",ISNUMBER($L58),ISNUMBER($M58)),$M58,NA()) -> #N/A | P58: =IF(AND($K58="Gold",ISNUMBER($L58),ISNUMBER($M58)),$M58,NA()) -> 6750 | Q58: =IF(AND($K58="Bronze",ISNUMBER($L58),ISNUMBER($N58)),$L58,NA()) -> #N/A | R58: =IF(AND($K58="Silver",ISNUMBER($L58),ISNUMBER($O58)),$L58,NA()) -> #N/A | S58: =IF(AND($K58="Gold",ISNUMBER($L58),ISNUMBER($P58)),$L58,NA()) -> 124732
J59: =CUBEMEMBER("ThisWorkbookDataModel","[Indian_Employee_Data].[Employee ID].&[Emp1029]") -> Emp1029 | K59: =CUBEMEMBER("ThisWorkbookDataModel",{"[Indian_Employee_Data].[Employee ID].&[Emp1029]","[Indian_Employee_Data].[Insurance tier].&[Bronze]"}) -> Bronze | L59: =CUBEVALUE("ThisWorkbookDataModel",$K59,L$29,Slicer_Department) -> 51444 | M59: =CUBEVALUE("ThisWorkbookDataModel",$K59,M$29,Slicer_Department) -> 1500 | N59: =IF(AND($K59="Bronze",ISNUMBER($L59),ISNUMBER($M59)),$M59,NA()) -> 1500 | O59: =IF(AND($K59="Silver",ISNUMBER($L59),ISNUMBER($M59)),$M59,NA()) -> #N/A | P59: =IF(AND($K59="Gold",ISNUMBER($L59),ISNUMBER($M59)),$M59,NA()) -> #N/A | Q59: =IF(AND($K59="Bronze",ISNUMBER($L59),ISNUMBER($N59)),$L59,NA()) -> 51444 | R59: =IF(AND($K59="Silver",ISNUMBER($L59),ISNUMBER($O59)),$L59,NA()) -> #N/A | S59: =IF(AND($K59="Gold",ISNUMBER($L59),ISNUMBER($P59)),$L59,NA()) -> #N/A
J60: =CUBEMEMBER("ThisWorkbookDataModel","[Indian_Employee_Data].[Employee ID].&[Emp1030]") -> Emp1030 | K60: =CUBEMEMBER("ThisWorkbookDataModel",{"[Indian_Employee_Data].[Employee ID].&[Emp1030]","[Indian_Employee_Data].[Insurance tier].&[Gold]"}) -> Gold | L60: =CUBEVALUE("ThisWorkbookDataModel",$K60,L$29,Slicer_Department) -> 127079 | M60: =CUBEVALUE("ThisWorkbookDataModel",$K60,M$29,Slicer_Department) -> 6750 | N60: =IF(AND($K60="Bronze",ISNUMBER($L60),ISNUMBER($M60)),$M60,NA()) -> #N/A | O60: =IF(AND($K60="Silver",ISNUMBER($L60),ISNUMBER($M60)),$M60,NA()) -> #N/A | P60: =IF(AND($K60="Gold",ISNUMBER($L60),ISNUMBER($M60)),$M60,NA()) -> 6750 | Q60: =IF(AND($K60="Bronze",ISNUMBER($L60),ISNUMBER($N60)),$L60,NA()) -> #N/A | R60: =IF(AND($K60="Silver",ISNUMBER($L60),ISNUMBER($O60)),$L60,NA()) -> #N/A | S60: =IF(AND($K60="Gold",ISNUMBER($L60),ISNUMBER($P60)),$L60,NA()) -> 127079
J61: =CUBEMEMBER("ThisWorkbookDataModel","[Indian_Employee_Data].[Employee ID].&[Emp1031]") -> Emp1031 | K61: =CUBEMEMBER("ThisWorkbookDataModel",{"[Indian_Employee_Data].[Employee ID].&[Emp1031]","[Indian_Employee_Data].[Insurance tier].&[Silver]"}) -> Silver | L61: =CUBEVALUE("ThisWorkbookDataModel",$K61,L$29,Slicer_Department) -> 71087 | M61: =CUBEVALUE("ThisWorkbookDataModel",$K61,M$29,Slicer_Department) -> 2800 | N61: =IF(AND($K61="Bronze",ISNUMBER($L61),ISNUMBER($M61)),$M61,NA()) -> #N/A | O61: =IF(AND($K61="Silver",ISNUMBER($L61),ISNUMBER($M61)),$M61,NA()) -> 2800 | P61: =IF(AND($K61="Gold",ISNUMBER($L61),ISNUMBER($M61)),$M61,NA()) -> #N/A | Q61: =IF(AND($K61="Bronze",ISNUMBER($L61),ISNUMBER($N61)),$L61,NA()) -> #N/A | R61: =IF(AND($K61="Silver",ISNUMBER($L61),ISNUMBER($O61)),$L61,NA()) -> 71087 | S61: =IF(AND($K61="Gold",ISNUMBER($L61),ISNUMBER($P61)),$L61,NA()) -> #N/A
J62: =CUBEMEMBER("ThisWorkbookDataModel","[Indian_Employee_Data].[Employee ID].&[Emp1032]") -> Emp1032 | K62: =CUBEMEMBER("ThisWorkbookDataModel",{"[Indian_Employee_Data].[Employee ID].&[Emp1032]","[Indian_Employee_Data].[Insurance tier].&[Bronze]"}) -> Bronze | L62: =CUBEVALUE("ThisWorkbookDataModel",$K62,L$29,Slicer_Department) -> 55377 | M62: =CUBEVALUE("ThisWorkbookDataModel",$K62,M$29,Slicer_Department) -> 1500 | N62: =IF(AND($K62="Bronze",ISNUMBER($L62),ISNUMBER($M62)),$M62,NA()) -> 1500 | O62: =IF(AND($K62="Silver",ISNUMBER($L62),ISNUMBER($M62)),$M62,NA()) -> #N/A | P62: =IF(AND($K62="Gold",ISNUMBER($L62),ISNUMBER($M62)),$M62,NA()) -> #N/A | Q62: =IF(AND($K62="Bronze",ISNUMBER($L62),ISNUMBER($N62)),$L62,NA()) -> 55377 | R62: =IF(AND($K62="Silver",ISNUMBER($L62),ISNUMBER($O62)),$L62,NA()) -> #N/A | S62: =IF(AND($K62="Gold",ISNUMBER($L62),ISNUMBER($P62)),$L62,NA()) -> #N/A
J63: =CUBEMEMBER("ThisWorkbookDataModel","[Indian_Employee_Data].[Employee ID].&[Emp1033]") -> Emp1033 | K63: =CUBEMEMBER("ThisWorkbookDataModel",{"[Indian_Employee_Data].[Employee ID].&[Emp1033]","[Indian_Employee_Data].[Insurance tier].&[Gold]"}) -> Gold | L63: =CUBEVALUE("ThisWorkbookDataModel",$K63,L$29,Slicer_Department) -> 205638 | M63: =CUBEVALUE("ThisWorkbookDataModel",$K63,M$29,Slicer_Department) -> 6750 | N63: =IF(AND($K63="Bronze",ISNUMBER($L63),ISNUMBER($M63)),$M63,NA()) -> #N/A | O63: =IF(AND($K63="Silver",ISNUMBER($L63),ISNUMBER($M63)),$M63,NA()) -> #N/A | P63: =IF(AND($K63="Gold",ISNUMBER($L63),ISNUMBER($M63)),$M63,NA()) -> 6750 | Q63: =IF(AND($K63="Bronze",ISNUMBER($L63),ISNUMBER($N63)),$L63,NA()) -> #N/A | R63: =IF(AND($K63="Silver",ISNUMBER($L63),ISNUMBER($O63)),$L63,NA()) -> #N/A | S63: =IF(AND($K63="Gold",ISNUMBER($L63),ISNUMBER($P63)),$L63,NA()) -> 205638
J64: =CUBEMEMBER("ThisWorkbookDataModel","[Indian_Employee_Data].[Employee ID].&[Emp1034]") -> Emp1034 | K64: =CUBEMEMBER("ThisWorkbookDataModel",{"[Indian_Employee_Data].[Employee ID].&[Emp1034]","[Indian_Employee_Data].[Insurance tier].&[Gold]"}) -> Gold | L64: =CUBEVALUE("ThisWorkbookDataModel",$K64,L$29,Slicer_Department) -> 213624 | M64: =CUBEVALUE("ThisWorkbookDataModel",$K64,M$29,Slicer_Department) -> 6750 | N64: =IF(AND($K64="Bronze",ISNUMBER($L64),ISNUMBER($M64)),$M64,NA()) -> #N/A | O64: =IF(AND($K64="Silver",ISNUMBER($L64),ISNUMBER($M64)),$M64,NA()) -> #N/A | P64: =IF(AND($K64="Gold",ISNUMBER($L64),ISNUMBER($M64)),$M64,NA()) -> 6750 | Q64: =IF(AND($K64="Bronze",ISNUMBER($L64),ISNUMBER($N64)),$L64,NA()) -> #N/A | R64: =IF(AND($K64="Silver",ISNUMBER($L64),ISNUMBER($O64)),$L64,NA()) -> #N/A | S64: =IF(AND($K64="Gold",ISNUMBER($L64),ISNUMBER($P64)),$L64,NA()) -> 213624
J65: =CUBEMEMBER("ThisWorkbookDataModel","[Indian_Employee_Data].[Employee ID].&[Emp1035]") -> Emp1035 | K65: =CUBEMEMBER("ThisWorkbookDataModel",{"[Indian_Employee_Data].[Employee ID].&[Emp1035]","[Indian_Employee_Data].[Insurance tier].&[Gold]"}) -> Gold | L65: =CUBEVALUE("ThisWorkbookDataModel",$K65,L$29,Slicer_Department) -> 164112 | M65: =CUBEVALUE("ThisWorkbookDataModel",$K65,M$29,Slicer_Department) -> 6750 | N65: =IF(AND($K65="Bronze",ISNUMBER($L65),ISNUMBER($M65)),$M65,NA()) -> #N/A | O65: =IF(AND($K65="Silver",ISNUMBER($L65),ISNUMBER($M65)),$M65,NA()) -> #N/A | P65: =IF(AND($K65="Gold",ISNUMBER($L65),ISNUMBER($M65)),$M65,NA()) -> 6750 | Q65: =IF(AND($K65="Bronze",ISNUMBER($L65),ISNUMBER($N65)),$L65,NA()) -> #N/A | R65: =IF(AND($K65="Silver",ISNUMBER($L65),ISNUMBER($O65)),$L65,NA()) -> #N/A | S65: =IF(AND($K65="Gold",ISNUMBER($L65),ISNUMBER($P65)),$L65,NA()) -> 164112
J66: =CUBEMEMBER("ThisWorkbookDataModel","[Indian_Employee_Data].[Employee ID].&[Emp1036]") -> Emp1036 | K66: =CUBEMEMBER("ThisWorkbookDataModel",{"[Indian_Employee_Data].[Employee ID].&[Emp1036]","[Indian_Employee_Data].[Insurance tier].&[Silver]"}) -> Silver | L66: =CUBEVALUE("ThisWorkbookDataModel",$K66,L$29,Slicer_Department) -> 86377 | M66: =CUBEVALUE("ThisWorkbookDataModel",$K66,M$29,Slicer_Department) -> 4200 | N66: =IF(AND($K66="Bronze",ISNUMBER($L66),ISNUMBER($M66)),$M66,NA()) -> #N/A | O66: =IF(AND($K66="Silver",ISNUMBER($L66),ISNUMBER($M66)),$M66,NA()) -> 4200 | P66: =IF(AND($K66="Gold",ISNUMBER($L66),ISNUMBER($M66)),$M66,NA()) -> #N/A | Q66: =IF(AND($K66="Bronze",ISNUMBER($L66),ISNUMBER($N66)),$L66,NA()) -> #N/A | R66: =IF(AND($K66="Silver",ISNUMBER($L66),ISNUMBER($O66)),$L66,NA()) -> 86377 | S66: =IF(AND($K66="Gold",ISNUMBER($L66),ISNUMBER($P66)),$L66,NA()) -> #N/A
J67: =CUBEMEMBER("ThisWorkbookDataModel","[Indian_Employee_Data].[Employee ID].&[Emp1037]") -> Emp1037 | K67: =CUBEMEMBER("ThisWorkbookDataModel",{"[Indian_Employee_Data].[Employee ID].&[Emp1037]","[Indian_Employee_Data].[Insurance tier].&[Silver]"}) -> Silver | L67: =CUBEVALUE("ThisWorkbookDataModel",$K67,L$29,Slicer_Department) -> 61095 | M67: =CUBEVALUE("ThisWorkbookDataModel",$K67,M$29,Slicer_Department) -> 2800 | N67: =IF(AND($K67="Bronze",ISNUMBER($L67),ISNUMBER($M67)),$M67,NA()) -> #N/A | O67: =IF(AND($K67="Silver",ISNUMBER($L67),ISNUMBER($M67)),$M67,NA()) -> 2800 | P67: =IF(AND($K67="Gold",ISNUMBER($L67),ISNUMBER($M67)),$M67,NA()) -> #N/A | Q67: =IF(AND($K67="Bronze",ISNUMBER($L67),ISNUMBER($N67)),$L67,NA()) -> #N/A | R67: =IF(AND($K67="Silver",ISNUMBER($L67),ISNUMBER($O67)),$L67,NA()) -> 61095 | S67: =IF(AND($K67="Gold",ISNUMBER($L67),ISNUMBER($P67)),$L67,NA()) -> #N/A
J68: =CUBEMEMBER("ThisWorkbookDataModel","[Indian_Employee_Data].[Employee ID].&[Emp1038]") -> Emp1038 | K68: =CUBEMEMBER("ThisWorkbookDataModel",{"[Indian_Employee_Data].[Employee ID].&[Emp1038]","[Indian_Employee_Data].[Insurance tier].&[Gold]"}) -> Gold | L68: =CUBEVALUE("ThisWorkbookDataModel",$K68,L$29,Slicer_Department) -> 139741 | M68: =CUBEVALUE("ThisWorkbookDataModel",$K68,M$29,Slicer_Department) -> 6750 | N68: =IF(AND($K68="Bronze",ISNUMBER($L68),ISNUMBER($M68)),$M68,NA()) -> #N/A | O68: =IF(AND($K68="Silver",ISNUMBER($L68),ISNUMBER($M68)),$M68,NA()) -> #N/A | P68: =IF(AND($K68="Gold",ISNUMBER($L68),ISNUMBER($M68)),$M68,NA()) -> 6750 | Q68: =IF(AND($K68="Bronze",ISNUMBER($L68),ISNUMBER($N68)),$L68,NA()) -> #N/A | R68: =IF(AND($K68="Silver",ISNUMBER($L68),ISNUMBER($O68)),$L68,NA()) -> #N/A | S68: =IF(AND($K68="Gold",ISNUMBER($L68),ISNUMBER($P68)),$L68,NA()) -> 139741
J69: =CUBEMEMBER("ThisWorkbookDataModel","[Indian_Employee_Data].[Employee ID].&[Emp1039]") -> Emp1039 | K69: =CUBEMEMBER("ThisWorkbookDataModel",{"[Indian_Employee_Data].[Employee ID].&[Emp1039]","[Indian_Employee_Data].[Insurance tier].&[Silver]"}) -> Silver | L69: =CUBEVALUE("ThisWorkbookDataModel",$K69,L$29,Slicer_Department) -> 103186 | M69: =CUBEVALUE("ThisWorkbookDataModel",$K69,M$29,Slicer_Department) -> 2800 | N69: =IF(AND($K69="Bronze",ISNUMBER($L69),ISNUMBER($M69)),$M69,NA()) -> #N/A | O69: =IF(AND($K69="Silver",ISNUMBER($L69),ISNUMBER($M69)),$M69,NA()) -> 2800 | P69: =IF(AND($K69="Gold",ISNUMBER($L69),ISNUMBER($M69)),$M69,NA()) -> #N/A | Q69: =IF(AND($K69="Bronze",ISNUMBER($L69),ISNUMBER($N69)),$L69,NA()) -> #N/A | R69: =IF(AND($K69="Silver",ISNUMBER($L69),ISNUMBER($O69)),$L69,NA()) -> 103186 | S69: =IF(AND($K69="Gold",ISNUMBER($L69),ISNUMBER($P69)),$L69,NA()) -> #N/A
J70: =CUBEMEMBER("ThisWorkbookDataModel","[Indian_Employee_Data].[Employee ID].&[Emp1040]") -> Emp1040 | K70: =CUBEMEMBER("ThisWorkbookDataModel",{"[Indian_Employee_Data].[Employee ID].&[Emp1040]","[Indian_Employee_Data].[Insurance tier].&[Silver]"}) -> Silver | L70: =CUBEVALUE("ThisWorkbookDataModel",$K70,L$29,Slicer_Department) -> 64758 | M70: =CUBEVALUE("ThisWorkbookDataModel",$K70,M$29,Slicer_Department) -> 4200 | N70: =IF(AND($K70="Bronze",ISNUMBER($L70),ISNUMBER($M70)),$M70,NA()) -> #N/A | O70: =IF(AND($K70="Silver",ISNUMBER($L70),ISNUMBER($M70)),$M70,NA()) -> 4200 | P70: =IF(AND($K70="Gold",ISNUMBER($L70),ISNUMBER($M70)),$M70,NA()) -> #N/A | Q70: =IF(AND($K70="Bronze",ISNUMBER($L70),ISNUMBER($N70)),$L70,NA()) -> #N/A | R70: =IF(AND($K70="Silver",ISNUMBER($L70),ISNUMBER($O70)),$L70,NA()) -> 64758 | S70: =IF(AND($K70="Gold",ISNUMBER($L70),ISNUMBER($P70)),$L70,NA()) -> #N/A
J71: =CUBEMEMBER("ThisWorkbookDataModel","[Indian_Employee_Data].[Employee ID].&[Emp1041]") -> Emp1041 | K71: =CUBEMEMBER("ThisWorkbookDataModel",{"[Indian_Employee_Data].[Employee ID].&[Emp1041]","[Indian_Employee_Data].[Insurance tier].&[Silver]"}) -> Silver | L71: =CUBEVALUE("ThisWorkbookDataModel",$K71,L$29,Slicer_Department) -> 110588 | M71: =CUBEVALUE("ThisWorkbookDataModel",$K71,M$29,Slicer_Department) -> 2800 | N71: =IF(AND($K71="Bronze",ISNUMBER($L71),ISNUMBER($M71)),$M71,NA()) -> #N/A | O71: =IF(AND($K71="Silver",ISNUMBER($L71),ISNUMBER($M71)),$M71,NA()) -> 2800 | P71: =IF(AND($K71="Gold",ISNUMBER($L71),ISNUMBER($M71)),$M71,NA()) -> #N/A | Q71: =IF(AND($K71="Bronze",ISNUMBER($L71),ISNUMBER($N71)),$L71,NA()) -> #N/A | R71: =IF(AND($K71="Silver",ISNUMBER($L71),ISNUMBER($O71)),$L71,NA()) -> 110588 | S71: =IF(AND($K71="Gold",ISNUMBER($L71),ISNUMBER($P71)),$L71,NA()) -> #N/A
J72: =CUBEMEMBER("ThisWorkbookDataModel","[Indian_Employee_Data].[Employee ID].&[Emp1042]") -> Emp1042 | K72: =CUBEMEMBER("ThisWorkbookDataModel",{"[Indian_Employee_Data].[Employee ID].&[Emp1042]","[Indian_Employee_Data].[Insurance tier].&[Bronze]"}) -> Bronze | L72: =CUBEVALUE("ThisWorkbookDataModel",$K72,L$29,Slicer_Department) -> 48451 | M72: =CUBEVALUE("ThisWorkbookDataModel",$K72,M$29,Slicer_Department) -> 1500 | N72: =IF(AND($K72="Bronze",ISNUMBER($L72),ISNUMBER($M72)),$M72,NA()) -> 1500 | O72: =IF(AND($K72="Silver",ISNUMBER($L72),ISNUMBER($M72)),$M72,NA()) -> #N/A | P72: =IF(AND($K72="Gold",ISNUMBER($L72),ISNUMBER($M72)),$M72,NA()) -> #N/A | Q72: =IF(AND($K72="Bronze",ISNUMBER($L72),ISNUMBER($N72)),$L72,NA()) -> 48451 | R72: =IF(AND($K72="Silver",ISNUMBER($L72),ISNUMBER($O72)),$L72,NA()) -> #N/A | S72: =IF(AND($K72="Gold",ISNUMBER($L72),ISNUMBER($P72)),$L72,NA()) -> #N/A
J73: =CUBEMEMBER("ThisWorkbookDataModel","[Indian_Employee_Data].[Employee ID].&[Emp1043]") -> Emp1043 | K73: =CUBEMEMBER("ThisWorkbookDataModel",{"[Indian_Employee_Data].[Employee ID].&[Emp1043]","[Indian_Employee_Data].[Insurance tier].&[Gold]"}) -> Gold | L73: =CUBEVALUE("ThisWorkbookDataModel",$K73,L$29,Slicer_Department) -> 190913 | M73: =CUBEVALUE("ThisWorkbookDataModel",$K73,M$29,Slicer_Department) -> 9000 | N73: =IF(AND($K73="Bronze",ISNUMBER($L73),ISNUMBER($M73)),$M73,NA()) -> #N/A | O73: =IF(AND($K73="Silver",ISNUMBER($L73),ISNUMBER($M73)),$M73,NA()) -> #N/A | P73: =IF(AND($K73="Gold",ISNUMBER($L73),ISNUMBER($M73)),$M73,NA()) -> 9000 | Q73: =IF(AND($K73="Bronze",ISNUMBER($L73),ISNUMBER($N73)),$L73,NA()) -> #N/A | R73: =IF(AND($K73="Silver",ISNUMBER($L73),ISNUMBER($O73)),$L73,NA()) -> #N/A | S73: =IF(AND($K73="Gold",ISNUMBER($L73),ISNUMBER($P73)),$L73,NA()) -> 190913
J74: =CUBEMEMBER("ThisWorkbookDataModel","[Indian_Employee_Data].[Employee ID].&[Emp1044]") -> Emp1044 | K74: =CUBEMEMBER("ThisWorkbookDataModel",{"[Indian_Employee_Data].[Employee ID].&[Emp1044]","[Indian_Employee_Data].[Insurance tier].&[Bronze]"}) -> Bronze | L74: =CUBEVALUE("ThisWorkbookDataModel",$K74,L$29,Slicer_Department) -> 81071 | M74: =CUBEVALUE("ThisWorkbookDataModel",$K74,M$29,Slicer_Department) -> 9500 | N74: =IF(AND($K74="Bronze",ISNUMBER($L74),ISNUMBER($M74)),$M74,NA()) -> 9500 | O74: =IF(AND($K74="Silver",ISNUMBER($L74),ISNUMBER($M74)),$M74,NA()) -> #N/A | P74: =IF(AND($K74="Gold",ISNUMBER($L74),ISNUMBER($M74)),$M74,NA()) -> #N/A | Q74: =IF(AND($K74="Bronze",ISNUMBER($L74),ISNUMBER($N74)),$L74,NA()) -> 81071 | R74: =IF(AND($K74="Silver",ISNUMBER($L74),ISNUMBER($O74)),$L74,NA()) -> #N/A | S74: =IF(AND($K74="Gold",ISNUMBER($L74),ISNUMBER($P74)),$L74,NA()) -> #N/A
J75: =CUBEMEMBER("ThisWorkbookDataModel","[Indian_Employee_Data].[Employee ID].&[Emp1045]") -> Emp1045 | K75: =CUBEMEMBER("ThisWorkbookDataModel",{"[Indian_Employee_Data].[Employee ID].&[Emp1045]","[Indian_Employee_Data].[Insurance tier].&[Gold]"}) -> Gold | L75: =CUBEVALUE("ThisWorkbookDataModel",$K75,L$29,Slicer_Department) -> 136013 | M75: =CUBEVALUE("ThisWorkbookDataModel",$K75,M$29,Slicer_Department) -> 9000 | N75: =IF(AND($K75="Bronze",ISNUMBER($L75),ISNUMBER($M75)),$M75,NA()) -> #N/A | O75: =IF(AND($K75="Silver",ISNUMBER($L75),ISNUMBER($M75)),$M75,NA()) -> #N/A | P75: =IF(AND($K75="Gold",ISNUMBER($L75),ISNUMBER($M75)),$M75,NA()) -> 9000 | Q75: =IF(AND($K75="Bronze",ISNUMBER($L75),ISNUMBER($N75)),$L75,NA()) -> #N/A | R75: =IF(AND($K75="Silver",ISNUMBER($L75),ISNUMBER($O75)),$L75,NA()) -> #N/A | S75: =IF(AND($K75="Gold",ISNUMBER($L75),ISNUMBER($P75)),$L75,NA()) -> 136013
J76: =CUBEMEMBER("ThisWorkbookDataModel","[Indian_Employee_Data].[Employee ID].&[Emp1046]") -> Emp1046 | K76: =CUBEMEMBER("ThisWorkbookDataModel",{"[Indian_Employee_Data].[Employee ID].&[Emp1046]","[Indian_Employee_Data].[Insurance tier].&[Silver]"}) -> Silver | L76: =CUBEVALUE("ThisWorkbookDataModel",$K76,L$29,Slicer_Department) -> 87214 | M76: =CUBEVALUE("ThisWorkbookDataModel",$K76,M$29,Slicer_Department) -> 4200 | N76: =IF(AND($K76="Bronze",ISNUMBER($L76),ISNUMBER($M76)),$M76,NA()) -> #N/A | O76: =IF(AND($K76="Silver",ISNUMBER($L76),ISNUMBER($M76)),$M76,NA()) -> 4200 | P76: =IF(AND($K76="Gold",ISNUMBER($L76),ISNUMBER($M76)),$M76,NA()) -> #N/A | Q76: =IF(AND($K76="Bronze",ISNUMBER($L76),ISNUMBER($N76)),$L76,NA()) -> #N/A | R76: =IF(AND($K76="Silver",ISNUMBER($L76),ISNUMBER($O76)),$L76,NA()) -> 87214 | S76: =IF(AND($K76="Gold",ISNUMBER($L76),ISNUMBER($P76)),$L76,NA()) -> #N/A
J77: =CUBEMEMBER("ThisWorkbookDataModel","[Indian_Employee_Data].[Employee ID].&[Emp1048]") -> Emp1048 | K77: =CUBEMEMBER("ThisWorkbookDataModel",{"[Indian_Employee_Data].[Employee ID].&[Emp1048]","[Indian_Employee_Data].[Insurance tier].&[Silver]"}) -> Silver | L77: =CUBEVALUE("ThisWorkbookDataModel",$K77,L$29,Slicer_Department) -> 117895 | M77: =CUBEVALUE("ThisWorkbookDataModel",$K77,M$29,Slicer_Department) -> 2800 | N77: =IF(AND($K77="Bronze",ISNUMBER($L77),ISNUMBER($M77)),$M77,NA()) -> #N/A | O77: =IF(AND($K77="Silver",ISNUMBER($L77),ISNUMBER($M77)),$M77,NA()) -> 2800 | P77: =IF(AND($K77="Gold",ISNUMBER($L77),ISNUMBER($M77)),$M77,NA()) -> #N/A | Q77: =IF(AND($K77="Bronze",ISNUMBER($L77),ISNUMBER($N77)),$L77,NA()) -> #N/A | R77: =IF(AND($K77="Silver",ISNUMBER($L77),ISNUMBER($O77)),$L77,NA()) -> 117895 | S77: =IF(AND($K77="Gold",ISNUMBER($L77),ISNUMBER($P77)),$L77,NA()) -> #N/A
J78: =CUBEMEMBER("ThisWorkbookDataModel","[Indian_Employee_Data].[Employee ID].&[Emp1049]") -> Emp1049 | K78: =CUBEMEMBER("ThisWorkbookDataModel",{"[Indian_Employee_Data].[Employee ID].&[Emp1049]","[Indian_Employee_Data].[Insurance tier].&[Silver]"}) -> Silver | L78: =CUBEVALUE("ThisWorkbookDataModel",$K78,L$29,Slicer_Department) -> 72779 | M78: =CUBEVALUE("ThisWorkbookDataModel",$K78,M$29,Slicer_Department) -> 2800 | N78: =IF(AND($K78="Bronze",ISNUMBER($L78),ISNUMBER($M78)),$M78,NA()) -> #N/A | O78: =IF(AND($K78="Silver",ISNUMBER($L78),ISNUMBER($M78)),$M78,NA()) -> 2800 | P78: =IF(AND($K78="Gold",ISNUMBER($L78),ISNUMBER($M78)),$M78,NA()) -> #N/A | Q78: =IF(AND($K78="Bronze",ISNUMBER($L78),ISNUMBER($N78)),$L78,NA()) -> #N/A | R78: =IF(AND($K78="Silver",ISNUMBER($L78),ISNUMBER($O78)),$L78,NA()) -> 72779 | S78: =IF(AND($K78="Gold",ISNUMBER($L78),ISNUMBER($P78)),$L78,NA()) -> #N/A
J79: =CUBEMEMBER("ThisWorkbookDataModel","[Indian_Employee_Data].[Employee ID].&[Emp1050]") -> Emp1050 | K79: =CUBEMEMBER("ThisWorkbookDataModel",{"[Indian_Employee_Data].[Employee ID].&[Emp1050]","[Indian_Employee_Data].[Insurance tier].&[Gold]"}) -> Gold | L79: =CUBEVALUE("ThisWorkbookDataModel",$K79,L$29,Slicer_Department) -> 215780 | M79: =CUBEVALUE("ThisWorkbookDataModel",$K79,M$29,Slicer_Department) -> 6750 | N79: =IF(AND($K79="Bronze",ISNUMBER($L79),ISNUMBER($M79)),$M79,NA()) -> #N/A | O79: =IF(AND($K79="Silver",ISNUMBER($L79),ISNUMBER($M79)),$M79,NA()) -> #N/A | P79: =IF(AND($K79="Gold",ISNUMBER($L79),ISNUMBER($M79)),$M79,NA()) -> 6750 | Q79: =IF(AND($K79="Bronze",ISNUMBER($L79),ISNUMBER($N79)),$L79,NA()) -> #N/A | R79: =IF(AND($K79="Silver",ISNUMBER($L79),ISNUMBER($O79)),$L79,NA()) -> #N/A | S79: =IF(AND($K79="Gold",ISNUMBER($L79),ISNUMBER($P79)),$L79,NA()) -> 215780
J80: =CUBEMEMBER("ThisWorkbookDataModel","[Indian_Employee_Data].[Employee ID].&[Emp1051]") -> Emp1051 | K80: =CUBEMEMBER("ThisWorkbookDataModel",{"[Indian_Employee_Data].[Employee ID].&[Emp1051]","[Indian_Employee_Data].[Insurance tier].&[Gold]"}) -> Gold | L80: =CUBEVALUE("ThisWorkbookDataModel",$K80,L$29,Slicer_Department) -> 156954 | M80: =CUBEVALUE("ThisWorkbookDataModel",$K80,M$29,Slicer_Department) -> 6750 | N80: =IF(AND($K80="Bronze",ISNUMBER($L80),ISNUMBER($M80)),$M80,NA()) -> #N/A | O80: =IF(AND($K80="Silver",ISNUMBER($L80),ISNUMBER($M80)),$M80,NA()) -> #N/A | P80: =IF(AND($K80="Gold",ISNUMBER($L80),ISNUMBER($M80)),$M80,NA()) -> 6750 | Q80: =IF(AND($K80="Bronze",ISNUMBER($L80),ISNUMBER($N80)),$L80,NA()) -> #N/A | R80: =IF(AND($K80="Silver",ISNUMBER($L80),ISNUMBER($O80)),$L80,NA()) -> #N/A | S80: =IF(AND($K80="Gold",ISNUMBER($L80),ISNUMBER($P80)),$L80,NA()) -> 156954
J81: =CUBEMEMBER("ThisWorkbookDataModel","[Indian_Employee_Data].[Employee ID].&[Emp1052]") -> Emp1052 | K81: =CUBEMEMBER("ThisWorkbookDataModel",{"[Indian_Employee_Data].[Employee ID].&[Emp1052]","[Indian_Employee_Data].[Insurance tier].&[Gold]"}) -> Gold | L81: =CUBEVALUE("ThisWorkbookDataModel",$K81,L$29,Slicer_Department) -> 201737 | M81: =CUBEVALUE("ThisWorkbookDataModel",$K81,M$29,Slicer_Department) -> 6750 | N81: =IF(AND($K81="Bronze",ISNUMBER($L81),ISNUMBER($M81)),$M81,NA()) -> #N/A | O81: =IF(AND($K81="Silver",ISNUMBER($L81),ISNUMBER($M81)),$M81,NA()) -> #N/A | P81: =IF(AND($K81="Gold",ISNUMBER($L81),ISNUMBER($M81)),$M81,NA()) -> 6750 | Q81: =IF(AND($K81="Bronze",ISNUMBER($L81),ISNUMBER($N81)),$L81,NA()) -> #N/A | R81: =IF(AND($K81="Silver",ISNUMBER($L81),ISNUMBER($O81)),$L81,NA()) -> #N/A | S81: =IF(AND($K81="Gold",ISNUMBER($L81),ISNUMBER($P81)),$L81,NA()) -> 201737
J82: =CUBEMEMBER("ThisWorkbookDataModel","[Indian_Employee_Data].[Employee ID].&[Emp1053]") -> Emp1053 | K82: =CUBEMEMBER("ThisWorkbookDataModel",{"[Indian_Employee_Data].[Employee ID].&[Emp1053]","[Indian_Employee_Data].[Insurance tier].&[Gold]"}) -> Gold | L82: =CUBEVALUE("ThisWorkbookDataModel",$K82,L$29,Slicer_Department) -> 186367 | M82: =CUBEVALUE("ThisWorkbookDataModel",$K82,M$29,Slicer_Department) -> 9000 | N82: =IF(AND($K82="Bronze",ISNUMBER($L82),ISNUMBER($M82)),$M82,NA()) -> #N/A | O82: =IF(AND($K82="Silver",ISNUMBER($L82),ISNUMBER($M82)),$M82,NA()) -> #N/A | P82: =IF(AND($K82="Gold",ISNUMBER($L82),ISNUMBER($M82)),$M82,NA()) -> 9000 | Q82: =IF(AND($K82="Bronze",ISNUMBER($L82),ISNUMBER($N82)),$L82,NA()) -> #N/A | R82: =IF(AND($K82="Silver",ISNUMBER($L82),ISNUMBER($O82)),$L82,NA()) -> #N/A | S82: =IF(AND($K82="Gold",ISNUMBER($L82),ISNUMBER($P82)),$L82,NA()) -> 186367
J83: =CUBEMEMBER("ThisWorkbookDataModel","[Indian_Employee_Data].[Employee ID].&[Emp1054]") -> Emp1054 | K83: =CUBEMEMBER("ThisWorkbookDataModel",{"[Indian_Employee_Data].[Employee ID].&[Emp1054]","[Indian_Employee_Data].[Insurance tier].&[Gold]"}) -> Gold | L83: =CUBEVALUE("ThisWorkbookDataModel",$K83,L$29,Slicer_Department) -> 125577 | M83: =CUBEVALUE("ThisWorkbookDataModel",$K83,M$29,Slicer_Department) -> 9000 | N83: =IF(AND($K83="Bronze",ISNUMBER($L83),ISNUMBER($M83)),$M83,NA()) -> #N/A | O83: =IF(AND($K83="Silver",ISNUMBER($L83),ISNUMBER($M83)),$M83,NA()) -> #N/A | P83: =IF(AND($K83="Gold",ISNUMBER($L83),ISNUMBER($M83)),$M83,NA()) -> 9000 | Q83: =IF(AND($K83="Bronze",ISNUMBER($L83),ISNUMBER($N83)),$L83,NA()) -> #N/A | R83: =IF(AND($K83="Silver",ISNUMBER($L83),ISNUMBER($O83)),$L83,NA()) -> #N/A | S83: =IF(AND($K83="Gold",ISNUMBER($L83),ISNUMBER($P83)),$L83,NA()) -> 125577
J84: =CUBEMEMBER("ThisWorkbookDataModel","[Indian_Employee_Data].[Employee ID].&[Emp1055]") -> Emp1055 | K84: =CUBEMEMBER("ThisWorkbookDataModel",{"[Indian_Employee_Data].[Employee ID].&[Emp1055]","[Indian_Employee_Data].[Insurance tier].&[Gold]"}) -> Gold | L84: =CUBEVALUE("ThisWorkbookDataModel",$K84,L$29,Slicer_Department) -> 195156 | M84: =CUBEVALUE("ThisWorkbookDataModel",$K84,M$29,Slicer_Department) -> 9000 | N84: =IF(AND($K84="Bronze",ISNUMBER($L84),ISNUMBER($M84)),$M84,NA()) -> #N/A | O84: =IF(AND($K84="Silver",ISNUMBER($L84),ISNUMBER($M84)),$M84,NA()) -> #N/A | P84: =IF(AND($K84="Gold",ISNUMBER($L84),ISNUMBER($M84)),$M84,NA()) -> 9000 | Q84: =IF(AND($K84="Bronze",ISNUMBER($L84),ISNUMBER($N84)),$L84,NA()) -> #N/A | R84: =IF(AND($K84="Silver",ISNUMBER($L84),ISNUMBER($O84)),$L84,NA()) -> #N/A | S84: =IF(AND($K84="Gold",ISNUMBER($L84),ISNUMBER($P84)),$L84,NA()) -> 195156
J85: =CUBEMEMBER("ThisWorkbookDataModel","[Indian_Employee_Data].[Employee ID].&[Emp1056]") -> Emp1056 | K85: =CUBEMEMBER("ThisWorkbookDataModel",{"[Indian_Employee_Data].[Employee ID].&[Emp1056]","[Indian_Employee_Data].[Insurance tier].&[Bronze]"}) -> Bronze | L85: =CUBEVALUE("ThisWorkbookDataModel",$K85,L$29,Slicer_Department) -> 59598 | M85: =CUBEVALUE("ThisWorkbookDataModel",$K85,M$29,Slicer_Department) -> 1500 | N85: =IF(AND($K85="Bronze",ISNUMBER($L85),ISNUMBER($M85)),$M85,NA()) -> 1500 | O85: =IF(AND($K85="Silver",ISNUMBER($L85),ISNUMBER($M85)),$M85,NA()) -> #N/A | P85: =IF(AND($K85="Gold",ISNUMBER($L85),ISNUMBER($M85)),$M85,NA()) -> #N/A | Q85: =IF(AND($K85="Bronze",ISNUMBER($L85),ISNUMBER($N85)),$L85,NA()) -> 59598 | R85: =IF(AND($K85="Silver",ISNUMBER($L85),ISNUMBER($O85)),$L85,NA()) -> #N/A | S85: =IF(AND($K85="Gold",ISNUMBER($L85),ISNUMBER($P85)),$L85,NA()) -> #N/A
J86: =CUBEMEMBER("ThisWorkbookDataModel","[Indian_Employee_Data].[Employee ID].&[Emp1057]") -> Emp1057 | K86: =CUBEMEMBER("ThisWorkbookDataModel",{"[Indian_Employee_Data].[Employee ID].&[Emp1057]","[Indian_Employee_Data].[Insurance tier].&[Silver]"}) -> Silver | L86: =CUBEVALUE("ThisWorkbookDataModel",$K86,L$29,Slicer_Department) -> 74048 | M86: =CUBEVALUE("ThisWorkbookDataModel",$K86,M$29,Slicer_Department) -> 2800 | N86: =IF(AND($K86="Bronze",ISNUMBER($L86),ISNUMBER($M86)),$M86,NA()) -> #N/A | O86: =IF(AND($K86="Silver",ISNUMBER($L86),ISNUMBER($M86)),$M86,NA()) -> 2800 | P86: =IF(AND($K86="Gold",ISNUMBER($L86),ISNUMBER($M86)),$M86,NA()) -> #N/A | Q86: =IF(AND($K86="Bronze",ISNUMBER($L86),ISNUMBER($N86)),$L86,NA()) -> #N/A | R86: =IF(AND($K86="Silver",ISNUMBER($L86),ISNUMBER($O86)),$L86,NA()) -> 74048 | S86: =IF(AND($K86="Gold",ISNUMBER($L86),ISNUMBER($P86)),$L86,NA()) -> #N/A
J87: =CUBEMEMBER("ThisWorkbookDataModel","[Indian_Employee_Data].[Employee ID].&[Emp1058]") -> Emp1058 | K87: =CUBEMEMBER("ThisWorkbookDataModel",{"[Indian_Employee_Data].[Employee ID].&[Emp1058]","[Indian_Employee_Data].[Insurance tier].&[Bronze]"}) -> Bronze | L87: =CUBEVALUE("ThisWorkbookDataModel",$K87,L$29,Slicer_Department) -> 51160 | M87: =CUBEVALUE("ThisWorkbookDataModel",$K87,M$29,Slicer_Department) -> 1500 | N87: =IF(AND($K87="Bronze",ISNUMBER($L87),ISNUMBER($M87)),$M87,NA()) -> 1500 | O87: =IF(AND($K87="Silver",ISNUMBER($L87),ISNUMBER($M87)),$M87,NA()) -> #N/A | P87: =IF(AND($K87="Gold",ISNUMBER($L87),ISNUMBER($M87)),$M87,NA()) -> #N/A | Q87: =IF(AND($K87="Bronze",ISNUMBER($L87),ISNUMBER($N87)),$L87,NA()) -> 51160 | R87: =IF(AND($K87="Silver",ISNUMBER($L87),ISNUMBER($O87)),$L87,NA()) -> #N/A | S87: =IF(AND($K87="Gold",ISNUMBER($L87),ISNUMBER($P87)),$L87,NA()) -> #N/A
J88: =CUBEMEMBER("ThisWorkbookDataModel","[Indian_Employee_Data].[Employee ID].&[Emp1059]") -> Emp1059 | K88: =CUBEMEMBER("ThisWorkbookDataModel",{"[Indian_Employee_Data].[Employee ID].&[Emp1059]","[Indian_Employee_Data].[Insurance tier].&[Silver]"}) -> Silver | L88: =CUBEVALUE("ThisWorkbookDataModel",$K88,L$29,Slicer_Department) -> 88833 | M88: =CUBEVALUE("ThisWorkbookDataModel",$K88,M$29,Slicer_Department) -> 4200 | N88: =IF(AND($K88="Bronze",ISNUMBER($L88),ISNUMBER($M88)),$M88,NA()) -> #N/A | O88: =IF(AND($K88="Silver",ISNUMBER($L88),ISNUMBER($M88)),$M88,NA()) -> 4200 | P88: =IF(AND($K88="Gold",ISNUMBER($L88),ISNUMBER($M88)),$M88,NA()) -> #N/A | Q88: =IF(AND($K88="Bronze",ISNUMBER($L88),ISNUMBER($N88)),$L88,NA()) -> #N/A | R88: =IF(AND($K88="Silver",ISNUMBER($L88),ISNUMBER($O88)),$L88,NA()) -> 88833 | S88: =IF(AND($K88="Gold",ISNUMBER($L88),ISNUMBER($P88)),$L88,NA()) -> #N/A
J89: =CUBEMEMBER("ThisWorkbookDataModel","[Indian_Employee_Data].[Employee ID].&[Emp1060]") -> Emp1060 | K89: =CUBEMEMBER("ThisWorkbookDataModel",{"[Indian_Employee_Data].[Employee ID].&[Emp1060]","[Indian_Employee_Data].[Insurance tier].&[Silver]"}) -> Silver | L89: =CUBEVALUE("ThisWorkbookDataModel",$K89,L$29,Slicer_Department) -> 96585 | M89: =CUBEVALUE("ThisWorkbookDataModel",$K89,M$29,Slicer_Department) -> 2800 | N89: =IF(AND($K89="Bronze",ISNUMBER($L89),ISNUMBER($M89)),$M89,NA()) -> #N/A | O89: =IF(AND($K89="Silver",ISNUMBER($L89),ISNUMBER($M89)),$M89,NA()) -> 2800 | P89: =IF(AND($K89="Gold",ISNUMBER($L89),ISNUMBER($M89)),$M89,NA()) -> #N/A | Q89: =IF(AND($K89="Bronze",ISNUMBER($L89),ISNUMBER($N89)),$L89,NA()) -> #N/A | R89: =IF(AND($K89="Silver",ISNUMBER($L89),ISNUMBER($O89)),$L89,NA()) -> 96585 | S89: =IF(AND($K89="Gold",ISNUMBER($L89),ISNUMBER($P89)),$L89,NA()) -> #N/A
J90: =CUBEMEMBER("ThisWorkbookDataModel","[Indian_Employee_Data].[Employee ID].&[Emp1061]") -> Emp1061 | K90: =CUBEMEMBER("ThisWorkbookDataModel",{"[Indian_Employee_Data].[Employee ID].&[Emp1061]","[Indian_Employee_Data].[Insurance tier].&[Silver]"}) -> Silver | L90: =CUBEVALUE("ThisWorkbookDataModel",$K90,L$29,Slicer_Department) -> 82509 | M90: =CUBEVALUE("ThisWorkbookDataModel",$K90,M$29,Slicer_Department) -> 4200 | N90: =IF(AND($K90="Bronze",ISNUMBER($L90),ISNUMBER($M90)),$M90,NA()) -> #N/A | O90: =IF(AND($K90="Silver",ISNUMBER($L90),ISNUMBER($M90)),$M90,NA()) -> 4200 | P90: =IF(AND($K90="Gold",ISNUMBER($L90),ISNUMBER($M90)),$M90,NA()) -> #N/A | Q90: =IF(AND($K90="Bronze",ISNUMBER($L90),ISNUMBER($N90)),$L90,NA()) -> #N/A | R90: =IF(AND($K90="Silver",ISNUMBER($L90),ISNUMBER($O90)),$L90,NA()) -> 82509 | S90: =IF(AND($K90="Gold",ISNUMBER($L90),ISNUMBER($P90)),$L90,NA()) -> #N/A
J91: =CUBEMEMBER("ThisWorkbookDataModel","[Indian_Employee_Data].[Employee ID].&[Emp1062]") -> Emp1062 | K91: =CUBEMEMBER("ThisWorkbookDataModel",{"[Indian_Employee_Data].[Employee ID].&[Emp1062]","[Indian_Employee_Data].[Insurance tier].&[Gold]"}) -> Gold | L91: =CUBEVALUE("ThisWorkbookDataModel",$K91,L$29,Slicer_Department) -> 168798 | M91: =CUBEVALUE("ThisWorkbookDataModel",$K91,M$29,Slicer_Department) -> 9000 | N91: =IF(AND($K91="Bronze",ISNUMBER($L91),ISNUMBER($M91)),$M91,NA()) -> #N/A | O91: =IF(AND($K91="Silver",ISNUMBER($L91),ISNUMBER($M91)),$M91,NA()) -> #N/A | P91: =IF(AND($K91="Gold",ISNUMBER($L91),ISNUMBER($M91)),$M91,NA()) -> 9000 | Q91: =IF(AND($K91="Bronze",ISNUMBER($L91),ISNUMBER($N91)),$L91,NA()) -> #N/A | R91: =IF(AND($K91="Silver",ISNUMBER($L91),ISNUMBER($O91)),$L91,NA()) -> #N/A | S91: =IF(AND($K91="Gold",ISNUMBER($L91),ISNUMBER($P91)),$L91,NA()) -> 168798
J92: =CUBEMEMBER("ThisWorkbookDataModel","[Indian_Employee_Data].[Employee ID].&[Emp1063]") -> Emp1063 | K92: =CUBEMEMBER("ThisWorkbookDataModel",{"[Indian_Employee_Data].[Employee ID].&[Emp1063]","[Indian_Employee_Data].[Insurance tier].&[Silver]"}) -> Silver | L92: =CUBEVALUE("ThisWorkbookDataModel",$K92,L$29,Slicer_Department) -> 92631 | M92: =CUBEVALUE("ThisWorkbookDataModel",$K92,M$29,Slicer_Department) -> 2800 | N92: =IF(AND($K92="Bronze",ISNUMBER($L92),ISNUMBER($M92)),$M92,NA()) -> #N/A | O92: =IF(AND($K92="Silver",ISNUMBER($L92),ISNUMBER($M92)),$M92,NA()) -> 2800 | P92: =IF(AND($K92="Gold",ISNUMBER($L92),ISNUMBER($M92)),$M92,NA()) -> #N/A | Q92: =IF(AND($K92="Bronze",ISNUMBER($L92),ISNUMBER($N92)),$L92,NA()) -> #N/A | R92: =IF(AND($K92="Silver",ISNUMBER($L92),ISNUMBER($O92)),$L92,NA()) -> 92631 | S92: =IF(AND($K92="Gold",ISNUMBER($L92),ISNUMBER($P92)),$L92,NA()) -> #N/A
J93: =CUBEMEMBER("ThisWorkbookDataModel","[Indian_Employee_Data].[Employee ID].&[Emp1064]") -> Emp1064 | K93: =CUBEMEMBER("ThisWorkbookDataModel",{"[Indian_Employee_Data].[Employee ID].&[Emp1064]","[Indian_Employee_Data].[Insurance tier].&[Silver]"}) -> Silver | L93: =CUBEVALUE("ThisWorkbookDataModel",$K93,L$29,Slicer_Department) -> 83614 | M93: =CUBEVALUE("ThisWorkbookDataModel",$K93,M$29,Slicer_Department) -> 2800 | N93: =IF(AND($K93="Bronze",ISNUMBER($L93),ISNUMBER($M93)),$M93,NA()) -> #N/A | O93: =IF(AND($K93="Silver",ISNUMBER($L93),ISNUMBER($M93)),$M93,NA()) -> 2800 | P93: =IF(AND($K93="Gold",ISNUMBER($L93),ISNUMBER($M93)),$M93,NA()) -> #N/A | Q93: =IF(AND($K93="Bronze",ISNUMBER($L93),ISNUMBER($N93)),$L93,NA()) -> #N/A | R93: =IF(AND($K93="Silver",ISNUMBER($L93),ISNUMBER($O93)),$L93,NA()) -> 83614 | S93: =IF(AND($K93="Gold",ISNUMBER($L93),ISNUMBER($P93)),$L93,NA()) -> #N/A
J94: =CUBEMEMBER("ThisWorkbookDataModel","[Indian_Employee_Data].[Employee ID].&[Emp1065]") -> Emp1065 | K94: =CUBEMEMBER("ThisWorkbookDataModel",{"[Indian_Employee_Data].[Employee ID].&[Emp1065]","[Indian_Employee_Data].[Insurance tier].&[Silver]"}) -> Silver | L94: =CUBEVALUE("ThisWorkbookDataModel",$K94,L$29,Slicer_Department) -> 117311 | M94: =CUBEVALUE("ThisWorkbookDataModel",$K94,M$29,Slicer_Department) -> 2800 | N94: =IF(AND($K94="Bronze",ISNUMBER($L94),ISNUMBER($M94)),$M94,NA()) -> #N/A | O94: =IF(AND($K94="Silver",ISNUMBER($L94),ISNUMBER($M94)),$M94,NA()) -> 2800 | P94: =IF(AND($K94="Gold",ISNUMBER($L94),ISNUMBER($M94)),$M94,NA()) -> #N/A | Q94: =IF(AND($K94="Bronze",ISNUMBER($L94),ISNUMBER($N94)),$L94,NA()) -> #N/A | R94: =IF(AND($K94="Silver",ISNUMBER($L94),ISNUMBER($O94)),$L94,NA()) -> 117311 | S94: =IF(AND($K94="Gold",ISNUMBER($L94),ISNUMBER($P94)),$L94,NA()) -> #N/A
J95: =CUBEMEMBER("ThisWorkbookDataModel","[Indian_Employee_Data].[Employee ID].&[Emp1066]") -> Emp1066 | K95: =CUBEMEMBER("ThisWorkbookDataModel",{"[Indian_Employee_Data].[Employee ID].&[Emp1066]","[Indian_Employee_Data].[Insurance tier].&[Silver]"}) -> Silver | L95: =CUBEVALUE("ThisWorkbookDataModel",$K95,L$29,Slicer_Department) -> 67351 | M95: =CUBEVALUE("ThisWorkbookDataModel",$K95,M$29,Slicer_Department) -> 4200 | N95: =IF(AND($K95="Bronze",ISNUMBER($L95),ISNUMBER($M95)),$M95,NA()) -> #N/A | O95: =IF(AND($K95="Silver",ISNUMBER($L95),ISNUMBER($M95)),$M95,NA()) -> 4200 | P95: =IF(AND($K95="Gold",ISNUMBER($L95),ISNUMBER($M95)),$M95,NA()) -> #N/A | Q95: =IF(AND($K95="Bronze",ISNUMBER($L95),ISNUMBER($N95)),$L95,NA()) -> #N/A | R95: =IF(AND($K95="Silver",ISNUMBER($L95),ISNUMBER($O95)),$L95,NA()) -> 67351 | S95: =IF(AND($K95="Gold",ISNUMBER($L95),ISNUMBER($P95)),$L95,NA()) -> #N/A
J96: =CUBEMEMBER("ThisWorkbookDataModel","[Indian_Employee_Data].[Employee ID].&[Emp1067]") -> Emp1067 | K96: =CUBEMEMBER("ThisWorkbookDataModel",{"[Indian_Employee_Data].[Employee ID].&[Emp1067]","[Indian_Employee_Data].[Insurance tier].&[Gold]"}) -> Gold | L96: =CUBEVALUE("ThisWorkbookDataModel",$K96,L$29,Slicer_Department) -> 162733 | M96: =CUBEVALUE("ThisWorkbookDataModel",$K96,M$29,Slicer_Department) -> 9000 | N96: =IF(AND($K96="Bronze",ISNUMBER($L96),ISNUMBER($M96)),$M96,NA()) -> #N/A | O96: =IF(AND($K96="Silver",ISNUMBER($L96),ISNUMBER($M96)),$M96,NA()) -> #N/A | P96: =IF(AND($K96="Gold",ISNUMBER($L96),ISNUMBER($M96)),$M96,NA()) -> 9000 | Q96: =IF(AND($K96="Bronze",ISNUMBER($L96),ISNUMBER($N96)),$L96,NA()) -> #N/A | R96: =IF(AND($K96="Silver",ISNUMBER($L96),ISNUMBER($O96)),$L96,NA()) -> #N/A | S96: =IF(AND($K96="Gold",ISNUMBER($L96),ISNUMBER($P96)),$L96,NA()) -> 162733
J97: =CUBEMEMBER("ThisWorkbookDataModel","[Indian_Employee_Data].[Employee ID].&[Emp1068]") -> Emp1068 | K97: =CUBEMEMBER("ThisWorkbookDataModel",{"[Indian_Employee_Data].[Employee ID].&[Emp1068]","[Indian_Employee_Data].[Insurance tier].&[Bronze]"}) -> Bronze | L97: =CUBEVALUE("ThisWorkbookDataModel",$K97,L$29,Slicer_Department) -> 57167 | M97: =CUBEVALUE("ThisWorkbookDataModel",$K97,M$29,Slicer_Department) -> 1500 | N97: =IF(AND($K97="Bronze",ISNUMBER($L97),ISNUMBER($M97)),$M97,NA()) -> 1500 | O97: =IF(AND($K97="Silver",ISNUMBER($L97),ISNUMBER($M97)),$M97,NA()) -> #N/A | P97: =IF(AND($K97="Gold",ISNUMBER($L97),ISNUMBER($M97)),$M97,NA()) -> #N/A | Q97: =IF(AND($K97="Bronze",ISNUMBER($L97),ISNUMBER($N97)),$L97,NA()) -> 57167 | R97: =IF(AND($K97="Silver",ISNUMBER($L97),ISNUMBER($O97)),$L97,NA()) -> #N/A | S97: =IF(AND($K97="Gold",ISNUMBER($L97),ISNUMBER($P97)),$L97,NA()) -> #N/A
J98: =CUBEMEMBER("ThisWorkbookDataModel","[Indian_Employee_Data].[Employee ID].&[Emp1069]") -> Emp1069 | K98: =CUBEMEMBER("ThisWorkbookDataModel",{"[Indian_Employee_Data].[Employee ID].&[Emp1069]","[Indian_Employee_Data].[Insurance tier].&[Gold]"}) -> Gold | L98: =CUBEVALUE("ThisWorkbookDataModel",$K98,L$29,Slicer_Department) -> 227531 | M98: =CUBEVALUE("ThisWorkbookDataModel",$K98,M$29,Slicer_Department) -> 6750 | N98: =IF(AND($K98="Bronze",ISNUMBER($L98),ISNUMBER($M98)),$M98,NA()) -> #N/A | O98: =IF(AND($K98="Silver",ISNUMBER($L98),ISNUMBER($M98)),$M98,NA()) -> #N/A | P98: =IF(AND($K98="Gold",ISNUMBER($L98),ISNUMBER($M98)),$M98,NA()) -> 6750 | Q98: =IF(AND($K98="Bronze",ISNUMBER($L98),ISNUMBER($N98)),$L98,NA()) -> #N/A | R98: =IF(AND($K98="Silver",ISNUMBER($L98),ISNUMBER($O98)),$L98,NA()) -> #N/A | S98: =IF(AND($K98="Gold",ISNUMBER($L98),ISNUMBER($P98)),$L98,NA()) -> 227531
J99: =CUBEMEMBER("ThisWorkbookDataModel","[Indian_Employee_Data].[Employee ID].&[Emp1070]") -> Emp1070 | K99: =CUBEMEMBER("ThisWorkbookDataModel",{"[Indian_Employee_Data].[Employee ID].&[Emp1070]","[Indian_Employee_Data].[Insurance tier].&[Gold]"}) -> Gold | L99: =CUBEVALUE("ThisWorkbookDataModel",$K99,L$29,Slicer_Department) -> 156359 | M99: =CUBEVALUE("ThisWorkbookDataModel",$K99,M$29,Slicer_Department) -> 9000 | N99: =IF(AND($K99="Bronze",ISNUMBER($L99),ISNUMBER($M99)),$M99,NA()) -> #N/A | O99: =IF(AND($K99="Silver",ISNUMBER($L99),ISNUMBER($M99)),$M99,NA()) -> #N/A | P99: =IF(AND($K99="Gold",ISNUMBER($L99),ISNUMBER($M99)),$M99,NA()) -> 9000 | Q99: =IF(AND($K99="Bronze",ISNUMBER($L99),ISNUMBER($N99)),$L99,NA()) -> #N/A | R99: =IF(AND($K99="Silver",ISNUMBER($L99),ISNUMBER($O99)),$L99,NA()) -> #N/A | S99: =IF(AND($K99="Gold",ISNUMBER($L99),ISNUMBER($P99)),$L99,NA()) -> 156359
J100: =CUBEMEMBER("ThisWorkbookDataModel","[Indian_Employee_Data].[Employee ID].&[Emp1071]") -> Emp1071 | K100: =CUBEMEMBER("ThisWorkbookDataModel",{"[Indian_Employee_Data].[Employee ID].&[Emp1071]","[Indian_Employee_Data].[Insurance tier].&[Silver]"}) -> Silver | L100: =CUBEVALUE("ThisWorkbookDataModel",$K100,L$29,Slicer_Department) -> 74354 | M100: =CUBEVALUE("ThisWorkbookDataModel",$K100,M$29,Slicer_Department) -> 4200 | N100: =IF(AND($K100="Bronze",ISNUMBER($L100),ISNUMBER($M100)),$M100,NA()) -> #N/A | O100: =IF(AND($K100="Silver",ISNUMBER($L100),ISNUMBER($M100)),$M100,NA()) -> 4200 | P100: =IF(AND($K100="Gold",ISNUMBER($L100),ISNUMBER($M100)),$M100,NA()) -> #N/A | Q100: =IF(AND($K100="Bronze",ISNUMBER($L100),ISNUMBER($N100)),$L100,NA()) -> #N/A | R100: =IF(AND($K100="Silver",ISNUMBER($L100),ISNUMBER($O100)),$L100,NA()) -> 74354 | S100: =IF(AND($K100="Gold",ISNUMBER($L100),ISNUMBER($P100)),$L100,NA()) -> #N/A
J101: =CUBEMEMBER("ThisWorkbookDataModel","[Indian_Employee_Data].[Employee ID].&[Emp1072]") -> Emp1072 | K101: =CUBEMEMBER("ThisWorkbookDataModel",{"[Indian_Employee_Data].[Employee ID].&[Emp1072]","[Indian_Employee_Data].[Insurance tier].&[Bronze]"}) -> Bronze | L101: =CUBEVALUE("ThisWorkbookDataModel",$K101,L$29,Slicer_Department) -> 37393 | M101: =CUBEVALUE("ThisWorkbookDataModel",$K101,M$29,Slicer_Department) -> 1500 | N101: =IF(AND($K101="Bronze",ISNUMBER($L101),ISNUMBER($M101)),$M101,NA()) -> 1500 | O101: =IF(AND($K101="Silver",ISNUMBER($L101),ISNUMBER($M101)),$M101,NA()) -> #N/A | P101: =IF(AND($K101="Gold",ISNUMBER($L101),ISNUMBER($M101)),$M101,NA()) -> #N/A | Q101: =IF(AND($K101="Bronze",ISNUMBER($L101),ISNUMBER($N101)),$L101,NA()) -> 37393 | R101: =IF(AND($K101="Silver",ISNUMBER($L101),ISNUMBER($O101)),$L101,NA()) -> #N/A | S101: =IF(AND($K101="Gold",ISNUMBER($L101),ISNUMBER($P101)),$L101,NA()) -> #N/A
J102: =CUBEMEMBER("ThisWorkbookDataModel","[Indian_Employee_Data].[Employee ID].&[Emp1073]") -> Emp1073 | K102: =CUBEMEMBER("ThisWorkbookDataModel",{"[Indian_Employee_Data].[Employee ID].&[Emp1073]","[Indian_Employee_Data].[Insurance tier].&[Gold]"}) -> Gold | L102: =CUBEVALUE("ThisWorkbookDataModel",$K102,L$29,Slicer_Department) -> 165710 | M102: =CUBEVALUE("ThisWorkbookDataModel",$K102,M$29,Slicer_Department) -> 9000 | N102: =IF(AND($K102="Bronze",ISNUMBER($L102),ISNUMBER($M102)),$M102,NA()) -> #N/A | O102: =IF(AND($K102="Silver",ISNUMBER($L102),ISNUMBER($M102)),$M102,NA()) -> #N/A | P102: =IF(AND($K102="Gold",ISNUMBER($L102),ISNUMBER($M102)),$M102,NA()) -> 9000 | Q102: =IF(AND($K102="Bronze",ISNUMBER($L102),ISNUMBER($N102)),$L102,NA()) -> #N/A | R102: =IF(AND($K102="Silver",ISNUMBER($L102),ISNUMBER($O102)),$L102,NA()) -> #N/A | S102: =IF(AND($K102="Gold",ISNUMBER($L102),ISNUMBER($P102)),$L102,NA()) -> 165710
J103: =CUBEMEMBER("ThisWorkbookDataModel","[Indian_Employee_Data].[Employee ID].&[Emp1074]") -> Emp1074 | K103: =CUBEMEMBER("ThisWorkbookDataModel",{"[Indian_Employee_Data].[Employee ID].&[Emp1074]","[Indian_Employee_Data].[Insurance tier].&[Gold]"}) -> Gold | L103: =CUBEVALUE("ThisWorkbookDataModel",$K103,L$29,Slicer_Department) -> 143764 | M103: =CUBEVALUE("ThisWorkbookDataModel",$K103,M$29,Slicer_Department) -> 6750 | N103: =IF(AND($K103="Bronze",ISNUMBER($L103),ISNUMBER($M103)),$M103,NA()) -> #N/A | O103: =IF(AND($K103="Silver",ISNUMBER($L103),ISNUMBER($M103)),$M103,NA()) -> #N/A | P103: =IF(AND($K103="Gold",ISNUMBER($L103),ISNUMBER($M103)),$M103,NA()) -> 6750 | Q103: =IF(AND($K103="Bronze",ISNUMBER($L103),ISNUMBER($N103)),$L103,NA()) -> #N/A | R103: =IF(AND($K103="Silver",ISNUMBER($L103),ISNUMBER($O103)),$L103,NA()) -> #N/A | S103: =IF(AND($K103="Gold",ISNUMBER($L103),ISNUMBER($P103)),$L103,NA()) -> 143764
J104: =CUBEMEMBER("ThisWorkbookDataModel","[Indian_Employee_Data].[Employee ID].&[Emp1075]") -> Emp1075 | K104: =CUBEMEMBER("ThisWorkbookDataModel",{"[Indian_Employee_Data].[Employee ID].&[Emp1075]","[Indian_Employee_Data].[Insurance tier].&[Gold]"}) -> Gold | L104: =CUBEVALUE("ThisWorkbookDataModel",$K104,L$29,Slicer_Department) -> 147856 | M104: =CUBEVALUE("ThisWorkbookDataModel",$K104,M$29,Slicer_Department) -> 9000 | N104: =IF(AND($K104="Bronze",ISNUMBER($L104),ISNUMBER($M104)),$M104,NA()) -> #N/A | O104: =IF(AND($K104="Silver",ISNUMBER($L104),ISNUMBER($M104)),$M104,NA()) -> #N/A | P104: =IF(AND($K104="Gold",ISNUMBER($L104),ISNUMBER($M104)),$M104,NA()) -> 9000 | Q104: =IF(AND($K104="Bronze",ISNUMBER($L104),ISNUMBER($N104)),$L104,NA()) -> #N/A | R104: =IF(AND($K104="Silver",ISNUMBER($L104),ISNUMBER($O104)),$L104,NA()) -> #N/A | S104: =IF(AND($K104="Gold",ISNUMBER($L104),ISNUMBER($P104)),$L104,NA()) -> 147856
J105: =CUBEMEMBER("ThisWorkbookDataModel","[Indian_Employee_Data].[Employee ID].&[Emp1076]") -> Emp1076 | K105: =CUBEMEMBER("ThisWorkbookDataModel",{"[Indian_Employee_Data].[Employee ID].&[Emp1076]","[Indian_Employee_Data].[Insurance tier].&[Bronze]"}) -> Bronze | L105: =CUBEVALUE("ThisWorkbookDataModel",$K105,L$29,Slicer_Department) -> 156159 | M105: =CUBEVALUE("ThisWorkbookDataModel",$K105,M$29,Slicer_Department) -> 9500 | N105: =IF(AND($K105="Bronze",ISNUMBER($L105),ISNUMBER($M105)),$M105,NA()) -> 9500 | O105: =IF(AND($K105="Silver",ISNUMBER($L105),ISNUMBER($M105)),$M105,NA()) -> #N/A | P105: =IF(AND($K105="Gold",ISNUMBER($L105),ISNUMBER($M105)),$M105,NA()) -> #N/A | Q105: =IF(AND($K105="Bronze",ISNUMBER($L105),ISNUMBER($N105)),$L105,NA()) -> 156159 | R105: =IF(AND($K105="Silver",ISNUMBER($L105),ISNUMBER($O105)),$L105,NA()) -> #N/A | S105: =IF(AND($K105="Gold",ISNUMBER($L105),ISNUMBER($P105)),$L105,NA()) -> #N/A
J106: =CUBEMEMBER("ThisWorkbookDataModel","[Indian_Employee_Data].[Employee ID].&[Emp1078]") -> Emp1078 | K106: =CUBEMEMBER("ThisWorkbookDataModel",{"[Indian_Employee_Data].[Employee ID].&[Emp1078]","[Indian_Employee_Data].[Insurance tier].&[Silver]"}) -> Silver | L106: =CUBEVALUE("ThisWorkbookDataModel",$K106,L$29,Slicer_Department) -> 92840 | M106: =CUBEVALUE("ThisWorkbookDataModel",$K106,M$29,Slicer_Department) -> 4200 | N106: =IF(AND($K106="Bronze",ISNUMBER($L106),ISNUMBER($M106)),$M106,NA()) -> #N/A | O106: =IF(AND($K106="Silver",ISNUMBER($L106),ISNUMBER($M106)),$M106,NA()) -> 4200 | P106: =IF(AND($K106="Gold",ISNUMBER($L106),ISNUMBER($M106)),$M106,NA()) -> #N/A | Q106: =IF(AND($K106="Bronze",ISNUMBER($L106),ISNUMBER($N106)),$L106,NA()) -> #N/A | R106: =IF(AND($K106="Silver",ISNUMBER($L106),ISNUMBER($O106)),$L106,NA()) -> 92840 | S106: =IF(AND($K106="Gold",ISNUMBER($L106),ISNUMBER($P106)),$L106,NA()) -> #N/A
...

Sheet Validation
A1: Gender | B1: Location | C1: Insurance tier | D1: Corporate Benefit Plan | E1: Department
A2: Female | B2: Hyderabad | C2: Gold | D2: Family Floater | E2: Sales
A3: Male | B3: Bengaluru | C3: Bronze | D3: Parents Included | E3: Operations
A4: Transgender | B4: Noida | C4: Silver | D4: Individual | E4: Tech
B5: Gurugram | E5: Finance
E6: HR
